Workbook

Sheet Summary
A1: Party Name | B1: INOX AIR PRODUCTS PRIVATE LIMITED | C1: Date Tolerance | D1: 0 - 15
A2: Reconciliation Period | B2: 01-Apr-2025 to 31-Mar-2026 | C2: TDS Percentage | D2: 0.0 - 10.0
A3: Statement Type | B3: Ledger | C3: Amount Tolerance | D3: 1.0 Rs
A4: Party Type | B4: Vendor
A5: Reconciliation Date | B5: 03-Aug-26 04:10 PM
A7: Reconciliation Statement
A8: Particulars | B8: Annexure | C8: Amount | D8: No. of Entries | E8: Action Required
A9: Closing Balance Difference | C9: =SUM(C10:C11) -> 64448.34 | D9: =SUM(D10:D11) -> 2
A10: Closing Balance as per Company | C10: =-(SUMIFS(Reconciliation!L:L,Reconciliation!D:D,A10,Reconciliation!F:F,"ledger") +SUMIFS(Reconciliation!S:S,Reconciliation!D:D,A10,Reconciliation!M:M,"ledger")) -> -152786.08 | D10: =COUNTIFS(Reconciliation!D:D,A10,Reconciliation!F:F,"ledger") +COUNTIFS(Reconciliation!D:D,A10,Reconciliation!M:M,"ledger") -> 1
A11: Closing Balance as per Party | C11: =-(SUMIFS(Reconciliation!L:L,Reconciliation!D:D,A11,Reconciliation!F:F,"ledger") +SUMIFS(Reconciliation!S:S,Reconciliation!D:D,A11,Reconciliation!M:M,"ledger")) -> 217234.42 | D11: =COUNTIFS(Reconciliation!D:D,A11,Reconciliation!F:F,"ledger") +COUNTIFS(Reconciliation!D:D,A11,Reconciliation!M:M,"ledger") -> 1
A13: Invoice Difference | C13: =SUM(C14:C14) -> 204357.32 | D13: =SUM(D14:D14) -> 3
A14: Invoice not booked by Company | B14: 1 | C14: =SUMIFS(Reconciliation!L:L,Reconciliation!D:D,A14,Reconciliation!F:F,"ledger") +SUMIFS(Reconciliation!S:S,Reconciliation!D:D,A14,Reconciliation!M:M,"ledger") -> 204357.32 | D14: =COUNTIFS(Reconciliation!D:D,A14,Reconciliation!F:F,"ledger") +COUNTIFS(Reconciliation!D:D,A14,Reconciliation!M:M,"ledger") -> 3 | E14: Vendor to provide the invoice copies
A15: Debit Note / Credit Note Difference | C15: =SUM(C16:C16) -> 17174.51 | D15: =SUM(D16:D16) -> 1
A16: Debit Note not booked by Party | B16: 33 | C16: =SUMIFS(Reconciliation!L:L,Reconciliation!D:D,A16,Reconciliation!F:F,"ledger") +SUMIFS(Reconciliation!S:S,Reconciliation!D:D,A16,Reconciliation!M:M,"ledger") -> 17174.51 | D16: =COUNTIFS(Reconciliation!D:D,A16,Reconciliation!F:F,"ledger") +COUNTIFS(Reconciliation!D:D,A16,Reconciliation!M:M,"ledger") -> 1 | E16: Vendor to book the Credit Note for Shortage / Deduction / Rate Difference etc
A17: Other Differences | C17: =SUM(C18:C19) -> -23983.59 | D17: =SUM(D18:D19) -> 29
A18: Other entry not booked by Company | B18: 74 | C18: =SUMIFS(Reconciliation!L:L,Reconciliation!D:D,A18,Reconciliation!F:F,"ledger") +SUMIFS(Reconciliation!S:S,Reconciliation!D:D,A18,Reconciliation!M:M,"ledger") -> -6809.08 | D18: =COUNTIFS(Reconciliation!D:D,A18,Reconciliation!F:F,"ledger") +COUNTIFS(Reconciliation!D:D,A18,Reconciliation!M:M,"ledger") -> 28
A19: Other entry not booked by Party | B19: 79 | C19: =SUMIFS(Reconciliation!L:L,Reconciliation!D:D,A19,Reconciliation!F:F,"ledger") +SUMIFS(Reconciliation!S:S,Reconciliation!D:D,A19,Reconciliation!M:M,"ledger") -> -17174.51 | D19: =COUNTIFS(Reconciliation!D:D,A19,Reconciliation!F:F,"ledger") +COUNTIFS(Reconciliation!D:D,A19,Reconciliation!M:M,"ledger") -> 1
A20: TDS / TCS Difference | C20: =SUM(C21:C22) -> 6799.99 | D20: =SUM(D21:D22) -> 15
A21: TDS Booked by Company | B21: 94 | C21: =SUMIFS(Reconciliation!T:T,Reconciliation!D:D,A21) -SUMIFS(Reconciliation!T:T,Reconciliation!D:D,A21,Reconciliation!F:F,"Brought forward",Reconciliation!M:M,"Brought forward") -SUMIFS(Reconciliation!T:T,Reconciliation!D:D,A21,Reconciliation!F:F,"Brought forward",Reconciliation!I:I,"tds") -SUMIFS(Reconciliation!T:T,Reconciliation!D:D,A21,Reconciliation!M:M,"Brought forward",Reconciliation!P:P,"tds") -> 7800 | D21: =COUNTIFS(Reconciliation!D:D,A21) -COUNTIFS(Reconciliation!D:D,A21,Reconciliation!F:F,"Brought forward",Reconciliation!M:M,"Brought forward") -COUNTIFS(Reconciliation!D:D,A21,Reconciliation!F:F,"Brought forward",Reconciliation!I:I,"tds") -COUNTIFS(Reconciliation!D:D,A21,Reconciliation!M:M,"Brought forward",Reconciliation!P:P,"tds") -> 14 | E21: Vendor to book the TDS entries
A22: TDS Booked by Party | B22: 94 | C22: =SUMIFS(Reconciliation!T:T,Reconciliation!D:D,A22) -SUMIFS(Reconciliation!T:T,Reconciliation!D:D,A22,Reconciliation!F:F,"Brought forward",Reconciliation!M:M,"Brought forward") -SUMIFS(Reconciliation!T:T,Reconciliation!D:D,A22,Reconciliation!F:F,"Brought forward",Reconciliation!I:I,"tds") -SUMIFS(Reconciliation!T:T,Reconciliation!D:D,A22,Reconciliation!M:M,"Brought forward",Reconciliation!P:P,"tds") -> -1000.01 | D22: =COUNTIFS(Reconciliation!D:D,A22) -COUNTIFS(Reconciliation!D:D,A22,Reconciliation!F:F,"Brought forward",Reconciliation!M:M,"Brought forward") -COUNTIFS(Reconciliation!D:D,A22,Reconciliation!F:F,"Brought forward",Reconciliation!I:I,"tds") -COUNTIFS(Reconciliation!D:D,A22,Reconciliation!M:M,"Brought forward",Reconciliation!P:P,"tds") -> 1 | E22: Vendor to book the TDS entries
A23: Write Off / Rounding Off | C23: =SUM(C24:C24) -> 23.17 | D23: =SUM(D24:D24) -> 63
A24: Write off / Rounding off | C24: =SUMIFS(Reconciliation!T:T,Reconciliation!D:D,A24) -SUMIFS(Reconciliation!T:T,Reconciliation!D:D,A24,Reconciliation!F:F,"Brought forward",Reconciliation!M:M,"Brought forward") -SUMIFS(Reconciliation!T:T,Reconciliation!D:D,A24,Reconciliation!F:F,"Brought forward",Reconciliation!I:I,"tds") -SUMIFS(Reconciliation!T:T,Reconciliation!D:D,A24,Reconciliation!M:M,"Brought forward",Reconciliation!P:P,"tds") -> 23.17 | D24: =COUNTIFS(Reconciliation!D:D,A24) -COUNTIFS(Reconciliation!D:D,A24,Reconciliation!F:F,"Brought forward",Reconciliation!M:M,"Brought forward") -COUNTIFS(Reconciliation!D:D,A24,Reconciliation!F:F,"Brought forward",Reconciliation!I:I,"tds") -COUNTIFS(Reconciliation!D:D,A24,Reconciliation!M:M,"Brought forward",Reconciliation!P:P,"tds") -> 63 | E24: No Action Required
A25: Reversal Entries | C25: =SUM(C26:C26) -> -18.34 | D25: =SUM(D26:D26) -> 208
A26: Reversal Entries | C26: =SUMIFS(Reconciliation!L:L,Reconciliation!D:D,A26,Reconciliation!F:F,"ledger") +SUMIFS(Reconciliation!S:S,Reconciliation!D:D,A26,Reconciliation!M:M,"ledger") -> -18.34 | D26: =COUNTIFS(Reconciliation!D:D,A26,Reconciliation!F:F,"ledger") +COUNTIFS(Reconciliation!D:D,A26,Reconciliation!M:M,"ledger") -> 208 | E26: No Action Required
A27: Opening Balance Difference | C27: =SUM(C28:C31) -> -139904.72 | D27: =SUM(D28:D31) -> 3
A28: Opening Balance as per Company | C28: =SUMIFS(Reconciliation!L:L,Reconciliation!D:D,A28,Reconciliation!F:F,"ledger") +SUMIFS(Reconciliation!S:S,Reconciliation!D:D,A28,Reconciliation!M:M,"ledger") -> -139904.72 | D28: =COUNTIFS(Reconciliation!D:D,A28,Reconciliation!F:F,"ledger") +COUNTIFS(Reconciliation!D:D,A28,Reconciliation!M:M,"ledger") -> 2
A29: Opening Balance as per Party | C29: =SUMIFS(Reconciliation!L:L,Reconciliation!D:D,A29,Reconciliation!F:F,"ledger") +SUMIFS(Reconciliation!S:S,Reconciliation!D:D,A29,Reconciliation!M:M,"ledger") -> 0 | D29: =COUNTIFS(Reconciliation!D:D,A29,Reconciliation!F:F,"ledger") +COUNTIFS(Reconciliation!D:D,A29,Reconciliation!M:M,"ledger") -> 1 | E29: Vendor to provide the breakup of Opening Balance
A30: Brought forward entries matched - company | B30: 210 | C30: 0 | D30: 0
A31: Brought forward entries matched - party | B31: 211 | C31: 0 | D31: 0
A32: Calculated Balance | C32: =C13+C15+C17+C20+C23+C25+C27 -> 64448.34
A34: Difference | C34: =C9-C32 -> 0

Sheet Reconciliation
A1: Company Id | B1: Party Id | C1: Matched Id | D1: Status | E1: Classification | F1: Company Statement Type | G1: Company Invoice Date | H1: Company Invoice Number | I1: Company DocType | J1: Company Original DocType | K1: Company Narration | L1: Company Amount | M1: Party Statement Type | N1: Party Invoice Date | O1: Party Invoice Number | P1: Party DocType | Q1: Party Original DocType | R1: Party Narration | S1: Party Amount | T1: Difference | U1: Matched Rule | V1: Reco Data & Time | W1: Remark | X1: Party Code | Y1: Daybook Name | Z1: Company Clearing Document Number | AA1: Company Clearing Date | AB1: Company TDS Amount | AC1: Company Posting Date | AD1: Company Code | AE1: Supplier | AF1: Document Number | AG1: Business Area | AH1: Assignment | AI1: Document Header Text | AJ1: Tax Code | AK1: Year/Month | AL1: Reference | AM1: Profit Center | AN1: Posting Date | AO1: Amount in Doc. Curr. | AP1: Document Currency | AQ1: Local Currency | AR1: Entry Date | AS1: Withhldg Tax Base Amount | AT1: Payment Date
A2: e239eb4a-7f5d-409c-bd66-9768ff790717 | B2: dc9fa5fd-9a3f-406c-aee0-738399a743cd | C2: 0102bb94-b8cf-31a5-96a0-453f08501b67 | D2: Reconciled | E2: Date and Amount Matched | F2: ledger | G2: 06-06-2025 | H2: 7053011113 | I2: payment | J2: KZ | L2: 14451.72 | M2: ledger | N2: 06-06-2025 | P2: payment | Q2: DZ | R2: /103010300003186-AXIS Bank | S2: -14451.72 | T2: 0 | U2: PRI-PAY10.1-company | V2: 03-Aug-26 04:10 PM | X2: AAACI5569D | Z2: 7053011113 | AB2: 0 | AD2: EPL | AE2: 708659 | AF2: 7053011113 | AG2: EP00 | AH2: 20250606-SUM02 | AI2: 20250606-SUM02 | AK2: 2025/03 | AM2: 7200 | AN2: 06-06-2025 | AO2: 14451.72 | AP2: INR | AQ2: INR | AR2: 06-06-2025 | AS2: 12247.22 | AT2: 06-06-2025
A3: 34c18428-e172-4ed6-9cf3-9f84fa81647c | B3: 34d96bd4-ca8e-4393-87f5-55fa43df3b57 | C3: 01ccdb63-ed9f-36c5-9754-a6a656b0875b | D3: Reconciled | E3: Invoice Number Matched | F3: ledger | G3: 17-11-2025 | H3: GJ2501032777 | I3: invoice | J3: MA | K3: NITROGEN USP - NF / IH | L3: -15498.94 | M3: ledger | N3: 18-11-2025 | O3: GJ2501032777 | P3: invoice | Q3: RV | S3: 15498.94 | T3: 0 | U3: PRI-INV1.5_A-company | V3: 03-Aug-26 04:10 PM | X3: AAACI5569D | Z3: 7053043675 | AB3: 0 | AD3: EPL | AE3: 708659 | AF3: 6000012318 | AG3: EP00 | AH3: GJ2501032777 | AI3: GJ2501032777 | AJ3: II | AK3: 2025/08 | AL3: EP22 | AM3: 7200 | AN3: 27-11-2025 | AO3: -15498.94 | AP3: INR | AQ3: INR | AR3: 27-11-2025 | AS3: -13134.7 | AT3: 18-11-2025
A4: 770f1c2f-fb75-4346-bd2f-1689cc863585 | B4: 1fafef18-af9f-4680-8b53-63964cbe3e07 | C4: 03d9b23e-c626-3277-ba22-bf72070d5dee | D4: Write off / Rounding off | E4: Invoice Number Matched | F4: ledger | G4: 07-07-2025 | H4: GJ2501013614 | I4: invoice | J4: MA | K4: NITROGEN USP - NF / IH | L4: -16755 | M4: ledger | N4: 07-07-2025 | O4: GJ2501013614 | P4: invoice | Q4: RV | S4: 16755.62 | T4: 0.62 | U4: PRI-INV1.5-company | V4: 03-Aug-26 04:10 PM | X4: AAACI5569D | Z4: 7053018640 | AB4: 0 | AD4: EPL | AE4: 708659 | AF4: 6000004942 | AG4: EP00 | AH4: GJ2501013614 | AI4: GJ2501013614 | AJ4: IA | AK4: 2025/04 | AL4: EP22 | AM4: 7200 | AN4: 09-07-2025 | AO4: -16755 | AP4: INR | AQ4: INR | AR4: 09-07-2025 | AS4: -14199.06 | AT4: 07-07-2025
A5: b5f9bba9-6b13-4843-ad8a-f8819089a230 | B5: 42253461-935f-4b4e-bdc8-eade7b5f4ea7 | C5: 045af481-bc1a-3a4c-8216-2fe1a75b3cb2 | D5: Reconciled | E5: Invoice Number Matched | F5: ledger | G5: 13-08-2025 | H5: GJ2501019099 | I5: invoice | J5: MA | K5: NITROGEN USP - NF / IH | L5: -15498.94 | M5: ledger | N5: 13-08-2025 | O5: GJ2501019099 | P5: invoice | Q5: RV | S5: 15498.94 | T5: 0 | U5: PRI-INV1.5_A-company | V5: 03-Aug-26 04:10 PM | X5: AAACI5569D | Z5: 7053026128 | AB5: 0 | AD5: EPL | AE5: 708659 | AF5: 6000007799 | AG5: EP00 | AH5: GJ2501019099 | AI5: GJ2501019099 | AJ5: IA | AK5: 2025/05 | AL5: EP22 | AM5: 7200 | AN5: 28-08-2025 | AO5: -15498.94 | AP5: INR | AQ5: INR | AR5: 28-08-2025 | AS5: -13134.7 | AT5: 13-08-2025
A6: 75a1507e-8616-4f1c-8f6d-ed2c6ce945b7 | B6: 6d2b9e65-1ff0-4ec0-bcb6-6072ffcacd9e | C6: 05f512b8-4c97-3448-80b9-c21f5bc76dc4 | D6: Reconciled | E6: Date and Amount Matched | F6: ledger | G6: 25-06-2025 | H6: 7053014217 | I6: payment | J6: KZ | L6: 15498.94 | M6: ledger | N6: 25-06-2025 | P6: payment | Q6: DZ | R6: /103010300003186-AXIS Bank | S6: -15498.94 | T6: 0 | U6: PRI-PAY10.1-company | V6: 03-Aug-26 04:10 PM | X6: AAACI5569D | Z6: 7053014217 | AB6: 0 | AD6: EPL | AE6: 708659 | AF6: 7053014217 | AG6: EP00 | AH6: 20250625-SUM01 | AI6: 20250625-SUM01 | AK6: 2025/03 | AM6: 7200 | AN6: 25-06-2025 | AO6: 15498.94 | AP6: INR | AQ6: INR | AR6: 25-06-2025 | AS6: 13134.7 | AT6: 25-06-2025
A7: 2235a0a0-f99f-4b11-9ee9-56e6fbbd79e2 | B7: 0fd9a2cc-cf2f-47ef-be61-97e31aebc5e8 | C7: 0629eb8d-fb71-3eab-b7ee-962c818ce396 | D7: Reconciled | E7: Invoice Number Matched | F7: ledger | G7: 02-09-2025 | H7: GJ2501022123 | I7: invoice | J7: MA | K7: NITROGEN USP - NF / IH | L7: -19687.86 | M7: ledger | N7: 03-09-2025 | O7: GJ2501022123 | P7: invoice | Q7: RV | S7: 19687.86 | T7: 0 | U7: PRI-INV1.5_A-company | V7: 03-Aug-26 04:10 PM | X7: AAACI5569D | Z7: 7053028420 | AB7: 0 | AD7: EPL | AE7: 708659 | AF7: 6000008455 | AG7: EP00 | AH7: GJ2501022123 | AI7: GJ2501022123 | AJ7: IA | AK7: 2025/06 | AL7: EP22 | AM7: 7200 | AN7: 09-09-2025 | AO7: -19687.86 | AP7: INR | AQ7: INR | AR7: 09-09-2025 | AS7: -16684.62 | AT7: 03-09-2025
A8: b7155055-1caf-4e32-806b-aa52ab865971 | B8: ab22d0f7-095b-45c1-b856-a8d126e3953e | C8: 06915f1c-466a-37d8-a69e-5203e6977836 | D8: Reconciled | E8: Invoice Number Matched | F8: ledger | G8: 24-05-2025 | H8: GJ2501007303 | I8: invoice | J8: MA | K8: NITROGEN USP - NF / IH | L8: -14451.72 | M8: ledger | N8: 24-05-2025 | O8: GJ2501007303 | P8: invoice | Q8: RV | S8: 14451.72 | T8: 0 | U8: PRI-INV1.5_A-company | V8: 03-Aug-26 04:10 PM | X8: AAACI5569D | Z8: 7053011113 | AB8: 0 | AD8: EPL | AE8: 708659 | AF8: 6000002545 | AG8: EP00 | AH8: GJ2501007303 | AI8: GJ2501007303 | AJ8: IA | AK8: 2025/02 | AL8: EP22 | AM8: 7200 | AN8: 27-05-2025 | AO8: -14451.72 | AP8: INR | AQ8: INR | AR8: 27-05-2025 | AS8: -12247.22 | AT8: 26-05-2025
A9: 419f95e8-b40d-4a7d-875a-f77e13e3d13d | B9: f46a04d3-50f1-410f-9dc4-d32813671676 | C9: 0751589e-1f28-3d03-8a52-20da3026c011 | D9: Reconciled | E9: Date and Amount Matched | F9: ledger | G9: 03-12-2025 | H9: 7053044053 | I9: payment | J9: KZ | L9: 14451.72 | M9: ledger | N9: 03-12-2025 | P9: payment | Q9: DZ | R9: /103010300003186-AXIS Bank | S9: -14451.72 | T9: 0 | U9: PRI-PAY10.1-company | V9: 03-Aug-26 04:10 PM | X9: AAACI5569D | Z9: 7053044053 | AB9: 0 | AD9: EPL | AE9: 708659 | AF9: 7053044053 | AG9: EP00 | AH9: 20251203-SUM10 | AI9: 20251203-SUM10 | AK9: 2025/09 | AM9: 7200 | AN9: 03-12-2025 | AO9: 14451.72 | AP9: INR | AQ9: INR | AR9: 03-12-2025 | AS9: 12247.22 | AT9: 03-12-2025
A10: 7d1679e1-3bb1-4476-9a3e-ac8e0296508a | B10: ae90adba-0758-4a8b-a007-e0ac0a074a0f | C10: 08090543-befc-3333-abbb-055443e2311b | D10: Reconciled | E10: Date and Amount Matched | F10: ledger | G10: 12-11-2025 | H10: 7053039840 | I10: payment | J10: KZ | L10: 16755.62 | M10: ledger | N10: 12-11-2025 | P10: payment | Q10: DZ | R10: /103010300003186-AXIS Bank | S10: -16755.62 | T10: 0 | U10: PRI-PAY10.1-company | V10: 03-Aug-26 04:10 PM | X10: AAACI5569D | Z10: 7053039840 | AB10: 0 | AD10: EPL | AE10: 708659 | AF10: 7053039840 | AG10: EP00 | AH10: 20251112-SUM02 | AI10: 20251112-SUM02 | AK10: 2025/08 | AM10: 7200 | AN10: 12-11-2025 | AO10: 16755.62 | AP10: INR | AQ10: INR | AR10: 12-11-2025 | AS10: 14199.68 | AT10: 12-11-2025
A11: 4fa6e103-8352-4fa5-82c2-8ad1a9ac9546 | B11: 22851b8b-1969-4590-a3b5-8d6620d3dee0 | C11: 0a46fe88-ffcf-3e58-ad12-81417f99e660 | D11: Reconciled | E11: Date and Amount Matched | F11: ledger | G11: 10-12-2025 | H11: 7053045044 | I11: payment | J11: KZ | L11: 13613.94 | M11: ledger | N11: 10-12-2025 | P11: payment | Q11: DZ | R11: /103010300003186-AXIS Bank | S11: -13613.94 | T11: 0 | U11: PRI-PAY10.1-company | V11: 03-Aug-26 04:10 PM | X11: AAACI5569D | Z11: 7053045044 | AB11: 0 | AD11: EPL | AE11: 708659 | AF11: 7053045044 | AG11: EP00 | AH11: 20251210-SUM02 | AI11: 20251210-SUM02 | AK11: 2025/09 | AM11: 7200 | AN11: 10-12-2025 | AO11: 13613.94 | AP11: INR | AQ11: INR | AR11: 10-12-2025 | AS11: 11537.24 | AT11: 10-12-2025
A12: 1a922d31-d186-4e4c-aa1f-f2289a8a79d4 | B12: 8b8a393a-e179-46b1-8dd9-cbc5938ded87 | C12: 0ad380c7-d851-32e8-a15f-148dccd6158d | D12: Reconciled | E12: Invoice Number Matched | F12: ledger | G12: 27-11-2025 | H12: GJ2501034356 | I12: invoice | J12: MA | K12: NITROGEN USP - NF / IH | L12: -15498.94 | M12: ledger | N12: 28-11-2025 | O12: GJ2501034356 | P12: invoice | Q12: RV | S12: 15498.94 | T12: 0 | U12: PRI-INV1.5_A-company | V12: 03-Aug-26 04:10 PM | X12: AAACI5569D | Z12: 7053045773 | AB12: 0 | AD12: EPL | AE12: 708659 | AF12: 6000012593 | AG12: EP00 | AH12: GJ2501034356 | AI12: GJ2501034356 | AJ12: II | AK12: 2025/09 | AL12: EP22 | AM12: 7200 | AN12: 01-12-2025 | AO12: -15498.94 | AP12: INR | AQ12: INR | AR12: 01-12-2025 | AS12: -13134.7 | AT12: 28-11-2025
A13: b774ef5e-3b11-4525-b185-71d8da4ef911 | B13: e9d901d3-899f-4f0f-9526-7a583554dc58 | C13: 0c3f5a3b-3748-3cfb-9475-17d40608f144 | D13: Reconciled | E13: Date and Amount Matched | F13: ledger | G13: 20-03-2026 | H13: 7053065837 | I13: payment | J13: KZ | L13: 38859 | M13: ledger | N13: 20-03-2026 | P13: payment | Q13: DZ | R13: NEFT Cr-UTIB0001636-EMCURE PHARMACEUTICALS LIMITED | S13: -38859 | T13: 0 | U13: PRI-PAY10.1-company | V13: 03-Aug-26 04:10 PM | X13: AAACI5569D | Z13: 7053065837 | AB13: 0 | AD13: EPL | AE13: 714213 | AF13: 7053065837 | AG13: EP00 | AH13: 20260320-SUM01 | AI13: 20260320-SUM01 | AK13: 2025/12 | AM13: 7200 | AN13: 20-03-2026 | AO13: 38859 | AP13: INR | AQ13: INR | AR13: 20-03-2026 | AS13: 32931.360000000001 | AT13: 20-03-2026
A14: 978a5118-8f9b-4f54-ab7b-de26a6e84029 | B14: 1753e470-c31e-44ee-8c22-932192d984dc | C14: 0ca1f6e1-3818-37d8-abe4-e28760ace981 | D14: TDS Booked by Company | E14: Invoice Number Matched | F14: ledger | G14: 05-07-2025 | H14: GJ2502001220 | I14: invoice | J14: MI | K14: Fixed facility charges july-25 | L14: -8120 | M14: ledger | N14: 05-07-2025 | O14: GJ2502001220 | P14: invoice | Q14: RV | S14: 8260 | T14: 140 | U14: PRI-INV1.6-company | V14: 03-Aug-26 04:10 PM | X14: AAACI5569D | Z14: 7053018640 | AB14: -140 | AD14: EPL | AE14: 708659 | AF14: 6008011428 | AG14: EP00 | AH14: GJ2502001220 | AI14: GJ2502001220 | AJ14: IA | AK14: 2025/04 | AL14: EP22 | AM14: 7200 | AN14: 14-07-2025 | AO14: -8120 | AP14: INR | AQ14: INR | AR14: 14-07-2025 | AS14: -7000 | AT14: 09-07-2025
A15: 72be1a7e-de00-4fd0-8e54-9f420150202c | B15: 68db1cf9-695a-4338-8441-6d672543df07 | C15: 0d6f58c1-3d6a-3d8d-a262-9322227f107c | D15: Write off / Rounding off | E15: Invoice Number Matched | F15: ledger | G15: 03-01-2026 | H15: GJ2501039969 | I15: invoice | J15: MA | K15: NITROGEN USP - NF /Ph.Eur./IH | L15: -64849 | M15: ledger | N15: 03-01-2026 | O15: GJ2501039969 | P15: invoice | Q15: RV | S15: 64849.12 | T15: 0.12 | U15: PRI-INV1.5-company | V15: 03-Aug-26 04:10 PM | X15: AAACI5569D | Z15: 7053062135 | AB15: 0 | AD15: EPL | AE15: 714213 | AF15: 6000015127 | AG15: EP00 | AH15: GJ2501039969 | AI15: GJ501039969 | AJ15: II | AK15: 2025/10 | AL15: EP22 | AM15: 7200 | AN15: 08-01-2026 | AO15: -64849 | AP15: INR | AQ15: INR | AR15: 08-01-2026 | AS15: -54956.76 | AT15: 05-02-2026
A16: 18a22fcd-aa46-43ba-bea8-a7df2be52ecf | B16: fb427b4a-0596-41c3-b838-4d2490b3b7fd | C16: 0ddc8c6f-8b90-34e4-8974-3667e8ffe791 | D16: TDS Booked by Company | E16: Invoice Number Matched | F16: ledger | G16: 05-06-2025 | H16: GJ2502000831 | I16: invoice | J16: MI | K16: Rent charges of nitrogen for June 25 | L16: -8120 | M16: ledger | N16: 05-06-2025 | O16: GJ2502000831 | P16: invoice | Q16: RV | S16: 8260 | T16: 140 | U16: PRI-INV1.6-company | V16: 03-Aug-26 04:10 PM | X16: AAACI5569D | Z16: 7053046690 | AB16: -140 | AD16: EPL | AE16: 708659 | AF16: 6008028039 | AG16: EP00 | AH16: GJ2502000831 | AI16: GJ2502000831 | AJ16: II | AK16: 2025/09 | AL16: EP22 | AM16: 7200 | AN16: 03-12-2025 | AO16: -8120 | AP16: INR | AQ16: INR | AR16: 03-12-2025 | AS16: -7000 | AT16: 21-11-2025
A17: 170e69cc-07fd-4cb5-9794-83d05841139c | B17: 59c3147f-8d47-4538-b89e-eb33f76b06cb | C17: 0dfbfa1c-a556-3548-86cf-642408720a57 | D17: Reconciled | E17: Invoice Number Matched | F17: ledger | G17: 28-07-2025 | H17: GJ2501016823 | I17: invoice | J17: MA | K17: NITROGEN USP - NF / IH | L17: -11938.37 | M17: ledger | N17: 28-07-2025 | O17: GJ2501016823 | P17: invoice | Q17: RV | S17: 11938.37 | T17: 0 | U17: PRI-INV1.5_A-company | V17: 03-Aug-26 04:10 PM | X17: AAACI5569D | Z17: 7053022562 | AB17: 0 | AD17: EPL | AE17: 708659 | AF17: 6000006496 | AG17: EP00 | AH17: GJ2501016823 | AI17: GJ2501016823 | AJ17: IA | AK17: 2025/04 | AL17: EP22 | AM17: 7200 | AN17: 31-07-2025 | AO17: -11938.37 | AP17: INR | AQ17: INR | AR17: 31-07-2025 | AS17: -10117.27 | AT17: 28-07-2025
A18: 619e07ca-fb10-4050-8184-91b2cd0ea0cb | B18: 381048b6-4c9b-46f2-9394-3addac6a373c | C18: 0f0198d3-9f6b-3a13-94bd-40f5464d2661 | D18: Reconciled | E18: Invoice Number Matched | F18: ledger | G18: 27-05-2025 | H18: GJ2501007694 | I18: invoice | J18: MA | K18: NITROGEN USP - NF / IH | L18: -17802.84 | M18: ledger | N18: 27-05-2025 | O18: GJ2501007694 | P18: invoice | Q18: RV | S18: 17802.84 | T18: 0 | U18: PRI-INV1.5_A-company | V18: 03-Aug-26 04:10 PM | X18: AAACI5569D | Z18: 7053011696 | AB18: 0 | AD18: EPL | AE18: 708659 | AF18: 6000002794 | AG18: EP00 | AH18: GJ2501007694 | AI18: GJ2501007694 | AJ18: IA | AK18: 2025/03 | AL18: EP22 | AM18: 7200 | AN18: 02-06-2025 | AO18: -17802.84 | AP18: INR | AQ18: INR | AR18: 02-06-2025 | AS18: -15087.16 | AT18: 28-05-2025
A19: 537db7e4-5131-4d30-ad04-e8a3bda13f80 | B19: 16d98f5b-7192-4f4f-9581-3d76cc11477d | C19: 0f6b9183-9481-3ca8-ad34-d9c464fc060c | D19: Reconciled | E19: Invoice Number Matched | F19: ledger | G19: 27-01-2026 | H19: GJ2501043584 | I19: invoice | J19: MA | K19: NITROGEN USP - NF / IH | L19: -14661.16 | M19: ledger | N19: 27-01-2026 | O19: GJ2501043584 | P19: invoice | Q19: RV | S19: 14661.16 | T19: 0 | U19: PRI-INV1.5_A-company | V19: 03-Aug-26 04:10 PM | X19: AAACI5569D | Z19: 7053058317 | AB19: 0 | AD19: EPL | AE19: 708659 | AF19: 6000016109 | AG19: EP00 | AH19: GJ2501043584 | AI19: GJ2501043584 | AJ19: II | AK19: 2025/10 | AL19: EP22 | AM19: 7200 | AN19: 29-01-2026 | AO19: -14661.16 | AP19: INR | AQ19: INR | AR19: 29-01-2026 | AS19: -12424.72 | AT19: 28-01-2026
A20: 7e32b000-4c36-41d5-ad50-2d95744cc8e8 | B20: d9b5b396-0cb9-4308-a2b6-5845677070b8 | C20: 1042934f-e325-3aa2-b1e6-67ce509b480f | D20: Reconciled | E20: Date and Amount Matched | F20: ledger | G20: 21-04-2025 | H20: 7053003056 | I20: payment | J20: KZ | L20: 18431.19 | M20: ledger | N20: 21-04-2025 | P20: payment | Q20: DZ | R20: /103010300003186-AXIS Bank | S20: -18431.19 | T20: 0 | U20: PRI-PAY10.1-company | V20: 03-Aug-26 04:10 PM | X20: AAACI5569D | Z20: 7053003056 | AB20: 0 | AD20: EPL | AE20: 708659 | AF20: 7053003056 | AG20: EP00 | AH20: 20250421-SUM02 | AI20: 20250421-SUM02 | AK20: 2025/01 | AM20: 7200 | AN20: 21-04-2025 | AO20: 18431.189999999999 | AP20: INR | AQ20: INR | AR20: 21-04-2025 | AS20: 15619.65 | AT20: 21-04-2025
A21: 2568f5d0-48d2-44bd-acf6-9f2158611cba | B21: 77d26c2e-a512-4b25-b25d-43a78503a417 | C21: 106c61c6-f08b-3269-8369-81e371ed4e6d | D21: Reconciled | E21: Invoice Number Matched | F21: ledger | G21: 16-09-2025 | H21: GJ2501017485 | I21: invoice | J21: MA | K21: NITROGEN USP - NF / IH | L21: -17174.51 | M21: ledger | N21: 01-08-2025 | O21: GJ2501017485 | P21: invoice | Q21: RV | S21: 17174.51 | T21: 0 | U21: PRI-INV1.5_A-company | V21: 03-Aug-26 04:10 PM | X21: AAACI5569D | Z21: 7053034627 | AB21: 0 | AD21: EPL | AE21: 708659 | AF21: 6000009736 | AG21: EP00 | AH21: GJ2501017485 | AI21: GJ2501024363 | AJ21: II | AK21: 2025/06 | AL21: EP22 | AM21: 7200 | AN21: 30-09-2025 | AO21: -17174.509999999998 | AP21: INR | AQ21: INR | AR21: 30-09-2025 | AS21: -14554.67 | AT21: 01-08-2025
A22: 824c4c97-c29f-47f9-874f-8ff4134020b3 | B22: c6538111-bb2a-42b4-a133-51eb04f5c1c2 | C22: 110c9077-55d7-366f-901a-689dd1a2b184 | D22: Reconciled | E22: Date and Amount Matched | F22: ledger | G22: 28-05-2025 | H22: 7053009537 | I22: payment | J22: KZ | L22: 31207 | M22: ledger | N22: 28-05-2025 | P22: payment | Q22: DZ | R22: /103010300003186-AXIS Bank | S22: -31207 | T22: 0 | U22: PRI-PAY10.1-company | V22: 03-Aug-26 04:10 PM | X22: AAACI5569D | Z22: 7053009537 | AB22: 0 | AD22: EPL | AE22: 708659 | AF22: 7053009537 | AG22: EP00 | AH22: 20250528-SUM01 | AI22: 20250528-SUM01 | AK22: 2025/02 | AM22: 7200 | AN22: 28-05-2025 | AO22: 31207 | AP22: INR | AQ22: INR | AR22: 28-05-2025 | AS22: 26446.560000000001 | AT22: 28-05-2025
A23: a9dc7e96-48ff-47e7-95e7-1378163d69a3 | B23: bf5d9d3a-9642-4dec-a100-e2a69c626181 | C23: 12865390-331f-3113-9500-42d98c7e89c1 | D23: TDS Booked by Company | E23: Invoice Number Matched | F23: ledger | G23: 16-01-2026 | H23: GJ2502003787 | I23: invoice | J23: MI | K23: CONSULTANCY FEES- APPROX MONTH JAN 2025 | L23: -121800 | M23: ledger | N23: 16-01-2026 | O23: GJ2502003787 | P23: invoice | Q23: RV | S23: 123900 | T23: 2100 | U23: PRI-INV1.6-company | V23: 03-Aug-26 04:10 PM | X23: AAACI5569D | Z23: 7053056142 | AB23: -2100 | AD23: EPL | AE23: 708659 | AF23: 6008034932 | AG23: EP00 | AH23: GJ2502003787 | AI23: GJ2502003787 | AJ23: II | AK23: 2025/10 | AL23: EP22 | AM23: 7200 | AN23: 21-01-2026 | AO23: -121800 | AP23: INR | AQ23: INR | AR23: 21-01-2026 | AS23: -105000 | AT23: 20-01-2026
A24: 241dd284-d5a2-41cc-910d-d161ab84c990 | B24: decaaf4c-de4c-42bb-9f1a-fa2c1619ea9c | C24: 12c5ebd7-0bc5-3cb6-988a-a352ffa8c7dd | D24: Reconciled | E24: Date and Amount Matched | F24: ledger | G24: 29-01-2026 | H24: 7053055473 | I24: payment | J24: KZ | L24: 16127.29 | M24: ledger | N24: 29-01-2026 | P24: payment | Q24: DZ | R24: /103010300003186-AXIS Bank | S24: -16127.29 | T24: 0 | U24: PRI-PAY10.1-company | V24: 03-Aug-26 04:10 PM | X24: AAACI5569D | Z24: 7053055473 | AB24: 0 | AD24: EPL | AE24: 708659 | AF24: 7053055473 | AG24: EP00 | AH24: 20260129-SUM10 | AI24: 20260129-SUM10 | AK24: 2025/10 | AM24: 7200 | AN24: 29-01-2026 | AO24: 16127.29 | AP24: INR | AQ24: INR | AR24: 29-01-2026 | AS24: 13667.19 | AT24: 29-01-2026
A25: 5fbc469c-a265-4725-a34e-e3e6e122d815 | B25: 1b7bc51b-ebf7-45d6-8b00-73a7c0d47ffe | C25: 12df1500-5005-40c3-85f2-7d0f4e5e944e | D25: Reconciled | E25: Date Range and Amount Matched | F25: ledger | G25: 10-11-2025 | H25: 7053039489 | I25: payment | J25: KZ | L25: 55663.4 | M25: ledger | N25: 11-11-2025 | P25: payment | Q25: DZ | R25: /103010300003186-AXIS Bank | S25: -55663.4 | T25: 0 | U25: PRI-PAY11.1-company | V25: 03-Aug-26 04:10 PM | X25: AAACI5569D | Z25: 7053039489 | AB25: 0 | AD25: EPL | AE25: 708659 | AF25: 7053039489 | AG25: EP00 | AH25: 20251110-SUM02 | AI25: 20251110-SUM02 | AK25: 2025/08 | AM25: 7200 | AN25: 10-11-2025 | AO25: 55663.4 | AP25: INR | AQ25: INR | AR25: 10-11-2025 | AS25: 47290.92 | AT25: 10-11-2025
A26: 313fcd04-0514-4321-b7ea-bd5e17850e66 | B26: f879ae48-5e10-422c-abc1-fd7fb567032a | C26: 134030d4-0656-306c-923c-0033ee196bb6 | D26: Reconciled | E26: Date and Amount Matched | F26: ledger | G26: 23-03-2026 | H26: 7053065992 | I26: payment | J26: KZ | L26: 36588.02 | M26: ledger | N26: 23-03-2026 | P26: payment | Q26: DZ | R26: NEFT Cr-UTIB0001636-EMCURE PHARMACEUTICALS LIMITED | S26: -36588.02 | T26: 0 | U26: PRI-PAY10.1-company | V26: 03-Aug-26 04:10 PM | X26: AAACI5569D | Z26: 7053065992 | AB26: 0 | AD26: EPL | AE26: 714213 | AF26: 7053065992 | AG26: EP00 | AH26: 20260323-SUM10 | AI26: 20260323-SUM10 | AK26: 2025/12 | AM26: 7200 | AN26: 23-03-2026 | AO26: 36588.019999999997 | AP26: INR | AQ26: INR | AR26: 23-03-2026 | AS26: 31006.799999999999 | AT26: 23-03-2026
A27: 9c49830e-2d1e-42b9-815f-086292e35a0a | B27: 04d81620-531e-4e19-88ee-107613bd869b | C27: 1389c6c3-a6c5-3e19-86d9-0c8da1f05247 | D27: Reconciled | E27: Invoice Number Matched | F27: ledger | G27: 27-08-2025 | H27: GJ2501021121 | I27: invoice | J27: MA | K27: NITROGEN USP - NF / IH | L27: -18431.19 | M27: ledger | N27: 27-08-2025 | O27: GJ2501021121 | P27: invoice | Q27: RV | S27: 18431.19 | T27: 0 | U27: PRI-INV1.5_A-company | V27: 03-Aug-26 04:10 PM | X27: AAACI5569D | Z27: 7053028415 | AB27: 0 | AD27: EPL | AE27: 708659 | AF27: 6000008256 | AG27: EP00 | AH27: GJ2501021121 | AI27: GJ2501021121 | AJ27: IA | AK27: 2025/06 | AL27: EP22 | AM27: 7200 | AN27: 04-09-2025 | AO27: -18431.189999999999 | AP27: INR | AQ27: INR | AR27: 04-09-2025 | AS27: -15619.65 | AT27: 30-08-2025
A28: 20d86c9d-20cf-452b-b863-4d4161757ce2 | B28: 223b4917-7bb6-4d0b-a1e6-1a09de4e5ba4 | C28: 14106f01-4bbc-3296-9e9f-428271999dbc | D28: Write off / Rounding off | E28: Invoice Number Matched | F28: ledger | G28: 13-09-2025 | H28: GJ2501023625 | I28: invoice | J28: MA | K28: NITROGEN USP - NF / IH | L28: -17803 | M28: ledger | N28: 13-09-2025 | O28: GJ2501023625 | P28: invoice | Q28: RV | S28: 17802.84 | T28: -0.16 | U28: PRI-INV1.5-company | V28: 03-Aug-26 04:10 PM | X28: AAACI5569D | Z28: 7053031026 | AB28: 0 | AD28: EPL | AE28: 708659 | AF28: 6000009286 | AG28: EP00 | AH28: GJ2501023625 | AI28: GJ2501023625 | AJ28: II | AK28: 2025/06 | AL28: EP22 | AM28: 7200 | AN28: 24-09-2025 | AO28: -17803 | AP28: INR | AQ28: INR | AR28: 24-09-2025 | AS28: -15087.32 | AT28: 15-09-2025
A29: ef3174fa-b20c-4650-a437-2c28e373cc6b | B29: c217d3b2-dc98-4972-a22c-62690237c23d | C29: 1458031b-5016-3393-abba-62c141df9776 | D29: Reconciled | E29: Invoice Number Matched | F29: ledger | G29: 21-12-2025 | H29: GJ2501038191 | I29: invoice | J29: MA | K29: NITROGEN USP - NF / IH | L29: -16127.29 | M29: ledger | N29: 23-12-2025 | O29: GJ2501038191 | P29: invoice | Q29: RV | S29: 16127.29 | T29: 0 | U29: PRI-INV1.5_A-company | V29: 03-Aug-26 04:10 PM | X29: AAACI5569D | Z29: 7053052837 | AB29: 0 | AD29: EPL | AE29: 708659 | AF29: 6000014800 | AG29: EP00 | AH29: GJ2501038191 | AI29: GJ2501038191 | AJ29: II | AK29: 2025/09 | AL29: EP22 | AM29: 7200 | AN29: 31-12-2025 | AO29: -16127.29 | AP29: INR | AQ29: INR | AR29: 02-01-2026 | AS29: -13667.19 | AT29: 23-12-2025
A30: 13a89072-17f4-469b-adab-904e77bee999 | B30: 80f73e0c-33e6-46c1-8d62-587bbc3a6ddb | C30: 161da05b-906d-3575-9250-bfbc809ee54f | D30: TDS Booked by Company | E30: Invoice Number Matched | F30: ledger | G30: 05-02-2026 | H30: GJ2502003996 | I30: invoice | J30: MI | K30: Nitrogen tank 6kl Rent Charge (Inox) | L30: -29000 | M30: ledger | N30: 05-02-2026 | O30: GJ2502003996 | P30: invoice | Q30: RV | S30: 29500 | T30: 500 | U30: PRI-INV1.6-company | V30: 03-Aug-26 04:10 PM | X30: AAACI5569D | Z30: 7053062135 | AB30: -500 | AD30: EPL | AE30: 714213 | AF30: 6008037710 | AG30: EP00 | AH30: GJ2502003996 | AI30: GJ2502003996 | AJ30: II | AK30: 2025/11 | AL30: EP22 | AM30: 7200 | AN30: 12-02-2026 | AO30: -29000 | AP30: INR | AQ30: INR | AR30: 12-02-2026 | AS30: -25000 | AT30: 10-02-2026
A31: 950366d2-bbd9-4aa1-91a6-3874647c2db4 | B31: f3de4390-0fc5-4dde-bb2f-51aac3816e1a | C31: 165c1b3d-a552-3e10-b987-25b57387d0ee | D31: Reconciled | E31: Invoice Number Matched | F31: ledger | G31: 04-04-2025 | H31: GJ2501000356 | I31: invoice | J31: MA | K31: NITROGEN USP - NF / IH | L31: -17802.84 | M31: ledger | N31: 04-04-2025 | O31: GJ2501000356 | P31: invoice | Q31: RV | S31: 17802.84 | T31: 0 | U31: PRI-INV1.5_A-company | V31: 03-Aug-26 04:10 PM | X31: AAACI5569D | Z31: 7053003202 | AB31: 0 | AD31: EPL | AE31: 708659 | AF31: 6000000634 | AG31: EP00 | AH31: GJ2501000356 | AI31: GJ2501000356 | AJ31: IA | AK31: 2025/01 | AL31: EP22 | AM31: 7200 | AN31: 21-04-2025 | AO31: -17802.84 | AP31: INR | AQ31: INR | AR31: 21-04-2025 | AS31: -15087.16 | AT31: 03-04-2025
A32: 3459e23a-ac4a-4af6-8300-ec0ed529935d | B32: 0320d7df-9a8d-4d25-9dc8-f3bc70fe582e | C32: 17c0c9f1-a4e5-32fd-b0c2-d53b07c35f44 | D32: Reconciled | E32: Invoice Number Matched | F32: ledger | G32: 01-02-2026 | H32: GJ2501044504 | I32: invoice | J32: MA | K32: NITROGEN USP - NF / IH | L32: -15289.51 | M32: ledger | N32: 01-02-2026 | O32: GJ2501044504 | P32: invoice | Q32: RV | S32: 15289.51 | T32: 0 | U32: PRI-INV1.5_A-company | V32: 03-Aug-26 04:10 PM | X32: AAACI5569D | Z32: 7053058939 | AB32: 0 | AD32: EPL | AE32: 708659 | AF32: 6000016636 | AG32: EP00 | AH32: GJ2501044504 | AI32: GJ2501044504 | AJ32: II | AK32: 2025/11 | AL32: EP22 | AM32: 7200 | AN32: 06-02-2026 | AO32: -15289.51 | AP32: INR | AQ32: INR | AR32: 06-02-2026 | AS32: -12957.21 | AT32: 02-02-2026
A33: dccf8b26-0e80-4223-8058-0c6172df8eba | B33: 969ca46e-22f0-4074-a516-d83e25f51713 | C33: 18c90947-08ce-3d07-8cdf-d8ddf23b1be2 | D33: Reconciled | E33: Date and Amount Matched | F33: ledger | G33: 04-06-2025 | H33: 7053010772 | I33: payment | J33: KZ | L33: 31206 | M33: ledger | N33: 04-06-2025 | P33: payment | Q33: DZ | R33: /103010300003186-AXIS Bank | S33: -31206 | T33: 0 | U33: PRI-PAY10.1-company | V33: 03-Aug-26 04:10 PM | X33: AAACI5569D | Z33: 7053010772 | AB33: 0 | AD33: EPL | AE33: 708659 | AF33: 7053010772 | AG33: EP00 | AH33: 20250604-SUM02 | AI33: 20250604-SUM02 | AK33: 2025/03 | AM33: 7200 | AN33: 04-06-2025 | AO33: 31206 | AP33: INR | AQ33: INR | AR33: 04-06-2025 | AS33: 26445.56 | AT33: 04-06-2025
A34: d443d5bb-02a1-47d3-81cc-d8c9187ab4ef | B34: 912c5f17-4bc3-4292-bedd-c4853c791d10 | C34: 194b8823-59b1-3caa-8a44-6e333f1a9231 | D34: Reconciled | E34: Invoice Number Matched | F34: ledger | G34: 13-12-2025 | H34: GJ2501036831 | I34: invoice | J34: MA | K34: NITROGEN USP - NF / IH | L34: -14870.62 | M34: ledger | N34: 14-12-2025 | O34: GJ2501036831 | P34: invoice | Q34: RV | S34: 14870.62 | T34: 0 | U34: PRI-INV1.5_A-company | V34: 03-Aug-26 04:10 PM | X34: AAACI5569D | Z34: 7053048840 | AB34: 0 | AD34: EPL | AE34: 708659 | AF34: 6000013561 | AG34: EP00 | AH34: GJ2501036831 | AI34: GJ2501036831 | AJ34: II | AK34: 2025/09 | AL34: EP22 | AM34: 7200 | AN34: 18-12-2025 | AO34: -14870.62 | AP34: INR | AQ34: INR | AR34: 18-12-2025 | AS34: -12602.22 | AT34: 13-12-2025
A35: dc257bdb-875c-466b-88f2-40a6f8bfcc5e | B35: 58f60edc-1f82-411d-9f23-a773bc3f54a6 | C35: 1a75c43e-9692-3b49-a0ca-b819f205b2ba | D35: Reconciled | E35: Date and Amount Matched | F35: ledger | G35: 24-12-2025 | H35: 7053047776 | I35: payment | J35: KZ | L35: 29531 | M35: ledger | N35: 24-12-2025 | P35: payment | Q35: DZ | R35: /103010300003186-AXIS Bank | S35: -29531 | T35: 0 | U35: PRI-PAY10.1-company | V35: 03-Aug-26 04:10 PM | X35: AAACI5569D | Z35: 7053047776 | AB35: 0 | AD35: EPL | AE35: 708659 | AF35: 7053047776 | AG35: EP00 | AH35: 20251224-SUM01 | AI35: 20251224-SUM01 | AK35: 2025/09 | AM35: 7200 | AN35: 24-12-2025 | AO35: 29531 | AP35: INR | AQ35: INR | AR35: 24-12-2025 | AS35: 25026.16 | AT35: 24-12-2025
A36: c86cceed-0cec-4bce-881b-9e889fa9534a | B36: 3caa2a32-692a-45a7-b31f-4bc48d5ecee1 | C36: 1b464bbe-c278-3e49-948f-b1263bd94f23 | D36: Reconciled | E36: Invoice Number Matched | F36: ledger | G36: 29-11-2025 | H36: GJ2501034724 | I36: invoice | J36: MA | K36: NITROGEN USP - NF / IH | L36: -12985.61 | M36: ledger | N36: 30-11-2025 | O36: GJ2501034724 | P36: invoice | Q36: RV | S36: 12985.61 | T36: 0 | U36: PRI-INV1.5_A-company | V36: 03-Aug-26 04:10 PM | X36: AAACI5569D | Z36: 7053047188 | AB36: 0 | AD36: EPL | AE36: 708659 | AF36: 6000013502 | AG36: EP00 | AH36: GJ2501034724 | AI36: GJ2501034724 | AJ36: II | AK36: 2025/09 | AL36: EP22 | AM36: 7200 | AN36: 18-12-2025 | AO36: -12985.61 | AP36: INR | AQ36: INR | AR36: 18-12-2025 | AS36: -11004.75 | AT36: 02-12-2025
A37: ed421c7a-fe50-45b8-9bd6-5d949c6cd7ea | B37: 990c846b-d514-4741-98f9-d63b6127bc7f | C37: 1c189260-3413-3264-8ec4-304bb0a4a29c | D37: Write off / Rounding off | E37: Invoice Number Matched | F37: ledger | G37: 30-03-2026 | H37: GJ2501053696 | I37: invoice | J37: MA | K37: NITROGEN USP - NF /Ph.Eur./IH | L37: -24728 | M37: ledger | N37: 30-03-2026 | O37: GJ2501053696 | P37: invoice | Q37: RV | S37: 24728.46 | T37: 0.46 | U37: PRI-INV1.5-company | V37: 03-Aug-26 04:10 PM | X37: AAACI5569D | Z37: 7053002120 | AB37: 0 | AD37: EPL | AE37: 714213 | AF37: 6000019806 | AG37: EP00 | AH37: GJ2501053696 | AI37: GJ2501053696 | AJ37: II | AK37: 2025/12 | AL37: EP22 | AM37: 7200 | AN37: 31-03-2026 | AO37: -24728 | AP37: INR | AQ37: INR | AR37: 31-03-2026 | AS37: -20955.86 | AT37: 31-03-2026
A38: 48ec9e30-b538-4174-ac1c-cb0ef9dff214 | B38: 34cd6a9b-9985-4b4a-92c8-97e6dcb31a11 | C38: 1c1b6223-e656-3a45-8026-dfe15012b0b4 | D38: Reconciled | E38: Multiple Date and Amount Matched | F38: ledger | G38: 05-05-2025 | H38: 7053005096 | I38: payment | J38: KZ | L38: 15498.94 | M38: ledger | N38: 05-05-2025 | P38: payment | Q38: DZ | R38: /103010300003186-AXIS Bank | S38: -15498.94 | T38: 0 | U38: PRI-PAY1.1-company | V38: 03-Aug-26 04:10 PM | X38: AAACI5569D | Z38: 7053005096 | AB38: 0 | AD38: EPL | AE38: 708659 | AF38: 7053005096 | AG38: EP16 | AH38: 20250505-SUM10 | AI38: 20250505-SUM10 | AK38: 2025/02 | AM38: 7200 | AN38: 05-05-2025 | AO38: 15498.94 | AP38: INR | AQ38: INR | AR38: 05-05-2025 | AS38: 13134.7 | AT38: 05-05-2025
A39: 7364a35b-7b93-41b1-9d9b-0410d48cb70a | B39: c03d826c-ca9d-4ceb-ada9-b6eea7ea14c1 | C39: 1c1b6223-e656-3a45-8026-dfe15012b0b4 | D39: Reconciled | E39: Multiple Date and Amount Matched | F39: ledger | G39: 05-05-2025 | H39: 7053005095 | I39: payment | J39: KZ | L39: 95505.13 | M39: ledger | N39: 05-05-2025 | P39: payment | Q39: DZ | R39: /103010300003186-AXIS Bank | S39: -95505.13 | T39: 0 | U39: PRI-PAY1.1-company | V39: 03-Aug-26 04:10 PM | X39: AAACI5569D | Z39: 7053005095 | AB39: 0 | AD39: EPL | AE39: 708659 | AF39: 7053005095 | AG39: EP00 | AH39: 20250505-SUM10 | AI39: 20250505-SUM10 | AK39: 2025/02 | AM39: 7200 | AN39: 05-05-2025 | AO39: 95505.13 | AP39: INR | AQ39: INR | AR39: 05-05-2025 | AS39: 80936.25 | AT39: 05-05-2025
A40: 6e05986c-f44b-4328-a278-7f5c7eb32394 | B40: 341e14db-7a60-4284-9554-eda308453feb | C40: 1c79962d-b9e7-3e4d-b6b6-f28d16f13cd6 | D40: Write off / Rounding off | E40: Invoice Number Matched | F40: ledger | G40: 18-11-2025 | H40: GJ2501032941 | I40: invoice | J40: MA | K40: NITROGEN USP - NF / IH | L40: -15080 | M40: ledger | N40: 19-11-2025 | O40: GJ2501032941 | P40: invoice | Q40: RV | S40: 15080.05 | T40: 0.05 | U40: PRI-INV1.5-company | V40: 03-Aug-26 04:10 PM | X40: AAACI5569D | Z40: 7053043908 | AB40: 0 | AD40: EPL | AE40: 708659 | AF40: 6000012320 | AG40: EP00 | AH40: GJ2501032941 | AI40: GJ2501032941 | AJ40: II | AK40: 2025/08 | AL40: EP22 | AM40: 7200 | AN40: 27-11-2025 | AO40: -15080 | AP40: INR | AQ40: INR | AR40: 27-11-2025 | AS40: -12779.66 | AT40: 20-11-2025
A41: 1def87c0-5cd6-4758-a604-4146686645e0 | B41: b4056325-e39b-4a5f-907c-55f2736a0e96 | C41: 1d564d8f-2c6c-358d-a115-b01e8f392ee6 | D41: Write off / Rounding off | E41: Invoice Number Matched | F41: ledger | G41: 12-05-2025 | H41: GJ2501005550 | I41: invoice | J41: MA | K41: NITROGEN USP - NF / IH | L41: -14032 | M41: ledger | N41: 12-05-2025 | O41: GJ2501005550 | P41: invoice | Q41: RV | S41: 14032.83 | T41: 0.83 | U41: PRI-INV1.5-company | V41: 03-Aug-26 04:10 PM | X41: AAACI5569D | Z41: 7053009400 | AB41: 0 | AD41: EPL | AE41: 708659 | AF41: 6000002366 | AG41: EP00 | AH41: GJ2501005550 | AI41: GJ2501005550 | AJ41: IA | AK41: 2025/02 | AL41: EP22 | AM41: 7200 | AN41: 23-05-2025 | AO41: -14032 | AP41: INR | AQ41: INR | AR41: 23-05-2025 | AS41: -11891.4 | AT41: 12-05-2025
A42: b30481d6-8cf6-4919-81ad-ea03eb5b98a6 | B42: fd696d75-da00-40a1-8bb6-ef319d280af3 | C42: 1f57551b-f843-3ea3-b162-da0b36b5f829 | D42: Reconciled | E42: Invoice Number Matched | F42: ledger | G42: 25-12-2025 | H42: GJ2501038566 | I42: invoice | J42: MA | K42: NITROGEN USP - NF / IH | L42: -8377.82 | M42: ledger | N42: 25-12-2025 | O42: GJ2501038566 | P42: invoice | Q42: RV | S42: 8377.82 | T42: 0 | U42: PRI-INV1.5_A-company | V42: 03-Aug-26 04:10 PM | X42: AAACI5569D | Z42: 7053052837 | AB42: 0 | AD42: EPL | AE42: 708659 | AF42: 6000014777 | AG42: EP00 | AH42: GJ2501038566 | AI42: GJ2501038566 | AJ42: II | AK42: 2025/09 | AL42: EP22 | AM42: 7200 | AN42: 31-12-2025 | AO42: -8377.82 | AP42: INR | AQ42: INR | AR42: 02-01-2026 | AS42: -7099.84 | AT42: 29-12-2025
A43: c69508f4-2dee-49b3-8155-e54f9f0da091 | B43: 9577d55f-cb42-447b-b226-1324d44882d1 | C43: 20ab084e-0738-38f8-b367-ca651a53ef33 | D43: Write off / Rounding off | E43: Invoice Number Matched | F43: ledger | G43: 10-06-2025 | H43: GJ2501009872 | I43: invoice | J43: MA | K43: NITROGEN USP - NF / IH | L43: -16965 | M43: ledger | N43: 11-06-2025 | O43: GJ2501009872 | P43: invoice | Q43: RV | S43: 16965.08 | T43: 0.08 | U43: PRI-INV1.5-company | V43: 03-Aug-26 04:10 PM | X43: AAACI5569D | Z43: 7053015082 | AB43: 0 | AD43: EPL | AE43: 708659 | AF43: 6000004285 | AG43: EP00 | AH43: GJ2501009872 | AI43: GJ2501009872 | AJ43: IA | AK43: 2025/03 | AL43: EP22 | AM43: 7200 | AN43: 27-06-2025 | AO43: -16965 | AP43: INR | AQ43: INR | AR43: 27-06-2025 | AS43: -14377.1 | AT43: 12-06-2025
A44: 2c191e1d-291c-46c8-a40b-7cf1e30ff49f | B44: 7287bf6a-976b-4ff9-a42c-9e42a34a023a | C44: 228e9f1a-21ae-358d-ab9e-ac0e172a95e4 | D44: Reconciled | E44: Invoice Number Matched | F44: ledger | G44: 13-01-2026 | H44: GJ2501041579 | I44: invoice | J44: MA | K44: NITROGEN USP - NF / IH | L44: -16127.29 | M44: ledger | N44: 13-01-2026 | O44: GJ2501041579 | P44: invoice | Q44: RV | S44: 16127.29 | T44: 0 | U44: PRI-INV1.5_A-company | V44: 03-Aug-26 04:10 PM | X44: AAACI5569D | Z44: 7053055473 | AB44: 0 | AD44: EPL | AE44: 708659 | AF44: 6000015579 | AG44: EP00 | AH44: GJ2501041579 | AI44: GJ2501041579 | AJ44: II | AK44: 2025/10 | AL44: EP22 | AM44: 7200 | AN44: 19-01-2026 | AO44: -16127.29 | AP44: INR | AQ44: INR | AR44: 19-01-2026 | AS44: -13667.19 | AT44: 12-01-2026
A45: 366fb887-765a-45be-bdf1-11c9b7d3a5fb | B45: 12667236-756f-46a7-9a93-34f4776f8324 | C45: 259a6478-fadb-397f-b1ce-54a9d0df2189 | D45: Reconciled | E45: Invoice Number Matched | F45: ledger | G45: 04-09-2025 | H45: GJ2501022610 | I45: invoice | J45: MA | K45: NITROGEN USP - NF / IH | L45: -4817.25 | M45: ledger | N45: 06-09-2025 | O45: GJ2501022610 | P45: invoice | Q45: RV | S45: 4817.25 | T45: 0 | U45: PRI-INV1.5_A-company | V45: 03-Aug-26 04:10 PM | X45: AAACI5569D | Z45: 7053028420 | AB45: 0 | AD45: EPL | AE45: 708659 | AF45: 6000008467 | AG45: EP00 | AH45: GJ2501022610 | AI45: GJ2501022610 | AJ45: IA | AK45: 2025/06 | AL45: EP22 | AM45: 7200 | AN45: 09-09-2025 | AO45: -4817.25 | AP45: INR | AQ45: INR | AR45: 09-09-2025 | AS45: -4082.41 | AT45: 06-09-2025
A46: 43181376-8459-462e-bd92-2aa42156db78 | B46: 9fca985e-86c7-42e9-a99c-fceebf42ed01 | C46: 26a85f82-af46-4f34-ac21-92685f4b8319 | D46: Reconciled | E46: Partial Invoice Number with Date Range | F46: ledger | G46: 27-01-2026 | H46: GJ2501043805R | I46: invoice | J46: MA | K46: NITROGEN USP - NF / IH | L46: -15289.51 | M46: ledger | N46: 28-01-2026 | O46: GJ2501043805 | P46: invoice | Q46: RV | S46: 15289.51 | T46: 0 | U46: PRI-INV3.1-company | V46: 03-Aug-26 04:10 PM | X46: AAACI5569D | Z46: 7053058317 | AB46: 0 | AD46: EPL | AE46: 708659 | AF46: 6000016650 | AG46: EP00 | AH46: GJ2501043805R | AI46: GJ2501043805 | AJ46: II | AK46: 2025/11 | AL46: EP22 | AM46: 7200 | AN46: 09-02-2026 | AO46: -15289.51 | AP46: INR | AQ46: INR | AR46: 09-02-2026 | AS46: -12957.21 | AT46: 29-01-2026
A47: 0a41572e-86b1-46ef-85b7-57552ede13a8 | B47: 1f4d0aec-9ff4-4f00-acb4-317ede02a2f7 | C47: 26fa3e12-ca1a-3ca8-a155-66251540de79 | D47: Reconciled | E47: Invoice Number Matched | F47: ledger | G47: 21-11-2025 | H47: GJ2501033465 | I47: invoice | J47: MA | K47: NITROGEN USP - NF / IH | L47: -14032.83 | M47: ledger | N47: 22-11-2025 | O47: GJ2501033465 | P47: invoice | Q47: RV | S47: 14032.83 | T47: 0 | U47: PRI-INV1.5_A-company | V47: 03-Aug-26 04:10 PM | X47: AAACI5569D | Z47: 7053044775 | AB47: 0 | AD47: EPL | AE47: 708659 | AF47: 6000012408 | AG47: EP00 | AH47: GJ2501033465 | AI47: GJ2501033465 | AJ47: II | AK47: 2025/08 | AL47: EP22 | AM47: 7200 | AN47: 28-11-2025 | AO47: -14032.83 | AP47: INR | AQ47: INR | AR47: 28-11-2025 | AS47: -11892.23 | AT47: 24-11-2025
A48: d9c40135-66d6-45da-a501-c0f699172173 | B48: 4e7b9f98-4b65-45f5-b6b1-b3534df47ca9 | C48: 27d5dc91-ea8e-3b6a-a05e-7cd307425bf2 | D48: Write off / Rounding off | E48: Invoice Number Matched | F48: ledger | G48: 07-04-2025 | H48: GJ2501000765 | I48: invoice | J48: MA | K48: NITROGEN USP - NF / IH | L48: -18431 | M48: ledger | N48: 07-04-2025 | O48: GJ2501000765 | P48: invoice | Q48: RV | S48: 18431.19 | T48: 0.19 | U48: PRI-INV1.5-company | V48: 03-Aug-26 04:10 PM | X48: AAACI5569D | Z48: 7053005095 | AB48: 0 | AD48: EPL | AE48: 708659 | AF48: 6000000884 | AG48: EP00 | AH48: GJ2501000765 | AI48: GJ2501000765 | AJ48: IA | AK48: 2025/01 | AL48: EP22 | AM48: 7200 | AN48: 24-04-2025 | AO48: -18431 | AP48: INR | AQ48: INR | AR48: 24-04-2025 | AS48: -15619.46 | AT48: 07-04-2025
A49: 4559a74a-9cab-46ae-8a2e-cca7f6d27775 | B49: 37aa09ba-614d-437d-896b-7e793c9564b6 | C49: 2baaf793-b9bb-3b7d-989b-ed1207b5da2f | D49: Reconciled | E49: Invoice Number Matched | F49: ledger | G49: 16-02-2026 | H49: GJ2501046999 | I49: invoice | J49: MA | K49: NITROGEN USP - NF /Ph.Eur./IH | L49: -30658.24 | M49: ledger | N49: 16-02-2026 | O49: GJ2501046999 | P49: invoice | Q49: RV | S49: 30658.24 | T49: 0 | U49: PRI-INV1.5_A-company | V49: 03-Aug-26 04:10 PM | X49: AAACI5569D | Z49: 7053062346 | AB49: 0 | AD49: EPL | AE49: 714213 | AF49: 6000017289 | AG49: EP00 | AH49: GJ2501046999 | AI49: GJ2501046999 | AJ49: II | AK49: 2025/11 | AL49: EP22 | AM49: 7200 | AN49: 19-02-2026 | AO49: -30658.240000000002 | AP49: INR | AQ49: INR | AR49: 19-02-2026 | AS49: -25981.56 | AT49: 17-02-2026
A50: 0e45f064-3797-4c0e-89c5-e92924d7ec20 | B50: d9e50e21-93e3-4e83-af33-8aa1a437811a | C50: 2bf3d35c-0695-348d-8036-e47f38e4ac54 | D50: Reconciled | E50: Date and Amount Matched | F50: ledger | G50: 09-09-2025 | H50: 7053027572 | I50: payment | J50: KZ | L50: 18012.3 | M50: ledger | N50: 09-09-2025 | P50: payment | Q50: DZ | R50: /103010300003186-AXIS Bank | S50: -18012.3 | T50: 0 | U50: PRI-PAY10.1-company | V50: 03-Aug-26 04:10 PM | X50: AAACI5569D | Z50: 7053027572 | AB50: 0 | AD50: EPL | AE50: 708659 | AF50: 7053027572 | AG50: EP00 | AH50: 20250909-SUM10 | AI50: 20250909-SUM10 | AK50: 2025/06 | AM50: 7200 | AN50: 09-09-2025 | AO50: 18012.3 | AP50: INR | AQ50: INR | AR50: 09-09-2025 | AS50: 15264.66 | AT50: 09-09-2025
A51: dba44f58-edbc-45be-acc2-0a1e55433ab0 | B51: bd0ffaa6-2c0b-4873-afab-b0481bb67b7d | C51: 2c906a7f-372f-3571-8fc6-afbc81cfb2b3 | D51: Reconciled | E51: Invoice Number Matched | F51: ledger | G51: 09-07-2025 | H51: GJ2501014156 | I51: invoice | J51: MA | K51: NITROGEN USP - NF / IH | L51: -11728.94 | M51: ledger | N51: 10-07-2025 | O51: GJ2501014156 | P51: invoice | Q51: RV | S51: 11728.94 | T51: 0 | U51: PRI-INV1.5_A-company | V51: 03-Aug-26 04:10 PM | X51: AAACI5569D | Z51: 7053020242 | AB51: 0 | AD51: EPL | AE51: 708659 | AF51: 6000005398 | AG51: EP00 | AH51: GJ2501014156 | AI51: GJ2501014156 | AJ51: IA | AK51: 2025/04 | AL51: EP22 | AM51: 7200 | AN51: 16-07-2025 | AO51: -11728.94 | AP51: INR | AQ51: INR | AR51: 16-07-2025 | AS51: -9939.7800000000007 | AT51: 10-07-2025
A52: 50e243c3-d874-42e9-9589-713d51549ef5 | B52: b6639706-d569-4f92-8428-bf55b54dad7d | C52: 2d5c906a-1203-3fb7-8096-20038d236704 | D52: Write off / Rounding off | E52: Invoice Number Matched | F52: ledger | G52: 20-05-2025 | H52: GJ2501006762 | I52: invoice | J52: MA | K52: NITROGEN USP - NF / IH | L52: -15708 | M52: ledger | N52: 20-05-2025 | O52: GJ2501006762 | P52: invoice | Q52: RV | S52: 15708.4 | T52: 0.4 | U52: PRI-INV1.5-company | V52: 03-Aug-26 04:10 PM | X52: AAACI5569D | Z52: 7053010772 | AB52: 0 | AD52: EPL | AE52: 708659 | AF52: 6000002373 | AG52: EP00 | AH52: GJ2501006762 | AI52: GJ2501006762 | AJ52: IA | AK52: 2025/02 | AL52: EP22 | AM52: 7200 | AN52: 23-05-2025 | AO52: -15708 | AP52: INR | AQ52: INR | AR52: 23-05-2025 | AS52: -13311.8 | AT52: 20-05-2025
A53: 722c0db9-ecda-4706-90de-0441812e6b06 | B53: a420e13e-078c-4206-bd82-2bda6cc2734f | C53: 2ec57796-dc03-444c-a85b-b1fb803d2b69 | D53: Reconciled | E53: Date Range and Amount Matched | F53: ledger | G53: 27-11-2025 | H53: 7053042965 | I53: payment | J53: KZ | L53: 17802.84 | M53: ledger | N53: 28-11-2025 | P53: payment | Q53: DZ | R53: /103010300003186-AXIS Bank | S53: -17802.84 | T53: 0 | U53: PRI-PAY11.1-company | V53: 03-Aug-26 04:10 PM | X53: AAACI5569D | Z53: 7053042965 | AB53: 0 | AD53: EPL | AE53: 708659 | AF53: 7053042965 | AG53: EP00 | AH53: 20251127-SUM01 | AI53: 20251127-SUM01 | AK53: 2025/08 | AM53: 7200 | AN53: 27-11-2025 | AO53: 17802.84 | AP53: INR | AQ53: INR | AR53: 27-11-2025 | AS53: 15087.16 | AT53: 27-11-2025
A54: 86e87b94-b975-40a2-9d54-dd106f2fe5b2 | B54: add63111-5ede-43b7-9659-af9ce20fc7a7 | C54: 2f718e6b-0f70-30c0-a673-404842d3c309 | D54: Reconciled | E54: Invoice Number Matched | F54: ledger | G54: 28-06-2025 | H54: GJ2501012386 | I54: invoice | J54: MA | K54: NITROGEN USP - NF / IH | L54: -15708.4 | M54: ledger | N54: 28-06-2025 | O54: GJ2501012386 | P54: invoice | Q54: RV | S54: 15708.4 | T54: 0 | U54: PRI-INV1.5_A-company | V54: 03-Aug-26 04:10 PM | X54: AAACI5569D | Z54: 7053016715 | AB54: 0 | AD54: EPL | AE54: 708659 | AF54: 6000004568 | AG54: EP00 | AH54: GJ2501012386 | AI54: GJ2501012386 | AJ54: IA | AK54: 2025/04 | AL54: EP22 | AM54: 7200 | AN54: 02-07-2025 | AO54: -15708.4 | AP54: INR | AQ54: INR | AR54: 02-07-2025 | AS54: -13312.2 | AT54: 28-06-2025
A55: 4874821a-8b6f-4048-bd07-738bb8486432 | B55: 8ac8f77e-3b4d-4238-9fa3-540b0d0726de | C55: 3033653d-2911-4521-a24c-412461f7be28 | D55: Reconciled | E55: Date Range and Amount Matched | F55: ledger | G55: 26-05-2025 | H55: 7053009064 | I55: payment | J55: KZ | L55: 77074.94 | M55: ledger | N55: 27-05-2025 | P55: payment | Q55: DZ | R55: /103010300003186-AXIS Bank | S55: -77074.94 | T55: 0 | U55: PRI-PAY11.1-company | V55: 03-Aug-26 04:10 PM | X55: AAACI5569D | Z55: 7053009064 | AB55: 0 | AD55: EPL | AE55: 708659 | AF55: 7053009064 | AG55: EP00 | AH55: 20250526-SUM01 | AI55: 20250526-SUM01 | AK55: 2025/02 | AM55: 7200 | AN55: 26-05-2025 | AO55: 77074.94 | AP55: INR | AQ55: INR | AR55: 26-05-2025 | AS55: 65317.599999999999 | AT55: 26-05-2025
A56: 5128b1e3-821f-40b5-8a6b-0ebf8fd4a83e | B56: d2958990-d0ac-4257-ab84-d028361b59e4 | C56: 3086b972-83b0-3dc8-88f3-dad7b281723a | D56: Reconciled | E56: Invoice Number Matched | F56: ledger | G56: 16-04-2025 | H56: GJ2501002744 | I56: invoice | J56: MA | K56: NITROGEN USP - NF / IH | L56: -17174.51 | M56: ledger | N56: 21-04-2025 | O56: GJ2501002744 | P56: invoice | Q56: RV | S56: 17174.51 | T56: 0 | U56: PRI-INV1.5_A-company | V56: 03-Aug-26 04:10 PM | X56: AAACI5569D | Z56: 7053005095 | AB56: 0 | AD56: EPL | AE56: 708659 | AF56: 6000001206 | AG56: EP00 | AH56: GJ2501002744 | AI56: GJ2501002744 | AJ56: IA | AK56: 2025/02 | AL56: EP22 | AM56: 7200 | AN56: 02-05-2025 | AO56: -17174.509999999998 | AP56: INR | AQ56: INR | AR56: 02-05-2025 | AS56: -14554.67 | AT56: 18-04-2025
A57: 979829ce-e635-47ba-ae76-0cbef67b5b22 | B57: 224035a9-72ee-46aa-a52e-3bd1c704baab | C57: 31aedadb-a547-3763-8812-c616b17cb02b | D57: Reconciled | E57: Amount Matched - Recommended | F57: ledger | G57: 12-06-2025 | H57: 7053012268 | I57: payment | J57: KZ | L57: 17383.97 | M57: ledger | N57: 12-06-2025 | P57: payment | Q57: DZ | R57: /103010300003186-AXIS Bank | S57: -17383.97 | T57: 0 | U57: SEC-PAY1.1-company | V57: 03-Aug-26 04:10 PM | X57: AAACI5569D | Z57: 7053012268 | AB57: 0 | AD57: EPL | AE57: 708659 | AF57: 7053012268 | AG57: EP00 | AH57: 20250612-SUM04 | AI57: 20250612-SUM04 | AK57: 2025/03 | AM57: 7200 | AN57: 12-06-2025 | AO57: 17383.97 | AP57: INR | AQ57: INR | AR57: 12-06-2025 | AS57: 14732.17 | AT57: 12-06-2025
A58: f7f78907-992c-4b39-ae2a-12b541739ab6 | B58: c4be4ff9-a80c-46b7-bd05-27ea7aaa83b4 | C58: 331dfe8f-9e42-3482-aef4-0743fe086906 | D58: Write off / Rounding off | E58: Invoice Number Matched | F58: ledger | G58: 01-10-2025 | H58: GJ2501026264 | I58: invoice | J58: MA | K58: NITROGEN USP - NF / IH | L58: -15498 | M58: ledger | N58: 01-10-2025 | O58: GJ2501026264 | P58: invoice | Q58: RV | S58: 15498.94 | T58: 0.94 | U58: PRI-INV1.5-company | V58: 03-Aug-26 04:10 PM | X58: AAACI5569D | Z58: 7053035181 | AB58: 0 | AD58: EPL | AE58: 708659 | AF58: 6000009991 | AG58: EP00 | AH58: GJ2501026264 | AI58: GJ2501026264 | AJ58: II | AK58: 2025/07 | AL58: EP22 | AM58: 7200 | AN58: 09-10-2025 | AO58: -15498 | AP58: INR | AQ58: INR | AR58: 09-10-2025 | AS58: -13133.76 | AT58: 01-10-2025
A59: 726e3e48-7e4a-49ba-b30b-40c1f586d9b5 | B59: 00568bd6-dc1e-4c1b-b3af-d340c62e09d7 | C59: 338d9c62-09dc-3c11-a8d5-39599d1733b2 | D59: Reconciled | E59: Invoice Number Matched | F59: ledger | G59: 31-12-2025 | H59: GJ2501039628 | I59: invoice | J59: MA | K59: NITROGEN USP - NF / IH | L59: -15498.94 | M59: ledger | N59: 31-12-2025 | O59: GJ2501039628 | P59: invoice | Q59: RV | S59: 15498.94 | T59: 0 | U59: PRI-INV1.5_A-company | V59: 03-Aug-26 04:10 PM | X59: AAACI5569D | Z59: 7053053526 | AB59: 0 | AD59: EPL | AE59: 708659 | AF59: 6000014931 | AG59: EP00 | AH59: GJ2501039628 | AI59: GJ2501039628 | AJ59: II | AK59: 2025/10 | AL59: EP22 | AM59: 7200 | AN59: 05-01-2026 | AO59: -15498.94 | AP59: INR | AQ59: INR | AR59: 05-01-2026 | AS59: -13134.7 | AT59: 03-01-2026
A60: e2e78c86-5769-489a-95b6-7a69b37ccbb3 | B60: ed5f093d-b0b9-4f43-8d87-76bb5137cd8e | C60: 33c678a2-3ff4-34d2-84a9-6a46355e55ef | D60: Reconciled | E60: Invoice Number Matched | F60: ledger | G60: 24-09-2025 | H60: GJ2501025447 | I60: invoice | J60: MA | K60: NITROGEN USP - NF / IH | L60: -16755.62 | M60: ledger | N60: 25-09-2025 | O60: GJ2501025447 | P60: invoice | Q60: RV | S60: 16755.62 | T60: 0 | U60: PRI-INV1.5_A-company | V60: 03-Aug-26 04:10 PM | X60: AAACI5569D | Z60: 7053034627 | AB60: 0 | AD60: EPL | AE60: 708659 | AF60: 6000009605 | AG60: EP00 | AH60: GJ2501025447 | AI60: GJ2501025447 | AJ60: II | AK60: 2025/06 | AL60: EP22 | AM60: 7200 | AN60: 27-09-2025 | AO60: -16755.62 | AP60: INR | AQ60: INR | AR60: 27-09-2025 | AS60: -14199.68 | AT60: 25-09-2025
A61: 5b750413-990c-4a2f-9f00-8d7f87e8b46f | B61: e6db5089-f0a8-43d7-965e-c5dacecd225b | C61: 34c3a83c-d3f5-3784-8d65-c351d2fed8e3 | D61: Write off / Rounding off | E61: Invoice Number Matched | F61: ledger | G61: 21-06-2025 | H61: GJ2501011374 | I61: invoice | J61: MA | K61: NITROGEN USP - NF / IH | L61: -18012.13 | M61: ledger | N61: 21-06-2025 | O61: GJ2501011374 | P61: invoice | Q61: RV | S61: 18012.3 | T61: 0.17 | U61: PRI-INV1.5-company | V61: 03-Aug-26 04:10 PM | X61: AAACI5569D | Z61: 7053015732 | AB61: 0 | AD61: EPL | AE61: 708659 | AF61: 6000003818 | AG61: EP00 | AH61: GJ2501011374 | AI61: GJ2501011374 | AJ61: IA | AK61: 2025/03 | AL61: EP22 | AM61: 7200 | AN61: 23-06-2025 | AO61: -18012.13 | AP61: INR | AQ61: INR | AR61: 23-06-2025 | AS61: -15264.49 | AT61: 21-06-2025
A62: aa5044c3-72d9-49f0-8250-cd3a143b1358 | B62: 667e6cec-f0c6-4b8b-a573-7b26452bfcb2 | C62: 367b342f-0dad-3717-991f-4d5a8dfcdffb | D62: Reconciled | E62: Date and Amount Matched | F62: ledger | G62: 07-04-2025 | H62: 7053000733 | I62: payment | J62: KZ | L62: 14661 | M62: ledger | N62: 07-04-2025 | P62: payment | Q62: DZ | R62: /103010300003186-AXIS Bank | S62: -14661 | T62: 0 | U62: PRI-PAY10.1-company | V62: 03-Aug-26 04:10 PM | X62: AAACI5569D | Z62: 7053000733 | AB62: 0 | AD62: EPL | AE62: 708659 | AF62: 7053000733 | AG62: EP00 | AH62: 20250407-SUM02 | AI62: 20250407-SUM02 | AK62: 2025/01 | AM62: 7200 | AN62: 07-04-2025 | AO62: 14661 | AP62: INR | AQ62: INR | AR62: 07-04-2025 | AS62: 12424.56 | AT62: 07-04-2025
A63: 17abf5e4-adc0-42da-a569-1e1a92b93363 | B63: 7f6c43cc-cd75-4b99-899e-c5e68e28a3e5 | C63: 369de95c-8bbf-3da8-acd6-9f0ebfd17645 | D63: Reconciled | E63: Invoice Number Matched | F63: ledger | G63: 09-06-2025 | H63: GJ2501009544 | I63: invoice | J63: MA | K63: NITROGEN USP - NF / IH | L63: -18640.62 | M63: ledger | N63: 09-06-2025 | O63: GJ2501009544 | P63: invoice | Q63: RV | S63: 18640.62 | T63: 0 | U63: PRI-INV1.5_A-company | V63: 03-Aug-26 04:10 PM | X63: AAACI5569D | Z63: 7053013917 | AB63: 0 | AD63: EPL | AE63: 708659 | AF63: 6000003313 | AG63: EP00 | AH63: GJ2501009544 | AI63: GJ2501009544 | AJ63: IA | AK63: 2025/03 | AL63: EP22 | AM63: 7200 | AN63: 12-06-2025 | AO63: -18640.62 | AP63: INR | AQ63: INR | AR63: 12-06-2025 | AS63: -15797.14 | AT63: 09-06-2025
A64: b012a4f4-d99a-4567-adbb-fe23a26b24e2 | B64: 248218c7-0cd1-4ae3-8033-2ffc1c97d3c0 | C64: 37501d95-96eb-33fc-b7bc-dd6012e96168 | D64: Reconciled | E64: Date and Amount Matched | F64: ledger | G64: 28-01-2026 | H64: 7053055132 | I64: payment | J64: KZ | L64: 68858.83 | M64: ledger | N64: 28-01-2026 | P64: payment | Q64: DZ | R64: /103010300003186-AXIS Bank | S64: -68858.83 | T64: 0 | U64: PRI-PAY10.1-company | V64: 03-Aug-26 04:10 PM | X64: AAACI5569D | Z64: 7053055132 | AB64: 0 | AD64: EPL | AE64: 708659 | AF64: 7053055132 | AG64: EP00 | AH64: 20260128-SUM01 | AI64: 20260128-SUM01 | AK64: 2025/10 | AM64: 7200 | AN64: 28-01-2026 | AO64: 68858.83 | AP64: INR | AQ64: INR | AR64: 28-01-2026 | AS64: 58473.55 | AT64: 28-01-2026
A65: 7179af8c-785d-4080-be91-b93e167103c2 | B65: 7f039d79-63ad-4c68-be29-ea12fea2eeb7 | C65: 3865b9a0-1cd4-32fc-bc81-f094f4d81ef0 | D65: Reconciled | E65: Date and Amount Matched | F65: ledger | G65: 08-12-2025 | H65: 7053044775 | I65: payment | J65: KZ | L65: 31416.8 | M65: ledger | N65: 08-12-2025 | P65: payment | Q65: DZ | R65: /103010300003186-AXIS Bank | S65: -31416.8 | T65: 0 | U65: PRI-PAY10.1-company | V65: 03-Aug-26 04:10 PM | X65: AAACI5569D | Z65: 7053044775 | AB65: 0 | AD65: EPL | AE65: 708659 | AF65: 7053044775 | AG65: EP00 | AH65: 20251208-SUM01 | AI65: 20251208-SUM01 | AK65: 2025/09 | AM65: 7200 | AN65: 08-12-2025 | AO65: 31416.799999999999 | AP65: INR | AQ65: INR | AR65: 08-12-2025 | AS65: 26624.400000000001 | AT65: 08-12-2025
A66: 6d46c81e-6183-4171-ae61-0895e15cdd5d | B66: a52564ee-a236-4ebe-88a0-a27bbdd29e22 | C66: 39089514-9c00-33a3-8e18-3e3ebcb562f8 | D66: Reconciled | E66: Invoice Number Matched | F66: ledger | G66: 11-12-2025 | H66: GJ2501036517 | I66: invoice | J66: MA | K66: NITROGEN USP - NF / IH | L66: -14451.72 | M66: ledger | N66: 12-12-2025 | O66: GJ2501036517 | P66: invoice | Q66: RV | S66: 14451.72 | T66: 0 | U66: PRI-INV1.5_A-company | V66: 03-Aug-26 04:10 PM | X66: AAACI5569D | Z66: 7053048840 | AB66: 0 | AD66: EPL | AE66: 708659 | AF66: 6000013553 | AG66: EP00 | AH66: GJ2501036517 | AI66: GJ2501036517 | AJ66: II | AK66: 2025/09 | AL66: EP22 | AM66: 7200 | AN66: 18-12-2025 | AO66: -14451.72 | AP66: INR | AQ66: INR | AR66: 18-12-2025 | AS66: -12247.22 | AT66: 12-12-2025
A67: e91e08fa-2ccd-42e4-8b68-0c929dce7afd | B67: 4a95c6e1-8a5f-49b3-8486-af53832836a6 | C67: 3ac8c05a-f1ef-3723-a1d5-52b6ea984359 | D67: Reconciled | E67: Invoice Number Matched | F67: ledger | G67: 14-07-2025 | H67: GJ2501014856 | I67: invoice | J67: MA | K67: NITROGEN USP - NF / IH | L67: -13613.94 | M67: ledger | N67: 15-07-2025 | O67: GJ2501014856 | P67: invoice | Q67: RV | S67: 13613.94 | T67: 0 | U67: PRI-INV1.5_A-company | V67: 03-Aug-26 04:10 PM | X67: AAACI5569D | Z67: 7053021010 | AB67: 0 | AD67: EPL | AE67: 708659 | AF67: 6000005403 | AG67: EP00 | AH67: GJ2501014856 | AI67: GJ2501014856 | AJ67: IA | AK67: 2025/04 | AL67: EP22 | AM67: 7200 | AN67: 16-07-2025 | AO67: -13613.94 | AP67: INR | AQ67: INR | AR67: 16-07-2025 | AS67: -11537.24 | AT67: 16-07-2025
A68: d2efe3f8-aad6-4f6d-8465-4064cfb11fed | B68: 2c81b926-785d-491f-8edf-fafd643ad1b9 | C68: 3bebb504-b542-3e83-8a56-2da499f958e8 | D68: Reconciled | E68: Date and Amount Matched | F68: ledger | G68: 07-08-2025 | H68: 7053022562 | I68: payment | J68: KZ | L68: 30788.45 | M68: ledger | N68: 07-08-2025 | P68: payment | Q68: DZ | R68: /103010300003186-AXIS Bank | S68: -30788.45 | T68: 0 | U68: PRI-PAY10.1-company | V68: 03-Aug-26 04:10 PM | X68: AAACI5569D | Z68: 7053022562 | AB68: 0 | AD68: EPL | AE68: 708659 | AF68: 7053022562 | AG68: EP00 | AH68: 20250807-SUM10 | AI68: 20250807-SUM10 | AK68: 2025/05 | AM68: 7200 | AN68: 07-08-2025 | AO68: 30788.45 | AP68: INR | AQ68: INR | AR68: 07-08-2025 | AS68: 26091.91 | AT68: 07-08-2025
A69: a5f6e2bf-26c8-4d30-b8ab-0b3e63f4c759 | B69: fe6fa99b-e253-43c2-8022-049bcf722a74 | C69: 3cbbde46-8a5d-3472-aa39-d43d5f4a07cc | D69: Reconciled | E69: Invoice Number Matched | F69: ledger | G69: 16-07-2025 | H69: GJ2501015206 | I69: invoice | J69: MA | K69: NITROGEN USP - NF / IH | L69: -14032.83 | M69: ledger | N69: 17-07-2025 | O69: GJ2501015206 | P69: invoice | Q69: RV | S69: 14032.83 | T69: 0 | U69: PRI-INV1.5_A-company | V69: 03-Aug-26 04:10 PM | X69: AAACI5569D | Z69: 7053021010 | AB69: 0 | AD69: EPL | AE69: 708659 | AF69: 6000005673 | AG69: EP00 | AH69: GJ2501015206 | AI69: GJ2501015206 | AJ69: IA | AK69: 2025/04 | AL69: EP22 | AM69: 7200 | AN69: 21-07-2025 | AO69: -14032.83 | AP69: INR | AQ69: INR | AR69: 21-07-2025 | AS69: -11892.23 | AT69: 18-07-2025
A70: 445b7f67-d19f-457d-803d-fb18f6d91269 | B70: d5559696-2893-481b-8e2f-b20577a41836 | C70: 3e337e96-bec6-340d-8686-e14f0ed2aac2 | D70: Reconciled | E70: Invoice Number Matched | F70: ledger | G70: 02-07-2025 | H70: GJ2501012966 | I70: invoice | J70: MA | K70: NITROGEN USP - NF / IH | L70: -9843.93 | M70: ledger | N70: 02-07-2025 | O70: GJ2501012966 | P70: invoice | Q70: RV | S70: 9843.93 | T70: 0 | U70: PRI-INV1.5_A-company | V70: 03-Aug-26 04:10 PM | X70: AAACI5569D | Z70: 7053018641 | AB70: 0 | AD70: EPL | AE70: 708659 | AF70: 6000004871 | AG70: EP04 | AH70: GJ2501012966 | AI70: GJ2501012966 | AJ70: IA | AK70: 2025/04 | AL70: EP22 | AM70: 7200 | AN70: 08-07-2025 | AO70: -9843.93 | AP70: INR | AQ70: INR | AR70: 08-07-2025 | AS70: -8342.31 | AT70: 02-07-2025
A71: 51c4d377-b950-44ce-85ed-e8bd8913041f | B71: 480cd4a5-aee7-40a5-a1fa-cd4b2f5dc226 | C71: 3e39b585-06d1-3a01-9512-a8d8aa0f50cd | D71: Reconciled | E71: Date and Amount Matched | F71: ledger | G71: 23-06-2025 | H71: 7053013917 | I71: payment | J71: KZ | L71: 18640.62 | M71: ledger | N71: 23-06-2025 | P71: payment | Q71: DZ | R71: /103010300003186-AXIS Bank | S71: -18640.62 | T71: 0 | U71: PRI-PAY10.1-company | V71: 03-Aug-26 04:10 PM | X71: AAACI5569D | Z71: 7053013917 | AB71: 0 | AD71: EPL | AE71: 708659 | AF71: 7053013917 | AG71: EP00 | AH71: 20250623-SUM04 | AI71: 20250623-SUM04 | AK71: 2025/03 | AM71: 7200 | AN71: 23-06-2025 | AO71: 18640.62 | AP71: INR | AQ71: INR | AR71: 23-06-2025 | AS71: 15797.14 | AT71: 23-06-2025
A72: 299df891-5c36-44e0-8268-8a155c0997fe | B72: be633a3d-e661-4e3b-bbf1-a84477f386ec | C72: 3ee29f42-8022-393e-9ab6-62cc6373aba9 | D72: Write off / Rounding off | E72: Invoice Number Matched | F72: ledger | G72: 29-04-2025 | H72: GJ2501003850 | I72: invoice | J72: MA | K72: NITROGEN USP - NF / IH | L72: -20106 | M72: ledger | N72: 29-04-2025 | O72: GJ2501003850 | P72: invoice | Q72: RV | S72: 20106.76 | T72: 0.76 | U72: PRI-INV1.5-company | V72: 03-Aug-26 04:10 PM | X72: AAACI5569D | Z72: 7053006160 | AB72: 0 | AD72: EPL | AE72: 708659 | AF72: 6000001516 | AG72: EP00 | AH72: GJ2501003850 | AI72: GJ2501003850 | AJ72: IA | AK72: 2025/02 | AL72: EP22 | AM72: 7200 | AN72: 08-05-2025 | AO72: -20106 | AP72: INR | AQ72: INR | AR72: 08-05-2025 | AS72: -17038.86 | AT72: 29-04-2025
A73: 12017f7d-e0a2-4816-ae07-cc6dbcc9393f | B73: 13856ba4-3a38-42b6-aa0c-280ba8ba07b8 | C73: 4028399e-6228-37fb-9053-64cb78f74f5b | D73: Write off / Rounding off | E73: Invoice Number Matched | F73: ledger | G73: 17-05-2025 | H73: GJ2501006317 | I73: invoice | J73: MA | K73: NITROGEN USP - NF / IH | L73: -15708 | M73: ledger | N73: 17-05-2025 | O73: GJ2501006317 | P73: invoice | Q73: RV | S73: 15708.4 | T73: 0.4 | U73: PRI-INV1.5-company | V73: 03-Aug-26 04:10 PM | X73: AAACI5569D | Z73: 7053010446 | AB73: 0 | AD73: EPL | AE73: 708659 | AF73: 6000002371 | AG73: EP00 | AH73: GJ2501006317 | AI73: GJ2501006317 | AJ73: IA | AK73: 2025/02 | AL73: EP22 | AM73: 7200 | AN73: 23-05-2025 | AO73: -15708 | AP73: INR | AQ73: INR | AR73: 23-05-2025 | AS73: -13311.8 | AT73: 16-05-2025
A74: 92e05181-f539-4134-8067-88279d4f80f1 | B74: e1289306-5bfe-4a3e-af69-7dc1573dde69 | C74: 405e905c-7830-3854-a757-ce2e16e96475 | D74: Write off / Rounding off | E74: Invoice Number Matched | F74: ledger | G74: 08-02-2026 | H74: GJ2501045608 | I74: invoice | J74: MA | K74: NITROGEN USP - NF /Ph.Eur./IH | L74: -34947.99 | M74: ledger | N74: 08-02-2026 | O74: GJ2501045608 | P74: invoice | Q74: RV | S74: 34947.88 | T74: -0.11 | U74: PRI-INV1.5-company | V74: 03-Aug-26 04:10 PM | X74: AAACI5569D | Z74: 7053062135 | AB74: 0 | AD74: EPL | AE74: 714213 | AF74: 6000016816 | AG74: EP00 | AH74: GJ2501045608 | AI74: GJ2501045608 | AJ74: II | AK74: 2025/11 | AL74: EP22 | AM74: 7200 | AN74: 10-02-2026 | AO74: -34947.99 | AP74: INR | AQ74: INR | AR74: 10-02-2026 | AS74: -29616.95 | AT74: 10-02-2026
A75: 429824a6-3bee-472e-8e83-7b61527ed135 | B75: 03d61b08-0128-41ee-b955-5c4ff5560faa | C75: 40b161a7-aa6d-3a52-baad-50d925135767 | D75: Reconciled | E75: Date and Amount Matched | F75: ledger | G75: 09-05-2025 | H75: 7053006160 | I75: payment | J75: KZ | L75: 40841 | M75: ledger | N75: 09-05-2025 | P75: payment | Q75: DZ | R75: /103010300003186-AXIS Bank | S75: -40841 | T75: 0 | U75: PRI-PAY10.1-company | V75: 03-Aug-26 04:10 PM | X75: AAACI5569D | Z75: 7053006160 | AB75: 0 | AD75: EPL | AE75: 708659 | AF75: 7053006160 | AG75: EP00 | AH75: 20250509-SUM01 | AI75: 20250509-SUM01 | AK75: 2025/02 | AM75: 7200 | AN75: 09-05-2025 | AO75: 40841 | AP75: INR | AQ75: INR | AR75: 09-05-2025 | AS75: 34610.879999999997 | AT75: 09-05-2025
A76: 7227bd2e-5d20-4045-ac53-03f4311411da | B76: 011cc82e-ce12-4f07-9b59-8cb23954081c | C76: 411bb97f-154a-3e93-838a-aaf7cfc38ffc | D76: Reconciled | E76: Date and Amount Matched | F76: ledger | G76: 29-08-2025 | H76: 7053026128 | I76: payment | J76: KZ | L76: 56131.33 | M76: ledger | N76: 29-08-2025 | P76: payment | Q76: DZ | R76: /103010300003186-AXIS Bank | S76: -56131.33 | T76: 0 | U76: PRI-PAY10.1-company | V76: 03-Aug-26 04:10 PM | X76: AAACI5569D | Z76: 7053026128 | AB76: 0 | AD76: EPL | AE76: 708659 | AF76: 7053026128 | AG76: EP00 | AH76: 20250829-SUM11 | AI76: 20250829-SUM11 | AK76: 2025/05 | AM76: 7200 | AN76: 29-08-2025 | AO76: 56131.33 | AP76: INR | AQ76: INR | AR76: 29-08-2025 | AS76: 47568.93 | AT76: 29-08-2025
A77: f02a8155-c2c9-419b-8a84-90824a3161b1 | B77: 30061288-e954-489e-a6dd-8a6fee6238bb | C77: 41468cf6-499f-360d-a95c-d3e680c3880e | D77: Reconciled | E77: Invoice Number Matched | F77: ledger | G77: 24-07-2025 | H77: GJ2501016291 | I77: invoice | J77: MA | K77: NITROGEN USP - NF / IH | L77: -15289.51 | M77: ledger | N77: 24-07-2025 | O77: GJ2501016291 | P77: invoice | Q77: RV | S77: 15289.51 | T77: 0 | U77: PRI-INV1.5_A-company | V77: 03-Aug-26 04:10 PM | X77: AAACI5569D | Z77: 7053021635 | AB77: 0 | AD77: EPL | AE77: 708659 | AF77: 6000006307 | AG77: EP00 | AH77: GJ2501016291 | AI77: GJ2501016291 | AJ77: IA | AK77: 2025/04 | AL77: EP22 | AM77: 7200 | AN77: 29-07-2025 | AO77: -15289.51 | AP77: INR | AQ77: INR | AR77: 29-07-2025 | AS77: -12957.21 | AT77: 24-07-2025
A78: 6cfc14f2-d8b2-458f-84a8-13a664a40bf9 | B78: 36383fda-2536-486d-8a06-4c54ac6b2d9f | C78: 422c201a-3f2b-459b-b0bf-c9fad3749a98 | D78: Reconciled | E78: Date Range and Amount Matched | F78: ledger | G78: 19-12-2025 | H78: 7053047188 | I78: payment | J78: KZ | L78: 55712.45 | M78: ledger | N78: 20-12-2025 | P78: payment | Q78: DZ | R78: /103010300003186-AXIS Bank | S78: -55712.45 | T78: 0 | U78: PRI-PAY11.1-company | V78: 03-Aug-26 04:10 PM | X78: AAACI5569D | Z78: 7053047188 | AB78: 0 | AD78: EPL | AE78: 708659 | AF78: 7053047188 | AG78: EP00 | AH78: 20251219-SUM03 | AI78: 20251219-SUM03 | AK78: 2025/09 | AM78: 7200 | AN78: 19-12-2025 | AO78: 55712.45 | AP78: INR | AQ78: INR | AR78: 19-12-2025 | AS78: 47213.93 | AT78: 19-12-2025
A79: caaac7bb-3d7b-426a-bd47-f7ca2b2ca12e | B79: f4887775-c01f-434a-b7ab-bbaff4b2af8d | C79: 4258a712-3364-3661-a4eb-efd25500f7f1 | D79: Reconciled | E79: Date and Amount Matched | F79: ledger | G79: 24-06-2025 | H79: 7053014041 | I79: payment | J79: KZ | L79: 16336.73 | M79: ledger | N79: 24-06-2025 | P79: payment | Q79: DZ | R79: /103010300003186-AXIS Bank | S79: -16336.73 | T79: 0 | U79: PRI-PAY10.1-company | V79: 03-Aug-26 04:10 PM | X79: AAACI5569D | Z79: 7053014041 | AB79: 0 | AD79: EPL | AE79: 708659 | AF79: 7053014041 | AG79: EP00 | AH79: 20250624-SUM05 | AI79: 20250624-SUM05 | AK79: 2025/03 | AM79: 7200 | AN79: 24-06-2025 | AO79: 16336.73 | AP79: INR | AQ79: INR | AR79: 24-06-2025 | AS79: 13844.69 | AT79: 24-06-2025
A80: 65aa8dff-1376-4869-af0c-382cf1e6e5c6 | B80: e62e73b4-31f6-4fa3-86af-0b2d4172bd26 | C80: 430c2daa-96dc-47be-99ab-87604ffb30fc | D80: Reconciled | E80: Date Range and Amount Matched | F80: ledger | G80: 12-12-2025 | H80: 7053045773 | I80: payment | J80: KZ | L80: 15498.94 | M80: ledger | N80: 13-12-2025 | P80: payment | Q80: DZ | R80: /103010300003186-AXIS Bank | S80: -15498.94 | T80: 0 | U80: PRI-PAY11.1-company | V80: 03-Aug-26 04:10 PM | X80: AAACI5569D | Z80: 7053045773 | AB80: 0 | AD80: EPL | AE80: 708659 | AF80: 7053045773 | AG80: EP00 | AH80: 20251212-SUM10 | AI80: 20251212-SUM10 | AK80: 2025/09 | AM80: 7200 | AN80: 12-12-2025 | AO80: 15498.94 | AP80: INR | AQ80: INR | AR80: 12-12-2025 | AS80: 13134.7 | AT80: 12-12-2025
A81: f417295e-a26e-4b0b-8536-d088044f9206 | B81: 90decac3-c007-463c-b2e3-0d4d1c8ef9f5 | C81: 43fca39c-9fdf-311e-8790-32782d803e11 | D81: Write off / Rounding off | E81: Invoice Number Matched | F81: ledger | G81: 04-06-2025 | H81: GJ2501008861 | I81: invoice | J81: MA | K81: NITROGEN USP - NF / IH | L81: -16965 | M81: ledger | N81: 04-06-2025 | O81: GJ2501008861 | P81: invoice | Q81: RV | S81: 16965.08 | T81: 0.08 | U81: PRI-INV1.5-company | V81: 03-Aug-26 04:10 PM | X81: AAACI5569D | Z81: 7053013154 | AB81: 0 | AD81: EPL | AE81: 708659 | AF81: 6000003291 | AG81: EP00 | AH81: GJ2501008861 | AI81: GJ2501008861 | AJ81: IA | AK81: 2025/03 | AL81: EP22 | AM81: 7200 | AN81: 12-06-2025 | AO81: -16965 | AP81: INR | AQ81: INR | AR81: 12-06-2025 | AS81: -14377.1 | AT81: 04-06-2025
A82: 8b502d15-5682-4eb9-a85a-932ea778ecbb | B82: d7114fcf-c942-4062-861b-43079d764eb6 | C82: 4810ed6e-2ccb-30dc-b33a-dbff414ba958 | D82: Reconciled | E82: Invoice Number Matched | F82: ledger | G82: 12-11-2025 | H82: GJ2501032001 | I82: invoice | J82: MA | K82: NITROGEN USP - NF / IH | L82: -17802.84 | M82: ledger | N82: 12-11-2025 | O82: GJ2501032001 | P82: invoice | Q82: RV | S82: 17802.84 | T82: 0 | U82: PRI-INV1.5_A-company | V82: 03-Aug-26 04:10 PM | X82: AAACI5569D | Z82: 7053042965 | AB82: 0 | AD82: EPL | AE82: 708659 | AF82: 6000012153 | AG82: EP00 | AH82: GJ2501032001 | AI82: GJ2501032001 | AJ82: II | AK82: 2025/08 | AL82: EP22 | AM82: 7200 | AN82: 26-11-2025 | AO82: -17802.84 | AP82: INR | AQ82: INR | AR82: 26-11-2025 | AS82: -15087.16 | AT82: 13-11-2025
A83: 8892d256-1a53-4ce1-9e10-7f2afbb1e474 | B83: c31480e2-c11d-45fd-b3f1-873b1bfefbb5 | C83: 485d353d-a753-3678-9ddf-ae5b03db9240 | D83: Reconciled | E83: Date and Amount Matched | F83: ledger | G83: 09-06-2025 | H83: 7053011477 | I83: payment | J83: KZ | L83: 25761.76 | M83: ledger | N83: 09-06-2025 | P83: payment | Q83: DZ | R83: /103010300003186-AXIS Bank | S83: -25761.76 | T83: 0 | U83: PRI-PAY10.1-company | V83: 03-Aug-26 04:10 PM | X83: AAACI5569D | Z83: 7053011477 | AB83: 0 | AD83: EPL | AE83: 708659 | AF83: 7053011477 | AG83: EP00 | AH83: 20250609-SUM01 | AI83: 20250609-SUM01 | AK83: 2025/03 | AM83: 7200 | AN83: 09-06-2025 | AO83: 25761.759999999998 | AP83: INR | AQ83: INR | AR83: 09-06-2025 | AS83: 21832 | AT83: 09-06-2025
A84: 75ad78e0-6116-4edf-8d19-b1b338f57b24 | B84: 6d2ed575-497a-4725-bf82-47e43c8f4bb5 | C84: 49ce9eaa-ec64-3130-b1ff-226ce827ee33 | D84: Reconciled | E84: Invoice Number Matched | F84: ledger | G84: 19-03-2026 | H84: GJ2501051758 | I84: invoice | J84: MA | K84: NITROGEN USP - NF /Ph.Eur./IH | L84: -34190.88 | M84: ledger | N84: 19-03-2026 | O84: GJ2501051758 | P84: invoice | Q84: RV | S84: 34190.88 | T84: 0 | U84: PRI-INV1.5_A-company | V84: 03-Aug-26 04:10 PM | X84: AAACI5569D | Z84: 7053000264 | AB84: 0 | AD84: EPL | AE84: 714213 | AF84: 6000018931 | AG84: EP00 | AH84: GJ2501051758 | AI84: GJ2501051758 | AJ84: II | AK84: 2025/12 | AL84: EP22 | AM84: 7200 | AN84: 20-03-2026 | AO84: -34190.879999999997 | AP84: INR | AQ84: INR | AR84: 20-03-2026 | AS84: -28975.32 | AT84: 18-03-2026
A85: 4b75f1d2-1b83-4949-9a4c-2ede2ebf6d9e | B85: a9f0b56a-be17-4d38-be18-149aa2b56ccd | C85: 4a0f260d-818c-37a2-bef5-2510e4e19c5f | D85: Reconciled | E85: Invoice Number Matched | F85: ledger | G85: 22-07-2025 | H85: GJ2501015920 | I85: invoice | J85: MA | K85: NITROGEN USP - NF / IH | L85: -16755.62 | M85: ledger | N85: 22-07-2025 | O85: GJ2501015920 | P85: invoice | Q85: RV | S85: 16755.62 | T85: 0 | U85: PRI-INV1.5_A-company | V85: 03-Aug-26 04:10 PM | X85: AAACI5569D | Z85: 7053034319 | AB85: 0 | AD85: EPL | AE85: 708659 | AF85: 6000010085 | AG85: EP00 | AH85: GJ2501015920 | AI85: GJ2501015920 | AJ85: II | AK85: 2025/07 | AL85: EP22 | AM85: 7200 | AN85: 10-10-2025 | AO85: -16755.62 | AP85: INR | AQ85: INR | AR85: 10-10-2025 | AS85: -14199.68 | AT85: 22-07-2025
A86: 6ea56934-df6b-4ef3-90ed-c38c4e2159ce | B86: 8027dd2c-82e7-43d1-af70-cddd096b8630 | C86: 4bc190f6-0c58-323e-92d2-36430358a428 | D86: Reconciled | E86: Invoice Number Matched | F86: ledger | G86: 22-11-2025 | H86: GJ2501033609 | I86: invoice | J86: MA | K86: NITROGEN USP - NF / IH | L86: -17383.97 | M86: ledger | N86: 23-11-2025 | O86: GJ2501033609 | P86: invoice | Q86: RV | S86: 17383.97 | T86: 0 | U86: PRI-INV1.5_A-company | V86: 03-Aug-26 04:10 PM | X86: AAACI5569D | Z86: 7053044775 | AB86: 0 | AD86: EPL | AE86: 708659 | AF86: 6000012410 | AG86: EP00 | AH86: GJ2501033609 | AI86: GJ2501033609 | AJ86: II | AK86: 2025/08 | AL86: EP22 | AM86: 7200 | AN86: 28-11-2025 | AO86: -17383.97 | AP86: INR | AQ86: INR | AR86: 28-11-2025 | AS86: -14732.17 | AT86: 24-11-2025
A87: ff2ea373-c7eb-4d75-b2b9-2636cbaba25a | B87: 47465044-f66b-416a-af90-c50c7495fcef | C87: 4bcd0202-cfaa-3876-999a-5fb59de0b86f | D87: Reconciled | E87: Invoice Number Matched | F87: ledger | G87: 16-06-2025 | H87: GJ2501010575 | I87: invoice | J87: MA | K87: NITROGEN USP - NF / IH | L87: -16965.08 | M87: ledger | N87: 16-06-2025 | O87: GJ2501010575 | P87: invoice | Q87: RV | S87: 16965.08 | T87: 0 | U87: PRI-INV1.5_A-company | V87: 03-Aug-26 04:10 PM | X87: AAACI5569D | Z87: 7053015732 | AB87: 0 | AD87: EPL | AE87: 708659 | AF87: 6000003814 | AG87: EP00 | AH87: GJ2501010575 | AI87: GJ2501010575 | AJ87: IA | AK87: 2025/03 | AL87: EP22 | AM87: 7200 | AN87: 23-06-2025 | AO87: -16965.080000000002 | AP87: INR | AQ87: INR | AR87: 23-06-2025 | AS87: -14377.18 | AT87: 16-06-2025
A88: d2b9f58f-4e10-43bd-88ac-6b99c414bcd6 | B88: 3abcc4d8-81d5-475b-8379-fa306f782b5f | C88: 4cdd0cf2-d4f6-3934-b0e7-47827cb77005 | D88: Reconciled | E88: Invoice Number Matched | F88: ledger | G88: 13-06-2025 | H88: GJ2501010178 | I88: invoice | J88: MA | K88: NITROGEN USP - NF / IH | L88: -15498.94 | M88: ledger | N88: 13-06-2025 | O88: GJ2501010178 | P88: invoice | Q88: RV | S88: 15498.94 | T88: 0 | U88: PRI-INV1.5_A-company | V88: 03-Aug-26 04:10 PM | X88: AAACI5569D | Z88: 7053014217 | AB88: 0 | AD88: EPL | AE88: 708659 | AF88: 6000003813 | AG88: EP00 | AH88: GJ2501010178 | AI88: GJ2501010178 | AJ88: IA | AK88: 2025/03 | AL88: EP22 | AM88: 7200 | AN88: 23-06-2025 | AO88: -15498.94 | AP88: INR | AQ88: INR | AR88: 23-06-2025 | AS88: -13134.7 | AT88: 16-06-2025
A89: ea093ecd-a786-4e9b-bc6d-d4adbcc7c0fd | B89: 8d571869-ddbd-4526-88db-3c4245e77eab | C89: 4d9c6ad3-e24b-3101-b5c3-be7442892b67 | D89: Write off / Rounding off | E89: Invoice Number Matched | F89: ledger | G89: 20-08-2025 | H89: GJ2501019995 | I89: invoice | J89: MA | K89: NITROGEN USP - NF / IH | L89: -10891.16 | M89: ledger | N89: 20-08-2025 | O89: GJ2501019995 | P89: invoice | Q89: RV | S89: 10891.15 | T89: -0.01 | U89: PRI-INV1.5-company | V89: 03-Aug-26 04:10 PM | X89: AAACI5569D | Z89: 7053026728 | AB89: 0 | AD89: EPL | AE89: 708659 | AF89: 6000007816 | AG89: EP00 | AH89: GJ2501019995 | AI89: GJ2501019995 | AJ89: IA | AK89: 2025/05 | AL89: EP22 | AM89: 7200 | AN89: 28-08-2025 | AO89: -10891.16 | AP89: INR | AQ89: INR | AR89: 28-08-2025 | AS89: -9229.7999999999993 | AT89: 20-08-2025
A90: 5e144211-3f2c-47b6-9c13-76ad21cf3c11 | B90: a93eed28-60cc-45c1-aec5-740e9643bd65 | C90: 4ea51e15-1d43-3d54-8288-29b36d8e3d8e | D90: Reconciled | E90: Date and Amount Matched | F90: ledger | G90: 09-07-2025 | H90: 7053017025 | I90: payment | J90: KZ | L90: 16127.29 | M90: ledger | N90: 09-07-2025 | P90: payment | Q90: DZ | R90: /103010300003186-AXIS Bank | S90: -16127.29 | T90: 0 | U90: PRI-PAY10.1-company | V90: 03-Aug-26 04:10 PM | X90: AAACI5569D | Z90: 7053017025 | AB90: 0 | AD90: EPL | AE90: 708659 | AF90: 7053017025 | AG90: EP00 | AH90: 20250709-SUM10 | AI90: 20250709-SUM10 | AK90: 2025/04 | AM90: 7200 | AN90: 09-07-2025 | AO90: 16127.29 | AP90: INR | AQ90: INR | AR90: 09-07-2025 | AS90: 13667.19 | AT90: 09-07-2025
A91: 3f15c596-134f-4699-afd1-c520336f96d6 | B91: 20ac92f2-ef5d-4f4e-bba2-e74002936ff4 | C91: 4ebbce22-4de8-3461-9656-ac7defeab5a9 | D91: Reconciled | E91: Invoice Number Matched | F91: ledger | G91: 27-12-2025 | H91: GJ2501038910 | I91: invoice | J91: MA | K91: NITROGEN USP - NF / IH | L91: -16127.29 | M91: ledger | N91: 27-12-2025 | O91: GJ2501038910 | P91: invoice | Q91: RV | S91: 16127.29 | T91: 0 | U91: PRI-INV1.5_A-company | V91: 03-Aug-26 04:10 PM | X91: AAACI5569D | Z91: 7053052837 | AB91: 0 | AD91: EPL | AE91: 708659 | AF91: 6000014774 | AG91: EP00 | AH91: GJ2501038910 | AI91: GJ2501038910 | AJ91: II | AK91: 2025/09 | AL91: EP22 | AM91: 7200 | AN91: 31-12-2025 | AO91: -16127.29 | AP91: INR | AQ91: INR | AR91: 02-01-2026 | AS91: -13667.19 | AT91: 29-12-2025
A92: 25ab81c6-a66a-4291-b910-48cbe6b98ae3 | B92: 5c43c47f-6c64-4d85-87e6-a7d6db7da375 | C92: 4fecec16-cb39-3e68-b109-571de5470de4 | D92: Reconciled | E92: Invoice Number Matched | F92: ledger | G92: 30-06-2025 | H92: GJ2501012588 | I92: invoice | J92: MA | K92: NITROGEN USP - NF / IH | L92: -14661.16 | M92: ledger | N92: 30-06-2025 | O92: GJ2501012588 | P92: invoice | Q92: RV | S92: 14661.16 | T92: 0 | U92: PRI-INV1.5_A-company | V92: 03-Aug-26 04:10 PM | X92: AAACI5569D | Z92: 7053016715 | AB92: 0 | AD92: EPL | AE92: 708659 | AF92: 6000004569 | AG92: EP00 | AH92: GJ2501012588 | AI92: GJ2501012588 | AJ92: IA | AK92: 2025/04 | AL92: EP22 | AM92: 7200 | AN92: 02-07-2025 | AO92: -14661.16 | AP92: INR | AQ92: INR | AR92: 02-07-2025 | AS92: -12424.72 | AT92: 30-06-2025
A93: 151beaf5-5e94-4e89-88cc-24a12fd79cc5 | B93: 70e9cc67-a2eb-4368-8fe7-8454c37604ca | C93: 50da7622-7f5c-3b86-b10f-11c9f1268102 | D93: Write off / Rounding off | E93: Invoice Number Matched | F93: ledger | G93: 25-10-2025 | H93: GJ2501029378 | I93: invoice | J93: MA | K93: NITROGEN USP - NF / IH | L93: -15080 | M93: ledger | N93: 25-10-2025 | O93: GJ2501029378 | P93: invoice | Q93: RV | S93: 15080.05 | T93: 0.05 | U93: PRI-INV1.5-company | V93: 03-Aug-26 04:10 PM | X93: AAACI5569D | Z93: 7053039489 | AB93: 0 | AD93: EPL | AE93: 708659 | AF93: 6000010613 | AG93: EP00 | AH93: GJ2501029378 | AI93: GJ2501029378 | AJ93: II | AK93: 2025/07 | AL93: EP22 | AM93: 7200 | AN93: 29-10-2025 | AO93: -15080 | AP93: INR | AQ93: INR | AR93: 29-10-2025 | AS93: -12779.66 | AT93: 27-10-2025
A94: 97d7dce8-e18c-4c34-bd17-854ad9ddead7 | B94: 3bfecd43-169d-4a36-9e1c-cab059762874 | C94: 50f741c1-50cc-4c12-aa0b-7388dea352d7 | D94: Reconciled | E94: Date Range and Amount Matched | F94: ledger | G94: 03-04-2025 | H94: 7053000409 | I94: payment | J94: KZ | L94: 61574 | M94: ledger | N94: 04-04-2025 | P94: payment | Q94: DZ | R94: /103010300003186-AXIS Bank | S94: -61574 | T94: 0 | U94: PRI-PAY11.1-company | V94: 03-Aug-26 04:10 PM | X94: AAACI5569D | Z94: 7053000409 | AB94: 0 | AD94: EPL | AE94: 708659 | AF94: 7053000409 | AG94: EP00 | AH94: 20250403-SUM01 | AI94: 20250403-SUM01 | AK94: 2025/01 | AM94: 7200 | AN94: 03-04-2025 | AO94: 61574 | AP94: INR | AQ94: INR | AR94: 03-04-2025 | AS94: 52180.92 | AT94: 03-04-2025
A95: e4e6b4c6-6052-4ac6-beae-f8ba530faff7 | B95: 224c2a2e-04eb-4ed9-b847-f9a4b8d8409b | C95: 51b2c694-af40-3302-ae82-b33980e1516a | D95: Write off / Rounding off | E95: Invoice Number Matched | F95: ledger | G95: 18-05-2025 | H95: GJ2501006463 | I95: invoice | J95: MA | K95: NITROGEN USP - NF / IH | L95: -15498 | M95: ledger | N95: 18-05-2025 | O95: GJ2501006463 | P95: invoice | Q95: RV | S95: 15498.94 | T95: 0.94 | U95: PRI-INV1.5-company | V95: 03-Aug-26 04:10 PM | X95: AAACI5569D | Z95: 7053010772 | AB95: 0 | AD95: EPL | AE95: 708659 | AF95: 6000002372 | AG95: EP00 | AH95: GJ2501006463 | AI95: GJ2501006463 | AJ95: IA | AK95: 2025/02 | AL95: EP22 | AM95: 7200 | AN95: 23-05-2025 | AO95: -15498 | AP95: INR | AQ95: INR | AR95: 23-05-2025 | AS95: -13133.76 | AT95: 19-05-2025
A96: 0a66e518-afcf-4e5a-9650-d0b1f7be9023 | B96: d594f305-1fb6-4982-8015-872ddbf5e51f | C96: 5213c262-06cc-3407-a973-9bb40ac9b54d | D96: Reconciled | E96: Invoice Number Matched | F96: ledger | G96: 23-12-2025 | H96: GJ2501038397 | I96: invoice | J96: MA | K96: NITROGEN USP - NF / IH | L96: -18012.3 | M96: ledger | N96: 24-12-2025 | O96: GJ2501038397 | P96: invoice | Q96: RV | S96: 18012.3 | T96: 0 | U96: PRI-INV1.5_A-company | V96: 03-Aug-26 04:10 PM | X96: AAACI5569D | Z96: 7053053526 | AB96: 0 | AD96: EPL | AE96: 708659 | AF96: 6000014927 | AG96: EP00 | AH96: GJ2501038397 | AI96: GJ2501038397 | AJ96: II | AK96: 2025/10 | AL96: EP22 | AM96: 7200 | AN96: 05-01-2026 | AO96: -18012.3 | AP96: INR | AQ96: INR | AR96: 05-01-2026 | AS96: -15264.66 | AT96: 24-12-2025
A97: 1b3af696-1847-401b-a663-cc5ac5674b24 | B97: a312a41e-74ed-4e5b-9912-6cc27a05ffc7 | C97: 53cd940b-d762-3e54-a580-d2351cd2c5b5 | D97: Reconciled | E97: Invoice Number Matched | F97: ledger | G97: 15-01-2026 | H97: GJ2501042108 | I97: invoice | J97: MA | K97: NITROGEN USP - NF / IH | L97: -15498.94 | M97: ledger | N97: 17-01-2026 | O97: GJ2501042108 | P97: invoice | Q97: RV | S97: 15498.94 | T97: 0 | U97: PRI-INV1.5_A-company | V97: 03-Aug-26 04:10 PM | X97: AAACI5569D | Z97: 7053055913 | AB97: 0 | AD97: EPL | AE97: 708659 | AF97: 6000015702 | AG97: EP00 | AH97: GJ2501042108 | AI97: GJ2501042108 | AJ97: II | AK97: 2025/10 | AL97: EP22 | AM97: 7200 | AN97: 20-01-2026 | AO97: -15498.94 | AP97: INR | AQ97: INR | AR97: 20-01-2026 | AS97: -13134.7 | AT97: 19-01-2026
A98: 5326f382-617e-4b2e-b17d-2b08d84faae8 | B98: 46031c42-ad91-4cf1-b448-196c063344f4 | C98: 5430e656-f593-39be-b8ea-f2c01b181c33 | D98: Reconciled | E98: Date and Amount Matched | F98: ledger | G98: 03-02-2026 | H98: 7053056383 | I98: payment | J98: KZ | L98: 15289.51 | M98: ledger | N98: 03-02-2026 | P98: payment | Q98: DZ | R98: /103010300003186-AXIS Bank | S98: -15289.51 | T98: 0 | U98: PRI-PAY10.1-company | V98: 03-Aug-26 04:10 PM | X98: AAACI5569D | Z98: 7053056383 | AB98: 0 | AD98: EPL | AE98: 708659 | AF98: 7053056383 | AG98: EP16 | AH98: 20260203-SUM01 | AI98: 20260203-SUM01 | AK98: 2025/11 | AM98: 7200 | AN98: 03-02-2026 | AO98: 15289.51 | AP98: INR | AQ98: INR | AR98: 03-02-2026 | AS98: 12957.21 | AT98: 03-02-2026
A99: f57eb448-1b00-4deb-a13c-b46f43052bbd | B99: 0ee61f50-9915-4777-8be1-68d049432ac5 | C99: 54b6e825-2743-336b-a39a-1a0790198b19 | D99: Reconciled | E99: Date and Amount Matched | F99: ledger | G99: 24-11-2025 | H99: 7053042291 | I99: payment | J99: KZ | L99: 24247.29 | M99: ledger | N99: 24-11-2025 | P99: payment | Q99: DZ | R99: /103010300003186-AXIS Bank | S99: -24247.29 | T99: 0 | U99: PRI-PAY10.1-company | V99: 03-Aug-26 04:10 PM | X99: AAACI5569D | Z99: 7053042291 | AB99: 0 | AD99: EPL | AE99: 708659 | AF99: 7053042291 | AG99: EP00 | AH99: 20251124-SUM10 | AI99: 20251124-SUM10 | AK99: 2025/08 | AM99: 7200 | AN99: 24-11-2025 | AO99: 24247.29 | AP99: INR | AQ99: INR | AR99: 24-11-2025 | AS99: 20667.189999999999 | AT99: 24-11-2025
A100: b696f710-f7ff-44fb-bfe4-dba908df7bb5 | B100: 9e78c4ea-b317-433f-a01d-4b8c617ad3dd | C100: 54f3e95b-bdbf-36ae-9cfe-1de7ba28c5a5 | D100: Reconciled | E100: Invoice Number Matched | F100: ledger | G100: 20-11-2025 | H100: GJ2501033293 | I100: invoice | J100: MA | K100: NITROGEN USP - NF / IH | L100: -15289.51 | M100: ledger | N100: 21-11-2025 | O100: GJ2501033293 | P100: invoice | Q100: RV | S100: 15289.51 | T100: 0 | U100: PRI-INV1.5_A-company | V100: 03-Aug-26 04:10 PM | X100: AAACI5569D | Z100: 7053044484 | AB100: 0 | AD100: EPL | AE100: 708659 | AF100: 6000012393 | AG100: EP00 | AH100: GJ2501033293 | AI100: GJ2501033293 | AJ100: II | AK100: 2025/08 | AL100: EP22 | AM100: 7200 | AN100: 28-11-2025 | AO100: -15289.51 | AP100: INR | AQ100: INR | AR100: 28-11-2025 | AS100: -12957.21 | AT100: 21-11-2025
...

Sheet 1
A1: Party Id | B1: Matched Id | C1: Status | D1: Classification | E1: Company Statement Type | F1: Company Invoice Date | G1: Company Invoice Number | H1: Company DocType | I1: Company Original DocType | J1: Company Amount | K1: Party Statement Type | L1: Party Invoice Date | M1: Party Invoice Number | N1: Party DocType | O1: Party Original DocType | P1: Party Amount | Q1: Difference | R1: Party Clearing Document Number | S1: Party Clearing Date | T1: Party TDS Amount | U1: Party Posting Date | V1: Profit Center | W1: Document Number | X1: Billing Document | Y1: Document Header Text
A2: 83367621-45ac-4bfa-a27d-253caf496027 | C2: Invoice not booked by Company | D2: Unmatched | J2: 0 | K2: ledger | L2: 26-02-2026 | M2: GJ2501048647 | N2: invoice | O2: RV | P2: 34947.88 | Q2: 34947.88 | R2: 200019483 | S2: 18-05-2026 | T2: 0 | U2: 26-02-2026 | V2: 2121 | W2: 391913 | X2: 96042661
A3: 4e6a339d-98e1-45b0-a6c6-8c09b206b35d | C3: Invoice not booked by Company | D3: Unmatched | J3: 0 | K3: ledger | L3: 05-03-2026 | M3: GJ2502004390 | N3: invoice | O3: RV | P3: 29500 | Q3: 29500 | R3: 200014107 | S3: 30-04-2026 | T3: 0 | U3: 05-03-2026 | V3: 2121 | W3: 400046 | X3: 96050793
A4: 9420b795-bb86-4f11-9192-58449f7a6019 | C4: Invoice not booked by Company | D4: Unmatched | J4: 0 | K4: ledger | L4: 01-04-2025 | N4: invoice | O4: RV | P4: 139909.44 | Q4: 139909.44 | R4: 200000205 | S4: 05-04-2025 | T4: 0 | V4: 2013

Sheet 33
A1: Company Id | B1: Matched Id | C1: Status | D1: Classification | E1: Company Statement Type | F1: Company Invoice Date | G1: Company Invoice Number | H1: Company DocType | I1: Company Original DocType | J1: Company Amount | K1: Party Statement Type | L1: Party Invoice Date | M1: Party Invoice Number | N1: Party DocType | O1: Party Original DocType | P1: Party Amount | Q1: Difference | R1: Company Clearing Document Number | S1: Company Clearing Date | T1: Company TDS Amount | U1: Company Posting Date | V1: Company Code | W1: Supplier | X1: Document Number | Y1: Business Area | Z1: Assignment | AA1: Document Header Text | AB1: Tax Code | AC1: Year/Month | AD1: Reference | AE1: Profit Center | AF1: Posting Date | AG1: Amount in Doc. Curr. | AH1: Document Currency | AI1: Local Currency | AJ1: Entry Date | AK1: Withhldg Tax Base Amount | AL1: Payment Date
A2: 235e2d9d-0c3e-465a-bce7-c8540a216be3 | C2: Debit Note not booked by Party | D2: Unmatched | E2: ledger | F2: 19-09-2025 | H2: debitNote | I2: KG | J2: 17174.51 | P2: 0 | Q2: 17174.51 | R2: 7021002670 | T2: 0 | V2: EPL | W2: 708659 | X2: 7031002318 | Y2: EP00 | Z2: GJ2501024670-Rev | AA2: GJ2501024670-R | AB2: I5 | AC2: 2025/06 | AD2: EP22 | AE2: 7200 | AF2: 30-09-2025 | AG2: 17174.509999999998 | AH2: INR | AI2: INR | AJ2: 09-10-2025 | AK2: 14554.67 | AL2: 19-09-2025

Sheet 74
A1: Party Id | B1: Matched Id | C1: Status | D1: Classification | E1: Company Statement Type | F1: Company Invoice Date | G1: Company Invoice Number | H1: Company DocType | I1: Company Original DocType | J1: Company Amount | K1: Party Statement Type | L1: Party Invoice Date | M1: Party Invoice Number | N1: Party DocType | O1: Party Original DocType | P1: Party Amount | Q1: Difference | R1: Party Clearing Document Number | S1: Party Clearing Date | T1: Party TDS Amount | U1: Party Posting Date | V1: Profit Center | W1: Document Number | X1: Billing Document | Y1: Document Header Text
A2: 36a1e8bb-cb43-4030-b9bc-93be94971786 | C2: Other entry not booked by Company | D2: Unmatched | J2: 0 | K2: ledger | L2: 21-07-2025 | N2: clearing | O2: AB | P2: -38420.12 | Q2: -38420.12 | R2: 200037013 | S2: 21-07-2025 | T2: 0 | U2: 21-07-2025 | V2: 2011 | W2: 200037013
A3: 3d2dc23b-f138-4fd3-a676-b3237aac80b3 | C3: Other entry not booked by Company | D3: Unmatched | J3: 0 | K3: ledger | L3: 17-12-2025 | N3: clearing | O3: AB | P3: 8120 | Q3: 8120 | R3: 200098081 | S3: 17-12-2025 | T3: 0 | U3: 17-12-2025 | V3: 2011 | W3: 200098081
A4: 62292d65-5471-440c-b0ce-10489ac6d1fe | C4: Other entry not booked by Company | D4: Unmatched | J4: 0 | K4: ledger | L4: 08-01-2026 | N4: clearing | O4: AB | P4: 108280.51 | Q4: 108280.51 | R4: 200108729 | S4: 08-01-2026 | T4: 0 | U4: 08-01-2026 | V4: 2011 | W4: 200108729
A5: ba74d7a3-874f-4458-820c-6eb261c11d3f | C5: Other entry not booked by Company | D5: Unmatched | J5: 0 | K5: ledger | L5: 28-06-2025 | N5: clearing | O5: AB | P5: -8260 | Q5: -8260 | R5: 200025654 | S5: 28-06-2025 | T5: 0 | U5: 28-06-2025 | V5: 2011 | W5: 200025654
A6: f5fbf5ff-85d0-4195-8984-68ad1b83b9bb | C6: Other entry not booked by Company | D6: Unmatched | J6: 0 | K6: ledger | L6: 25-11-2025 | N6: clearing | O6: AB | P6: -24387.29 | Q6: -24387.29 | R6: 200088680 | S6: 25-11-2025 | T6: 0 | U6: 25-11-2025 | V6: 2011 | W6: 200088680
A7: 3122328d-4e8f-4214-b6ed-1a5d29b5e118 | C7: Other entry not booked by Company | D7: Unmatched | J7: 0 | K7: ledger | L7: 06-05-2025 | N7: clearing | O7: AB | P7: 95505.13 | Q7: 95505.13 | R7: 200009477 | S7: 06-05-2025 | T7: 0 | U7: 06-05-2025 | V7: 2013 | W7: 200009477
A8: 3169b1db-9463-45ca-97a4-c5f29e728e0c | C8: Other entry not booked by Company | D8: Unmatched | J8: 0 | K8: ledger | L8: 21-08-2025 | N8: clearing | O8: AB | P8: 8120 | Q8: 8120 | R8: 200048423 | S8: 21-08-2025 | T8: 0 | U8: 21-08-2025 | V8: 2011 | W8: 200048423
A9: 35d49a60-e57a-4c22-b647-7b09ecc744e9 | C9: Other entry not booked by Company | D9: Unmatched | J9: 0 | K9: ledger | L9: 29-01-2026 | N9: clearing | O9: AB | P9: -68999.12 | Q9: -68999.12 | R9: 200112844 | S9: 29-01-2026 | T9: 0 | U9: 29-01-2026 | V9: 2011 | W9: 200112844
A10: 56eeb852-d9c2-4387-9040-6f9c8a5b670b | C10: Other entry not booked by Company | D10: Unmatched | J10: 0 | K10: ledger | L10: 08-01-2026 | N10: clearing | O10: AB | P10: -108283.19 | Q10: -108283.19 | R10: 200108729 | S10: 08-01-2026 | T10: 0 | U10: 08-01-2026 | V10: 2011 | W10: 200108729
A11: 64ebcfa4-0b87-40d1-81d7-f6c16de835ac | C11: Other entry not booked by Company | D11: Unmatched | J11: 0 | K11: ledger | L11: 03-02-2026 | N11: clearing | O11: AB | P11: -334308.4 | Q11: -334308.4 | R11: 200123874 | S11: 03-02-2026 | T11: 0 | U11: 03-02-2026 | V11: 2013 | W11: 200123874
A12: 7a44f9d1-be29-4a3e-9782-fdb0cd6e60dc | C12: Other entry not booked by Company | D12: Unmatched | J12: 0 | K12: ledger | L12: 05-04-2025 | N12: clearing | O12: AB | P12: 61574 | Q12: 61574 | R12: 200000206 | S12: 05-04-2025 | T12: 0 | U12: 05-04-2025 | V12: 2013 | W12: 200000206
A13: 9ceb7afe-dcef-43db-a0db-27ef4899e2e0 | C13: Other entry not booked by Company | D13: Unmatched | J13: 0 | K13: ledger | L13: 12-11-2025 | N13: clearing | O13: AB | P13: -55804.07 | Q13: -55804.07 | R13: 200086152 | S13: 12-11-2025 | T13: 0 | U13: 12-11-2025 | V13: 2011 | W13: 200086152
... A29: fc59460b-31bc-459d-b137-e0efea74f193 | C29: Other entry not booked by Company | D29: Unmatched | J29: 0 | K29: ledger | L29: 06-05-2025 | N29: clearing | O29: AB | P29: -95507.05 | Q29: -95507.05 | R29: 200009477 | S29: 06-05-2025 | T29: 0 | U29: 06-05-2025 | V29: 2013 | W29: 200009477

Sheet 79
A1: Company Id | B1: Matched Id | C1: Status | D1: Classification | E1: Company Statement Type | F1: Company Invoice Date | G1: Company Invoice Number | H1: Company DocType | I1: Company Original DocType | J1: Company Amount | K1: Party Statement Type | L1: Party Invoice Date | M1: Party Invoice Number | N1: Party DocType | O1: Party Original DocType | P1: Party Amount | Q1: Difference | R1: Company Clearing Document Number | S1: Company Clearing Date | T1: Company TDS Amount | U1: Company Posting Date | V1: Company Code | W1: Supplier | X1: Document Number | Y1: Business Area | Z1: Assignment | AA1: Document Header Text | AB1: Tax Code | AC1: Year/Month | AD1: Reference | AE1: Profit Center | AF1: Posting Date | AG1: Amount in Doc. Curr. | AH1: Document Currency | AI1: Local Currency | AJ1: Entry Date | AK1: Withhldg Tax Base Amount | AL1: Payment Date
A2: 6f26c118-1932-4228-8692-f9f4c2aff5eb | C2: Other entry not booked by Party | D2: Unmatched | E2: ledger | F2: 19-09-2025 | H2: journal | I2: KA | J2: -17174.51 | P2: 0 | Q2: -17174.51 | R2: 7021002670 | T2: 0 | V2: EPL | W2: 708659 | X2: 7021002670 | Y2: EP00 | Z2: GJ2501024670-Rev | AA2: GJ2501024670-R | AB2: I5 | AC2: 2025/06 | AD2: EP22 | AE2: 7200 | AF2: 30-09-2025 | AG2: -17174.509999999998 | AH2: INR | AI2: INR | AJ2: 09-10-2025 | AK2: -14554.67 | AL2: 19-09-2025

Sheet 94
A1: Company Id | B1: Party Id | C1: Matched Id | D1: Status | E1: Classification | F1: Company Statement Type | G1: Company Invoice Date | H1: Company Invoice Number | I1: Company DocType | J1: Company Original DocType | K1: Company Narration | L1: Company Amount | M1: Party Statement Type | N1: Party Invoice Date | O1: Party Invoice Number | P1: Party DocType | Q1: Party Original DocType | R1: Party Narration | S1: Party Amount | T1: Difference
A2: 978a5118-8f9b-4f54-ab7b-de26a6e84029 | B2: 1753e470-c31e-44ee-8c22-932192d984dc | C2: 0ca1f6e1-3818-37d8-abe4-e28760ace981 | D2: TDS Booked by Company | E2: Invoice Number Matched | F2: ledger | G2: 05-07-2025 | H2: GJ2502001220 | I2: invoice | J2: MI | K2: Fixed facility charges july-25 | L2: -8120 | M2: ledger | N2: 05-07-2025 | O2: GJ2502001220 | P2: invoice | Q2: RV | S2: 8260 | T2: 140
A3: 81699d36-77e8-47e2-84b7-d79473efd7e7 | B3: 2f09a670-f8bb-488d-b481-f68bc079c1fb | C3: 7d8439fa-3569-3d4d-8e04-483f90e32539 | D3: TDS Booked by Company | E3: Invoice Number Matched | F3: ledger | G3: 05-09-2025 | H3: GJ2502001991 | I3: invoice | J3: MI | K3: Nitrogen charge for Sep 2025 | L3: -8120 | M3: ledger | N3: 05-09-2025 | O3: GJ2502001991 | P3: invoice | Q3: RV | S3: 8260 | T3: 140
A4: 1b2eed0c-69d7-4086-b222-84c806a0bc2d | B4: 52025ec7-6576-4532-96cb-3832f9894753 | C4: 60cba853-b0af-3a12-a105-b7ebec9ba82e | D4: TDS Booked by Company | E4: Invoice Number Matched | F4: ledger | G4: 05-04-2025 | H4: GJ2502000084 | I4: invoice | J4: MI | K4: Fixed Facility charges April-2025 | L4: -8120 | M4: ledger | N4: 05-04-2025 | O4: GJ2502000084 | P4: invoice | Q4: RV | S4: 8260 | T4: 140
A5: d84c105e-0d15-4c87-8093-51397aeeed96 | B5: 5bded08c-b8bb-4310-b6aa-84e43ea76a15 | C5: a812c24b-e13b-3e27-b92a-2cf60b3e73e8 | D5: TDS Booked by Company | E5: Invoice Number Matched | F5: ledger | G5: 05-12-2025 | H5: GJ2502003200 | I5: invoice | J5: MI | K5: Nitrogen charge for Dec 2025 | L5: -8120 | M5: ledger | N5: 05-12-2025 | O5: GJ2502003200 | P5: invoice | Q5: RV | S5: 8260 | T5: 140
A6: 13a89072-17f4-469b-adab-904e77bee999 | B6: 80f73e0c-33e6-46c1-8d62-587bbc3a6ddb | C6: 161da05b-906d-3575-9250-bfbc809ee54f | D6: TDS Booked by Company | E6: Invoice Number Matched | F6: ledger | G6: 05-02-2026 | H6: GJ2502003996 | I6: invoice | J6: MI | K6: Nitrogen tank 6kl Rent Charge (Inox) | L6: -29000 | M6: ledger | N6: 05-02-2026 | O6: GJ2502003996 | P6: invoice | Q6: RV | S6: 29500 | T6: 500
A7: b5bf1190-4f74-4bbe-a59f-dcb2eef139a5 | B7: 8eb60192-0029-4ab5-b967-7ae2120895a1 | C7: bd9d5fc0-06d9-3c2e-affe-610d3ee6c697 | D7: TDS Booked by Company | E7: Invoice Number Matched | F7: ledger | G7: 16-01-2026 | H7: GJ2502003786 | I7: invoice | J7: MI | K7: INSTALLATION & COMMISSIONING CHARGES | L7: -191400 | M7: ledger | N7: 16-01-2026 | O7: GJ2502003786 | P7: invoice | Q7: RV | S7: 194700 | T7: 3300
A8: 3940f24e-dfc9-4723-b284-a9633243c738 | B8: 9585cf72-7d9f-49d4-8de7-6598b9ef9d5b | C8: 91507aea-7dac-3408-967c-e19c93be9ccd | D8: TDS Booked by Company | E8: Invoice Number Matched | F8: ledger | G8: 05-05-2025 | H8: GJ2502000458 | I8: invoice | J8: MI | K8: YEARLY RENT CHARGES FOR NITROGEN MAY -25 | L8: -8120 | M8: ledger | N8: 05-05-2025 | O8: GJ2502000458 | P8: invoice | Q8: RV | S8: 8260 | T8: 140
A9: 2c198ecd-4da5-4e41-b2e0-1195d8b44afa | B9: a034260e-edf0-4c02-a6e0-6c3ea2bf4111 | C9: e9415d1a-cbd6-3be4-8bf0-91172cb5ed71 | D9: TDS Booked by Company | E9: Invoice Number Matched | F9: ledger | G9: 05-01-2026 | H9: GJ2502003741 | I9: invoice | J9: MI | K9: Nitrogen charge for Jan 2026 | L9: -8120 | M9: ledger | N9: 05-01-2026 | O9: GJ2502003741 | P9: invoice | Q9: RV | S9: 8260 | T9: 140
A10: a9dc7e96-48ff-47e7-95e7-1378163d69a3 | B10: bf5d9d3a-9642-4dec-a100-e2a69c626181 | C10: 12865390-331f-3113-9500-42d98c7e89c1 | D10: TDS Booked by Company | E10: Invoice Number Matched | F10: ledger | G10: 16-01-2026 | H10: GJ2502003787 | I10: invoice | J10: MI | K10: CONSULTANCY FEES- APPROX MONTH JAN 2025 | L10: -121800 | M10: ledger | N10: 16-01-2026 | O10: GJ2502003787 | P10: invoice | Q10: RV | S10: 123900 | T10: 2100
A11: 86801746-0a08-472a-81f9-c935168cb11d | B11: c8bc302e-567f-4af2-ad27-46d0ddb30d5c | C11: a906b5d9-6b60-38f2-ad22-63bc69ade4c6 | D11: TDS Booked by Company | E11: Invoice Number Matched | F11: ledger | G11: 05-08-2025 | H11: GJ2502001587 | I11: invoice | J11: MI | K11: FIXED FACILITY CHARGES FOR THE MONTH AUG 2025 | L11: -8120 | M11: ledger | N11: 05-08-2025 | O11: GJ2502001587 | P11: invoice | Q11: RV | S11: 8260 | T11: 140
A12: 51a92668-c8c7-4c24-9f2c-2631c3683758 | B12: cbb5426f-ca9b-4b03-b9c6-662f10c5e3d9 | C12: 91579428-4062-34c4-8fc3-25dd6e91e4e6 | D12: TDS Booked by Company | E12: Invoice Number Matched | F12: ledger | G12: 05-10-2025 | H12: GJ2502002394 | I12: invoice | J12: MI | K12: Nitrogen charge for Oct 2025 | L12: -8120 | M12: ledger | N12: 05-10-2025 | O12: GJ2502002394 | P12: invoice | Q12: RV | S12: 8260 | T12: 140
A13: 7ec3a1cb-0f6c-4ff9-9387-a76299ba90c2 | B13: d0115efd-f9dc-40ec-ba25-27535f0931c9 | C13: 89dac278-81b5-35a7-8dfb-4b95bb97a71d | D13: TDS Booked by Company | E13: Invoice Number Matched | F13: ledger | G13: 05-11-2025 | H13: GJ2502002813 | I13: invoice | J13: MI | K13: Nitrogen charge for Nov 2025 | L13: -8120 | M13: ledger | N13: 05-11-2025 | O13: GJ2502002813 | P13: invoice | Q13: RV | S13: 8260 | T13: 140
... A15: 2967a1fd-035c-4b49-8897-df1a4fef9b7d | B15: ff793414-4674-4195-a4cb-9916d8b4cffe | C15: 57b97990-b95b-3a06-9f29-8949bcacc33d | D15: TDS Booked by Company | E15: Invoice Number Matched | F15: ledger | G15: 05-01-2026 | H15: GJ2502003591 | I15: invoice | J15: MI | K15: Nitrogen tank 6kl Rent Charge (Inox) Month Jan 26 | L15: -29000 | M15: ledger | N15: 05-01-2026 | O15: GJ2502003591 | P15: invoice | Q15: RV | S15: 29500 | T15: 500
A16: 403538f4-e638-4059-b715-346bc44766df | B16: ab1cb182-2012-4bfc-9c4c-6a478cf177fa | C16: 5de0598d-fb5d-385d-83f5-f116f824a05e | D16: TDS Booked by Party | E16: Date and Amount Matched - Recommended | F16: ledger | G16: 02-03-2026 | H16: 7053062135 | I16: payment | J16: KZ | L16: 187950.57 | M16: ledger | N16: 02-03-2026 | P16: payment | Q16: DZ | S16: -188950.58 | T16: -1000.01

Sheet Party
A1: Party Id | B1: Matched Id | C1: Status | D1: Classification | E1: Party Statement Type | F1: Party Invoice Date | G1: Party Invoice Number | H1: Party DocType | I1: Party Original DocType | J1: Party Narration | K1: Party Amount | L1: Matched Rule | M1: Reco Data & Time | N1: Party Clearing Document Number | O1: Party Clearing Date | P1: Party TDS Amount | Q1: Party Posting Date | R1: Profit Center | S1: Document Number | T1: Billing Document | U1: Document Header Text
A2: 00568bd6-dc1e-4c1b-b3af-d340c62e09d7 | B2: 338d9c62-09dc-3c11-a8d5-39599d1733b2 | C2: Reconciled | D2: Invoice Number Matched | E2: ledger | F2: 31-12-2025 | G2: GJ2501039628 | H2: invoice | I2: RV | K2: 15498.94 | L2: PRI-INV1.5_A-company | M2: 03-Aug-26 04:10 PM | N2: 200111423 | O2: 21-01-2026 | P2: 0 | Q2: 31-12-2025 | R2: 2011 | S2: 322218 | T2: 95972934
A3: 011cc82e-ce12-4f07-9b59-8cb23954081c | B3: 411bb97f-154a-3e93-838a-aaf7cfc38ffc | C3: Reconciled | D3: Date and Amount Matched | E3: ledger | F3: 29-08-2025 | H3: payment | I3: DZ | J3: /103010300003186-AXIS Bank | K3: -56131.33 | L3: PRI-PAY10.1-company | M3: 03-Aug-26 04:10 PM | N3: 200051284 | O3: 30-08-2025 | P3: 0 | Q3: 29-08-2025 | R3: 2013 | S3: 1400048389 | U3: UTIBN62025082908954328
A4: 015634d8-09e8-4023-a05b-36d54c48610d | B4: bbc20328-c272-4c15-8e76-d77c91e4fb85 | C4: Reconciled | D4: Date Range and Amount Matched | E4: ledger | F4: 23-04-2025 | H4: payment | I4: DZ | J4: /103010300003186-AXIS Bank | K4: -43774.06 | L4: PRI-PAY11.1-company | M4: 03-Aug-26 04:10 PM | N4: 200002688 | O4: 23-04-2025 | P4: 0 | Q4: 23-04-2025 | R4: 2013 | S4: 1400005690 | U4: UTIBN62025042384063366
A5: 0320d7df-9a8d-4d25-9dc8-f3bc70fe582e | B5: 17c0c9f1-a4e5-32fd-b0c2-d53b07c35f44 | C5: Reconciled | D5: Invoice Number Matched | E5: ledger | F5: 01-02-2026 | G5: GJ2501044504 | H5: invoice | I5: RV | K5: 15289.51 | L5: PRI-INV1.5_A-company | M5: 03-Aug-26 04:10 PM | N5: 200127041 | O5: 14-02-2026 | P5: 0 | Q5: 01-02-2026 | R5: 2011 | S5: 360746 | T5: 96011469
A6: 03d61b08-0128-41ee-b955-5c4ff5560faa | B6: 40b161a7-aa6d-3a52-baad-50d925135767 | C6: Reconciled | D6: Date and Amount Matched | E6: ledger | F6: 09-05-2025 | H6: payment | I6: DZ | J6: /103010300003186-AXIS Bank | K6: -40841 | L6: PRI-PAY10.1-company | M6: 03-Aug-26 04:10 PM | N6: 200010428 | O6: 10-05-2025 | P6: 0 | Q6: 09-05-2025 | R6: 2013 | S6: 1400010998 | U6: UTIBN62025050950181213
A7: 04d81620-531e-4e19-88ee-107613bd869b | B7: 1389c6c3-a6c5-3e19-86d9-0c8da1f05247 | C7: Reconciled | D7: Invoice Number Matched | E7: ledger | F7: 27-08-2025 | G7: GJ2501021121 | H7: invoice | I7: RV | K7: 18431.19 | L7: PRI-INV1.5_A-company | M7: 03-Aug-26 04:10 PM | N7: 200058567 | O7: 16-09-2025 | P7: 0 | Q7: 27-08-2025 | R7: 2011 | S7: 172093 | T7: 95822724
A8: 05444b55-f170-4a18-ad36-24f0248b1ebf | B8: b1127b6c-9ebc-4778-9fbf-e92ccdeadead | C8: Reversal Entries | D8: Reversal Entries | E8: ledger | F8: 23-12-2025 | H8: clearing | I8: AB | K8: 28903 | L8: Pre-C-2.5_A-party | M8: 03-Aug-26 04:10 PM | N8: 200098952 | O8: 23-12-2025 | P8: 0 | Q8: 23-12-2025 | R8: 2011 | S8: 200098952
A9: 06072f9e-bce9-434a-834b-92937774341f | B9: a417e015-dd65-3146-aeed-78a488b1d737 | C9: Reconciled | D9: Date and Amount Matched | E9: ledger | F9: 08-04-2025 | H9: payment | I9: DZ | J9: /103010300003186-AXIS Bank | K9: -13404.5 | L9: PRI-PAY10.1-company | M9: 03-Aug-26 04:10 PM | N9: 200000551 | O9: 09-04-2025 | P9: 0 | Q9: 08-04-2025 | R9: 2013 | S9: 1400001752 | U9: UTIBN62025040818050778
A10: 06e0e672-43c3-46b9-bef2-8955ab2f6fbc | B10: d32111f5-e80a-3091-9ae1-5eff9d9b7249 | C10: Reconciled | D10: Date and Amount Matched | E10: ledger | F10: 20-10-2025 | H10: payment | I10: DZ | J10: /103010300003186-AXIS Bank | K10: -55503 | L10: PRI-PAY10.1-company | M10: 03-Aug-26 04:10 PM | N10: 200070021 | O10: 21-10-2025 | P10: 0 | Q10: 20-10-2025 | R10: 2013 | S10: 1400064794 | U10: UTIBN62025102095960257
A11: 0796d026-0402-413a-9301-cde53584fdb6 | B11: 4533fbb2-4143-4323-8a7d-4373f5657fa5 | C11: Reversal Entries | D11: Reversal Entries | E11: ledger | F11: 17-10-2025 | H11: clearing | I11: AB | K11: 18012 | L11: Pre-C-2.5_A-party | M11: 03-Aug-26 04:10 PM | N11: 200069296 | O11: 17-10-2025 | P11: 0 | Q11: 17-10-2025 | R11: 2011 | S11: 200069296
A12: 07b100d4-c250-4300-8bf1-8b6771cee943 | B12: ba553ae6-3bf4-3417-bc98-6fd9f305c957 | C12: Reconciled | D12: Date and Amount Matched | E12: ledger | F12: 29-07-2025 | H12: payment | I12: DZ | J12: /103010300003186-AXIS Bank | K12: -89013.58 | L12: PRI-PAY10.1-company | M12: 03-Aug-26 04:10 PM | N12: 200040134 | O12: 30-07-2025 | P12: 0 | Q12: 29-07-2025 | R12: 2013 | S12: 1400037857 | U12: UTIBN62025072982287240
A13: 08c9ed73-272a-49ec-9eb4-14d127952f20 | B13: 563737e2-2fb6-3c3d-a9de-2c77a62ceafd | C13: Reconciled | D13: Date and Amount Matched | E13: ledger | F13: 02-07-2025 | H13: payment | I13: DZ | J13: /103010300003186-AXIS Bank | K13: -46496.71 | L13: PRI-PAY10.1-company | M13: 03-Aug-26 04:10 PM | N13: 200029663 | O13: 03-07-2025 | P13: 0 | Q13: 02-07-2025 | R13: 2013 | S13: 1400028635 | U13: UTIBN62025070286926749
A14: 0949c732-28f6-4691-a576-a552862c67ce | B14: b9e8bf13-4417-3227-93d5-5160ea9dd12c | C14: Reconciled | D14: Date and Amount Matched | E14: ledger | F14: 11-02-2026 | H14: payment | I14: DZ | J14: /103010300003186-AXIS Bank | K14: -29950.67 | L14: PRI-PAY10.1-company | M14: 03-Aug-26 04:10 PM | N14: 200126611 | O14: 12-02-2026 | P14: 0 | Q14: 11-02-2026 | R14: 2013 | S14: 1400102560 | U14: AXISCN1249138144
A15: 0a0321c6-89f7-4c57-92de-8c4a76028ad3 | B15: f005b7c9-4b76-4cb4-99ba-d36255f5622f | C15: Reversal Entries | D15: Reversal Entries | E15: ledger | F15: 04-12-2025 | H15: clearing | I15: AB | K15: -14451.72 | L15: Pre-C-2.5_A-party | M15: 03-Aug-26 04:10 PM | N15: 200095703 | O15: 04-12-2025 | P15: 0 | Q15: 04-12-2025 | R15: 2011 | S15: 200095703
A16: 0a81d059-bc80-4f29-a70b-678a8c49cc0f | B16: b5a9f204-b92c-4cd8-80fa-11ab7201ec58 | C16: Reversal Entries | D16: Reversal Entries | E16: ledger | F16: 25-12-2025 | H16: clearing | I16: AB | K16: -29531.78 | L16: Pre-C-2.5_A-party | M16: 03-Aug-26 04:10 PM | N16: 200099446 | O16: 25-12-2025 | P16: 0 | Q16: 25-12-2025 | R16: 2011 | S16: 200099446
A17: 0c684ffc-6023-45f7-85f0-055ee52a6186 | B17: 70dac47e-b423-466c-8f46-117c51994a19 | C17: Reversal Entries | D17: Reversal Entries | E17: ledger | F17: 20-08-2025 | H17: clearing | I17: AB | K17: 25342 | L17: Pre-C-2.5_A-party | M17: 03-Aug-26 04:10 PM | N17: 200048357 | O17: 20-08-2025 | P17: 0 | Q17: 20-08-2025 | R17: 2011 | S17: 200048357
A18: 0d9f589f-e950-45e5-b567-4ad370ba9d5b | B18: 64e94695-6d05-3c53-adbf-ddefe5825ad9 | C18: Write off / Rounding off | D18: Invoice Number Matched | E18: ledger | F18: 08-08-2025 | G18: GJ2501018486 | H18: invoice | I18: RV | K18: 13823.4 | L18: PRI-INV1.5-company | M18: 03-Aug-26 04:10 PM | N18: 200048357 | O18: 20-08-2025 | P18: 0 | Q18: 08-08-2025 | R18: 2011 | S18: 152011 | T18: 95802632
A19: 0e2b51ec-62d9-4d6c-a760-1630824582c2 | B19: a01ded7b-10cf-490e-b332-b7882fd57180 | C19: Reversal Entries | D19: Reversal Entries | E19: ledger | F19: 31-07-2025 | H19: clearing | I19: AB | K19: -68069.73 | L19: Pre-C-2.5_A-party | M19: 03-Aug-26 04:10 PM | N19: 200041895 | O19: 31-07-2025 | P19: 0 | Q19: 31-07-2025 | R19: 2011 | S19: 200041895
A20: 0ee61f50-9915-4777-8be1-68d049432ac5 | B20: 54b6e825-2743-336b-a39a-1a0790198b19 | C20: Reconciled | D20: Date and Amount Matched | E20: ledger | F20: 24-11-2025 | H20: payment | I20: DZ | J20: /103010300003186-AXIS Bank | K20: -24247.29 | L20: PRI-PAY10.1-company | M20: 03-Aug-26 04:10 PM | N20: 200088680 | O20: 25-11-2025 | P20: 0 | Q20: 24-11-2025 | R20: 2013 | S20: 1400075625 | U20: AXISCN1164847715
A21: 0f6f9d09-f804-4bf9-bd73-6e978ef3fae3 | B21: 60dc5e24-ab89-3678-9e1b-62a5da0812e0 | C21: Reconciled | D21: Date and Amount Matched | E21: ledger | F21: 02-02-2026 | H21: payment | I21: DZ | J21: /103010300003186-AXIS Bank | K21: -328908.4 | L21: PRI-PAY10.1-company | M21: 03-Aug-26 04:10 PM | N21: 200123874 | O21: 03-02-2026 | P21: 0 | Q21: 02-02-2026 | R21: 2013 | S21: 1400099468 | U21: AXISCN1237968296
A22: 0f740e2b-72c0-45b0-8130-cb72d131b4e2 | B22: 9d56db5b-e2aa-4182-b5fd-8c2c8726ecc8 | C22: Reversal Entries | D22: Reversal Entries | E22: ledger | F22: 30-06-2025 | H22: clearing | I22: AB | K22: -69745.29 | L22: Pre-C-2.5_A-party | M22: 03-Aug-26 04:10 PM | N22: 200027381 | O22: 30-06-2025 | P22: 0 | Q22: 30-06-2025 | R22: 2011 | S22: 200027381
A23: 0fd9a2cc-cf2f-47ef-be61-97e31aebc5e8 | B23: 0629eb8d-fb71-3eab-b7ee-962c818ce396 | C23: Reconciled | D23: Invoice Number Matched | E23: ledger | F23: 03-09-2025 | G23: GJ2501022123 | H23: invoice | I23: RV | K23: 19687.86 | L23: PRI-INV1.5_A-company | M23: 03-Aug-26 04:10 PM | N23: 200058566 | O23: 16-09-2025 | P23: 0 | Q23: 03-09-2025 | R23: 2011 | S23: 180598 | T23: 95831237
A24: 116a8323-5084-4c75-bad6-0a21ea27e2d5 | B24: 807e2086-af67-4462-b291-03d569963116 | C24: Reversal Entries | D24: Reversal Entries | E24: ledger | F24: 06-12-2025 | H24: clearing | I24: AB | K24: 32464.02 | L24: Pre-C-2.5_A-party | M24: 03-Aug-26 04:10 PM | N24: 200096313 | O24: 06-12-2025 | P24: 0 | Q24: 06-12-2025 | R24: 2011 | S24: 200096313
A25: 118c9b94-a553-4c47-8f90-a31c088b763d | B25: 84b1a3c1-3cab-42ed-844c-49b665fd3bb5 | C25: Reversal Entries | D25: Reversal Entries | E25: ledger | F25: 13-06-2025 | H25: clearing | I25: AB | K25: 17383.97 | L25: Pre-C-2.5_A-party | M25: 03-Aug-26 04:10 PM | N25: 200022072 | O25: 13-06-2025 | P25: 0 | Q25: 13-06-2025 | R25: 2011 | S25: 200022072
A26: 12667236-756f-46a7-9a93-34f4776f8324 | B26: 259a6478-fadb-397f-b1ce-54a9d0df2189 | C26: Reconciled | D26: Invoice Number Matched | E26: ledger | F26: 06-09-2025 | G26: GJ2501022610 | H26: invoice | I26: RV | K26: 4817.25 | L26: PRI-INV1.5_A-company | M26: 03-Aug-26 04:10 PM | N26: 200058566 | O26: 16-09-2025 | P26: 0 | Q26: 06-09-2025 | R26: 2011 | S26: 185561 | T26: 95836201
A27: 13856ba4-3a38-42b6-aa0c-280ba8ba07b8 | B27: 4028399e-6228-37fb-9053-64cb78f74f5b | C27: Write off / Rounding off | D27: Invoice Number Matched | E27: ledger | F27: 17-05-2025 | G27: GJ2501006317 | H27: invoice | I27: RV | K27: 15708.4 | L27: PRI-INV1.5-company | M27: 03-Aug-26 04:10 PM | N27: 200018416 | O27: 03-06-2025 | P27: 0 | Q27: 17-05-2025 | R27: 2011 | S27: 52783 | T27: 95703361
A28: 142d3658-da48-4122-b8d5-eada1f618293 | C28: Other entry not booked by Company | D28: Unmatched | E28: ledger | F28: 25-11-2025 | H28: clearing | I28: AB | K28: 24247.29 | L28: Post-P-3.6-party | M28: 03-Aug-26 04:10 PM | N28: 200088680 | O28: 25-11-2025 | P28: 0 | Q28: 25-11-2025 | R28: 2011 | S28: 200088680
A29: 149f09f4-c7a5-4d1b-b86f-e6ea6f42e7b6 | B29: 149ec380-fbd9-41fa-9eb6-c8ff903ad1d7 | C29: Reversal Entries | D29: Reversal Entries | E29: ledger | F29: 03-06-2025 | H29: clearing | I29: AB | K29: 31206 | L29: Pre-C-2.5_A-party | M29: 03-Aug-26 04:10 PM | N29: 200018416 | O29: 03-06-2025 | P29: 0 | Q29: 03-06-2025 | R29: 2013 | S29: 200018416
A30: 14a73fa4-f592-4256-a8df-91ad3e24460e | B30: 91814e54-584f-31b8-ba2b-545bfc0c2324 | C30: Write off / Rounding off | D30: Invoice Number Matched | E30: ledger | F30: 25-11-2025 | G30: GJ2501033865 | H30: invoice | I30: RV | K30: 15708.4 | L30: PRI-INV1.5-company | M30: 03-Aug-26 04:10 PM | N30: 200096733 | O30: 10-12-2025 | P30: 0 | Q30: 25-11-2025 | R30: 2011 | S30: 277793 | T30: 95928487
A31: 15444b80-880c-4bfe-9453-bd2c96d68923 | B31: f98a9ac6-5777-4d9f-8feb-7904cb1cc621 | C31: Reversal Entries | D31: Reversal Entries | E31: ledger | F31: 29-11-2025 | H31: clearing | I31: AB | K31: -17802.84 | L31: Pre-C-2.5_A-party | M31: 03-Aug-26 04:10 PM | N31: 200091069 | O31: 29-11-2025 | P31: 0 | Q31: 29-11-2025 | R31: 2011 | S31: 200091069
A32: 155f2771-413a-4152-ba80-ba9ce52044f3 | B32: d33eeb97-4899-39b1-bcb0-960e121f42df | C32: Reconciled | D32: Date and Amount Matched | E32: ledger | F32: 31-07-2025 | H32: payment | I32: DZ | J32: /103010300003186-AXIS Bank | K32: -68069.01 | L32: PRI-PAY10.1-company | M32: 03-Aug-26 04:10 PM | N32: 200041895 | O32: 31-07-2025 | P32: 0 | Q32: 31-07-2025 | R32: 2013 | S32: 1400038901 | U32: UTIBN62025073104592284
A33: 158782ac-7fdf-4d79-ae6d-b69b241f63ff | B33: da8657e1-964d-32d8-9300-64be2eda94a1 | C33: Reconciled | D33: Date and Amount Matched | E33: ledger | F33: 17-12-2025 | H33: payment | I33: DZ | J33: /103010300003186-AXIS Bank | K33: -8120 | L33: PRI-PAY10.1-company | M33: 03-Aug-26 04:10 PM | N33: 200098081 | O33: 17-12-2025 | P33: 0 | Q33: 17-12-2025 | R33: 2013 | S33: 1400083474 | U33: AXISCN1190257713
A34: 16d98f5b-7192-4f4f-9581-3d76cc11477d | B34: 0f6b9183-9481-3ca8-ad34-d9c464fc060c | C34: Reconciled | D34: Invoice Number Matched | E34: ledger | F34: 27-01-2026 | G34: GJ2501043584 | H34: invoice | I34: RV | K34: 14661.16 | L34: PRI-INV1.5_A-company | M34: 03-Aug-26 04:10 PM | N34: 200126611 | O34: 12-02-2026 | P34: 0 | Q34: 27-01-2026 | R34: 2011 | S34: 353506 | T34: 96004228
A35: 16f02c90-edb7-4825-86c9-4e8372a51636 | B35: fe608291-7448-3f39-91ac-140875e7915b | C35: Reconciled | D35: Invoice Number Matched | E35: ledger | F35: 23-08-2025 | G35: GJ2501020519 | H35: invoice | I35: RV | K35: 15289.51 | L35: PRI-INV1.5_A-company | M35: 03-Aug-26 04:10 PM | N35: 200054006 | O35: 02-09-2025 | P35: 0 | Q35: 23-08-2025 | R35: 2011 | S35: 167823 | T35: 95818450
A36: 1740d2f7-3fab-472d-91a8-420f80387a17 | B36: 700a33ce-6808-3db0-9a5b-a182d02449c5 | C36: Reconciled | D36: Invoice Number Matched | E36: ledger | F36: 14-11-2025 | G36: GJ2501032227 | H36: invoice | I36: RV | K36: 11100.61 | L36: PRI-INV1.5_A-company | M36: 03-Aug-26 04:10 PM | N36: 200091315 | O36: 30-11-2025 | P36: 0 | Q36: 14-11-2025 | R36: 2011 | S36: 265464 | T36: 95916154
A37: 1753e470-c31e-44ee-8c22-932192d984dc | B37: 0ca1f6e1-3818-37d8-abe4-e28760ace981 | C37: TDS Booked by Company | D37: Invoice Number Matched | E37: ledger | F37: 05-07-2025 | G37: GJ2502001220 | H37: invoice | I37: RV | K37: 8260 | L37: PRI-INV1.6-company | M37: 03-Aug-26 04:10 PM | N37: 200037013 | O37: 21-07-2025 | P37: 0 | Q37: 05-07-2025 | R37: 2011 | S37: 110379 | T37: 95760979
A38: 17655b2c-d5fc-48dd-bb8c-923ebe380450 | B38: b2a4ff80-32f9-31d2-8704-648fcecc7070 | C38: Reconciled | D38: Invoice Number Matched | E38: ledger | F38: 10-06-2025 | G38: GJ2501009730 | H38: invoice | I38: RV | K38: 16336.73 | L38: PRI-INV1.5_A-company | M38: 03-Aug-26 04:10 PM | N38: 200024536 | O38: 25-06-2025 | P38: 0 | Q38: 10-06-2025 | R38: 2011 | S38: 80971 | T38: 95731557
A39: 17a5ef28-9953-409a-a6ed-1cdf37c6154f | B39: 5a11d8eb-95aa-4227-bd6b-6d9f778d7f7f | C39: Reversal Entries | D39: Reversal Entries | E39: ledger | F39: 21-10-2025 | H39: clearing | I39: AB | K39: 55503 | L39: Pre-C-2.5_A-party | M39: 03-Aug-26 04:10 PM | N39: 200070021 | O39: 21-10-2025 | P39: 0 | Q39: 21-10-2025 | R39: 2011 | S39: 200070021
A40: 17ccad7b-dc1b-4889-b3d9-f99186799596 | B40: c9e17340-60a5-3f13-bb4d-e24fad13ca50 | C40: Reconciled | D40: Multiple Date and Amount Matched | E40: ledger | F40: 15-09-2025 | H40: payment | I40: DZ | J40: /103010300003186-AXIS Bank | K40: -70792.53 | L40: PRI-PAY1.1-company | M40: 03-Aug-26 04:10 PM | N40: 200058566 | O40: 16-09-2025 | P40: 0 | Q40: 15-09-2025 | R40: 2013 | S40: 1400053494 | U40: UTIBN62025091596490274
A41: 184ca2a4-f68a-45d2-88df-362cab45cae8 | B41: b4876d7d-32da-4c2d-8b97-89018f31cac4 | C41: Reversal Entries | D41: Reversal Entries | E41: ledger | F41: 06-05-2025 | H41: clearing | I41: AB | K41: 15498.94 | L41: Pre-C-2.5_A-party | M41: 03-Aug-26 04:10 PM | N41: 200009479 | O41: 06-05-2025 | P41: 0 | Q41: 06-05-2025 | R41: 2013 | S41: 200009479
A42: 19133cf4-0ed9-4d39-a47f-c8855b923e82 | B42: 8959f92a-735c-399d-9436-e0fdd81deeda | C42: Reconciled | D42: Date and Amount Matched | E42: ledger | F42: 16-10-2025 | H42: payment | I42: DZ | J42: /103010300003186-AXIS Bank | K42: -18012 | L42: PRI-PAY10.1-company | M42: 03-Aug-26 04:10 PM | N42: 200069296 | O42: 17-10-2025 | P42: 0 | Q42: 16-10-2025 | R42: 2013 | S42: 1400063763 | U42: UTIBN62025101647212245
A43: 1a204ff6-5903-4f84-a6cf-d5495242278c | B43: b148a281-cccf-354a-b15b-b143e10c603e | C43: Reconciled | D43: Date and Amount Matched | E43: ledger | F43: 05-02-2026 | H43: payment | I43: DZ | J43: /103010300003186-AXIS Bank | K43: -16546 | L43: PRI-PAY10.1-company | M43: 03-Aug-26 04:10 PM | N43: 200125480 | O43: 06-02-2026 | P43: 0 | Q43: 05-02-2026 | R43: 2013 | S43: 1400100643 | U43: AXISCN1241656657
A44: 1a39cb45-510a-4baf-9131-4a62d9a97842 | B44: 93838ab0-ca5e-366e-a06a-38f236f3b468 | C44: Reconciled | D44: Invoice Number Matched | E44: ledger | F44: 03-11-2025 | G44: GJ2501030509 | H44: invoice | I44: RV | K44: 16336.73 | L44: PRI-INV1.5_A-company | M44: 03-Aug-26 04:10 PM | N44: 200087189 | O44: 18-11-2025 | P44: 0 | Q44: 03-11-2025 | R44: 2011 | S44: 251330 | T44: 95902014
A45: 1a6d541d-e405-48bf-bd71-63182e6282ae | B45: b2de2f6d-260c-44e2-9af8-09ba1e698786 | C45: Reversal Entries | D45: Reversal Entries | E45: ledger | F45: 10-12-2025 | H45: clearing | I45: AB | K45: 15708 | L45: Pre-C-2.5_A-party | M45: 03-Aug-26 04:10 PM | N45: 200096733 | O45: 10-12-2025 | P45: 0 | Q45: 10-12-2025 | R45: 2011 | S45: 200096733
A46: 1b33cab4-0057-4d25-8ee1-a957c028bbf7 | B46: 84b1a3c1-3cab-42ed-844c-49b665fd3bb5 | C46: Reversal Entries | D46: Reversal Entries | E46: ledger | F46: 12-06-2025 | H46: clearing | I46: AB | K46: -17383.97 | L46: Pre-C-2.5_A-party | M46: 03-Aug-26 04:10 PM | N46: 200021991 | O46: 12-06-2025 | P46: 0 | Q46: 12-06-2025 | R46: 2011 | S46: 200021991
A47: 1b7bc51b-ebf7-45d6-8b00-73a7c0d47ffe | B47: 12df1500-5005-40c3-85f2-7d0f4e5e944e | C47: Reconciled | D47: Date Range and Amount Matched | E47: ledger | F47: 11-11-2025 | H47: payment | I47: DZ | J47: /103010300003186-AXIS Bank | K47: -55663.4 | L47: PRI-PAY11.1-company | M47: 03-Aug-26 04:10 PM | N47: 200086152 | O47: 12-11-2025 | P47: 0 | Q47: 11-11-2025 | R47: 2013 | S47: 1400071392 | U47: UTIBN62025111147126173
A48: 1bc989be-a34e-4008-ac77-42fb424027c4 | B48: e8d25d0a-54e8-38fc-a90a-d2174fd7b709 | C48: Reconciled | D48: Invoice Number Matched | E48: ledger | F48: 24-01-2026 | G48: GJ2501043251 | H48: invoice | I48: RV | K48: 16336.73 | L48: PRI-INV1.5_A-company | M48: 03-Aug-26 04:10 PM | N48: 200126457 | O48: 11-02-2026 | P48: 0 | Q48: 24-01-2026 | R48: 2011 | S48: 350988 | T48: 96001709
A49: 1d1c64d9-f561-4d82-aad9-d48d5a82c3d8 | B49: e1ee8629-ac50-3b80-8305-8d3c66141bb9 | C49: Reconciled | D49: Invoice Number Matched | E49: ledger | F49: 04-02-2026 | G49: GJ2501044936 | H49: invoice | I49: RV | K49: 13613.94 | L49: PRI-INV1.5_A-company | M49: 03-Aug-26 04:10 PM | N49: 200128540 | O49: 21-02-2026 | P49: 0 | Q49: 04-02-2026 | R49: 2011 | S49: 364062 | T49: 96014797
A50: 1d50bebf-2587-41e4-87e0-522d83f06edd | B50: b1127b6c-9ebc-4778-9fbf-e92ccdeadead | C50: Reversal Entries | D50: Reversal Entries | E50: ledger | F50: 23-12-2025 | H50: clearing | I50: AB | K50: -28903.45 | L50: Pre-C-2.5_A-party | M50: 03-Aug-26 04:10 PM | N50: 200098952 | O50: 23-12-2025 | P50: 0 | Q50: 23-12-2025 | R50: 2011 | S50: 200098952
A51: 1f4d0aec-9ff4-4f00-acb4-317ede02a2f7 | B51: 26fa3e12-ca1a-3ca8-a155-66251540de79 | C51: Reconciled | D51: Invoice Number Matched | E51: ledger | F51: 22-11-2025 | G51: GJ2501033465 | H51: invoice | I51: RV | K51: 14032.83 | L51: PRI-INV1.5_A-company | M51: 03-Aug-26 04:10 PM | N51: 200096546 | O51: 09-12-2025 | P51: 0 | Q51: 22-11-2025 | R51: 2011 | S51: 274707 | T51: 95925401
A52: 1fafef18-af9f-4680-8b53-63964cbe3e07 | B52: 03d9b23e-c626-3277-ba22-bf72070d5dee | C52: Write off / Rounding off | D52: Invoice Number Matched | E52: ledger | F52: 07-07-2025 | G52: GJ2501013614 | H52: invoice | I52: RV | K52: 16755.62 | L52: PRI-INV1.5-company | M52: 03-Aug-26 04:10 PM | N52: 200037013 | O52: 21-07-2025 | P52: 0 | Q52: 07-07-2025 | R52: 2011 | S52: 113265 | T52: 95763865
A53: 1fcfc845-212e-4e79-bbb4-3f5587588d4b | B53: 1a6a0089-7afe-4b4c-8580-9420e7ed7d49 | C53: Reversal Entries | D53: Reversal Entries | E53: ledger | F53: 20-06-2025 | H53: clearing | I53: AB | K53: 32672 | L53: Pre-C-2.5_A-party | M53: 03-Aug-26 04:10 PM | N53: 200023347 | O53: 20-06-2025 | P53: 0 | Q53: 20-06-2025 | R53: 2011 | S53: 200023347
A54: 207c331d-630c-42d1-b1e4-9d28f0e950d9 | B54: 2918bdfb-6092-4b54-8783-26740eed566b | C54: Reversal Entries | D54: Reversal Entries | E54: ledger | F54: 25-06-2025 | H54: clearing | I54: AB | K54: 16336.73 | L54: Pre-C-2.5_A-party | M54: 03-Aug-26 04:10 PM | N54: 200024536 | O54: 25-06-2025 | P54: 0 | Q54: 25-06-2025 | R54: 2011 | S54: 200024536
A55: 207cf4eb-c2aa-4c87-947a-9565bda46afa | B55: 980b495e-9ee2-402d-b82a-86b60016ef60 | C55: Reversal Entries | D55: Reversal Entries | E55: ledger | F55: 20-12-2025 | H55: clearing | I55: AB | K55: -55712.45 | L55: Pre-C-2.5_A-party | M55: 03-Aug-26 04:10 PM | N55: 200098711 | O55: 20-12-2025 | P55: 0 | Q55: 20-12-2025 | R55: 2011 | S55: 200098711
A56: 20837353-19d9-49e6-9553-0e460d3263b6 | B56: de1ae23b-07e3-3976-be29-2a4167fb452c | C56: Reconciled | D56: Invoice Number Matched | E56: ledger | F56: 18-06-2025 | G56: GJ2501010892 | H56: invoice | I56: RV | K56: 17174.51 | L56: PRI-INV1.5_A-company | M56: 03-Aug-26 04:10 PM | N56: 200027381 | O56: 30-06-2025 | P56: 0 | Q56: 18-06-2025 | R56: 2011 | S56: 89882 | T56: 95740472
A57: 20a21d69-c290-4c27-aade-0c3a3fcd4b47 | B57: d6abccce-cf1b-3097-b5e6-1f4af9653720 | C57: Write off / Rounding off | D57: Invoice Number Matched | E57: ledger | F57: 12-09-2025 | G57: GJ2501023476 | H57: invoice | I57: RV | K57: 17593.4 | L57: PRI-INV1.5-company | M57: 03-Aug-26 04:10 PM | N57: 200060952 | O57: 26-09-2025 | P57: 0 | Q57: 12-09-2025 | R57: 2011 | S57: 192191 | T57: 95842834
A58: 20ac92f2-ef5d-4f4e-bba2-e74002936ff4 | B58: 4ebbce22-4de8-3461-9656-ac7defeab5a9 | C58: Reconciled | D58: Invoice Number Matched | E58: ledger | F58: 27-12-2025 | G58: GJ2501038910 | H58: invoice | I58: RV | K58: 16127.29 | L58: PRI-INV1.5_A-company | M58: 03-Aug-26 04:10 PM | N58: 200110398 | O58: 17-01-2026 | P58: 0 | Q58: 27-12-2025 | R58: 2011 | S58: 316973 | T58: 95967690
A59: 20db8847-6437-4c8a-b8ba-8e21b10cf9dc | B59: 7a242570-6228-3a64-822d-5c375c447a38 | C59: Reconciled | D59: Invoice Number Matched | E59: ledger | F59: 02-12-2025 | G59: GJ2501034960 | H59: invoice | I59: RV | K59: 11519.5 | L59: PRI-INV1.5_A-company | M59: 03-Aug-26 04:10 PM | N59: 200098711 | O59: 20-12-2025 | P59: 0 | Q59: 02-12-2025 | R59: 2011 | S59: 287055 | T59: 95937759
A60: 21e3d399-b32e-4215-99c2-eeef0cb437cc | B60: 5b84e596-750b-30a9-bf9e-0990e2deb453 | C60: Write off / Rounding off | D60: Invoice Number Matched | E60: ledger | F60: 08-01-2026 | G60: GJ2501040801 | H60: invoice | I60: RV | K60: 16127.29 | L60: PRI-INV1.5-company | M60: 03-Aug-26 04:10 PM | N60: 200112844 | O60: 29-01-2026 | P60: 0 | Q60: 08-01-2026 | R60: 2011 | S60: 333028 | T60: 95983748
A61: 21eef7b6-d5e8-4d7e-add6-5b60f1155196 | B61: e6421b9e-7afa-44d3-a110-38e09999f104 | C61: Reconciled | D61: Date Range and Amount Matched | E61: ledger | F61: 12-06-2025 | H61: payment | I61: DZ | J61: /103010300003186-AXIS Bank | K61: -17383.97 | L61: PRI-PAY11.1-company | M61: 03-Aug-26 04:10 PM | N61: 200021991 | O61: 12-06-2025 | P61: 0 | Q61: 12-06-2025 | R61: 2013 | S61: 1400021538 | U61: UTIBN62025061282539976
A62: 22054b46-59f7-416e-b6b6-7ed15074ffd3 | B62: a3b604a7-b5c3-3429-ada6-1cb8ff64318c | C62: Reconciled | D62: Invoice Number Matched | E62: ledger | F62: 14-10-2025 | G62: GJ2501028078 | H62: invoice | I62: RV | K62: 7958.93 | L62: PRI-INV1.5_A-company | M62: 03-Aug-26 04:10 PM | N62: 200070021 | O62: 21-10-2025 | P62: 0 | Q62: 14-10-2025 | R62: 2011 | S62: 229847 | T62: 95880521
A63: 221f9fab-5799-46d6-b5f8-5c07f3ffcd61 | B63: 6198436a-eccb-41b8-a193-6da64685ba82 | C63: Reversal Entries | D63: Reversal Entries | E63: ledger | F63: 22-04-2025 | H63: clearing | I63: AB | K63: 18431.19 | L63: Pre-C-2.5_A-party | M63: 03-Aug-26 04:10 PM | N63: 200002365 | O63: 22-04-2025 | P63: 0 | Q63: 22-04-2025 | R63: 2013 | S63: 200002365
A64: 223b4917-7bb6-4d0b-a1e6-1a09de4e5ba4 | B64: 14106f01-4bbc-3296-9e9f-428271999dbc | C64: Write off / Rounding off | D64: Invoice Number Matched | E64: ledger | F64: 13-09-2025 | G64: GJ2501023625 | H64: invoice | I64: RV | K64: 17802.84 | L64: PRI-INV1.5-company | M64: 03-Aug-26 04:10 PM | N64: 200061245 | O64: 27-09-2025 | P64: 0 | Q64: 13-09-2025 | R64: 2011 | S64: 193312 | T64: 95843955
A65: 224035a9-72ee-46aa-a52e-3bd1c704baab | B65: 31aedadb-a547-3763-8812-c616b17cb02b | C65: Reconciled | D65: Amount Matched - Recommended | E65: ledger | F65: 12-06-2025 | H65: payment | I65: DZ | J65: /103010300003186-AXIS Bank | K65: -17383.97 | L65: SEC-PAY1.1-company | M65: 03-Aug-26 04:10 PM | N65: 200022072 | O65: 13-06-2025 | P65: 0 | Q65: 12-06-2025 | R65: 2013 | S65: 1400021816 | U65: UTIBN62025061285667179
A66: 224c2a2e-04eb-4ed9-b847-f9a4b8d8409b | B66: 51b2c694-af40-3302-ae82-b33980e1516a | C66: Write off / Rounding off | D66: Invoice Number Matched | E66: ledger | F66: 18-05-2025 | G66: GJ2501006463 | H66: invoice | I66: RV | K66: 15498.94 | L66: PRI-INV1.5-company | M66: 03-Aug-26 04:10 PM | N66: 200020525 | O66: 05-06-2025 | P66: 0 | Q66: 18-05-2025 | R66: 2011 | S66: 53947 | T66: 95704525
A67: 22851b8b-1969-4590-a3b5-8d6620d3dee0 | B67: 0a46fe88-ffcf-3e58-ad12-81417f99e660 | C67: Reconciled | D67: Date and Amount Matched | E67: ledger | F67: 10-12-2025 | H67: payment | I67: DZ | J67: /103010300003186-AXIS Bank | K67: -13613.94 | L67: PRI-PAY10.1-company | M67: 03-Aug-26 04:10 PM | N67: 200096971 | O67: 11-12-2025 | P67: 0 | Q67: 10-12-2025 | R67: 2013 | S67: 1400081325 | U67: AXISCN1182694459
A68: 23ec0c0f-90a6-4eb0-95df-ac6ef085830f | B68: 9d56db5b-e2aa-4182-b5fd-8c2c8726ecc8 | C68: Reversal Entries | D68: Reversal Entries | E68: ledger | F68: 30-06-2025 | H68: clearing | I68: AB | K68: 69744.91 | L68: Pre-C-2.5_A-party | M68: 03-Aug-26 04:10 PM | N68: 200027381 | O68: 30-06-2025 | P68: 0 | Q68: 30-06-2025 | R68: 2011 | S68: 200027381
A69: 240f9a90-4baf-443a-ae03-ba20b5d51d75 | B69: 10162f21-288c-48cb-91d5-edf930c57906 | C69: Reversal Entries | D69: Reversal Entries | E69: ledger | F69: 08-08-2025 | H69: clearing | I69: AB | K69: -30788.45 | L69: Pre-C-2.5_A-party | M69: 03-Aug-26 04:10 PM | N69: 200046049 | O69: 08-08-2025 | P69: 0 | Q69: 08-08-2025 | R69: 2011 | S69: 200046049
A70: 248218c7-0cd1-4ae3-8033-2ffc1c97d3c0 | B70: 37501d95-96eb-33fc-b7bc-dd6012e96168 | C70: Reconciled | D70: Date and Amount Matched | E70: ledger | F70: 28-01-2026 | H70: payment | I70: DZ | J70: /103010300003186-AXIS Bank | K70: -68858.83 | L70: PRI-PAY10.1-company | M70: 03-Aug-26 04:10 PM | N70: 200112844 | O70: 29-01-2026 | P70: 0 | Q70: 28-01-2026 | R70: 2013 | S70: 1400097263 | U70: AXISCN1233242839
A71: 25b1fee7-fab4-4022-9db8-1104f0efb8c0 | B71: 668f6036-0b75-410f-ae91-fad766c3105b | C71: Reversal Entries | D71: Reversal Entries | E71: ledger | F71: 11-12-2025 | H71: clearing | I71: AB | K71: -13613.94 | L71: Pre-C-2.5_A-party | M71: 03-Aug-26 04:10 PM | N71: 200096971 | O71: 11-12-2025 | P71: 0 | Q71: 11-12-2025 | R71: 2011 | S71: 200096971
A72: 263222aa-e691-4f56-bab2-250f45670f1e | B72: d25f1073-1f1c-374d-8329-0d17f3857157 | C72: Reconciled | D72: Invoice Number Matched | E72: ledger | F72: 29-05-2025 | G72: GJ2501008018 | H72: invoice | I72: RV | K72: 17383.97 | L72: PRI-INV1.5_A-company | M72: 03-Aug-26 04:10 PM | N72: 200022072 | O72: 13-06-2025 | P72: 0 | Q72: 29-05-2025 | R72: 2011 | S72: 65879 | T72: 95716461
A73: 270fadc2-2dd4-491d-a678-7a01a6309436 | B73: 1f264474-6827-4495-afa7-8f713c97bf9c | C73: Reversal Entries | D73: Reversal Entries | E73: ledger | F73: 15-04-2025 | H73: clearing | I73: AB | K73: 10262.03 | L73: Pre-C-2.5_A-party | M73: 03-Aug-26 04:10 PM | N73: 200001275 | O73: 15-04-2025 | P73: 0 | Q73: 15-04-2025 | R73: 2013 | S73: 200001275
A74: 274cbf64-6124-42d9-b466-acbb17b168c5 | B74: 81f7183e-94ce-35a0-9c16-64686cacc6c0 | C74: Write off / Rounding off | D74: Invoice Number Matched | E74: ledger | F74: 04-11-2025 | G74: GJ2501030618 | H74: invoice | I74: RV | K74: 14870.62 | L74: PRI-INV1.5-company | M74: 03-Aug-26 04:10 PM | N74: 200087189 | O74: 18-11-2025 | P74: 0 | Q74: 04-11-2025 | R74: 2011 | S74: 252519 | T74: 95903203
A75: 277f44fa-0491-4464-a86e-fa1deb4df070 | B75: ae867d04-fbab-4d25-b5a4-969e5ffd6f0c | C75: Reversal Entries | D75: Reversal Entries | E75: ledger | F75: 19-07-2025 | H75: clearing | I75: AB | K75: -9843.93 | L75: Pre-C-2.5_A-party | M75: 03-Aug-26 04:10 PM | N75: 200036696 | O75: 19-07-2025 | P75: 0 | Q75: 19-07-2025 | R75: 2011 | S75: 200036696
A76: 27ade58e-2500-42e7-a86d-56d5a5b404e5 | B76: 47ead911-e592-4cb2-9068-eb74423df62b | C76: Reversal Entries | D76: Reversal Entries | E76: ledger | F76: 16-09-2025 | H76: clearing | I76: AB | K76: -70792.53 | L76: Pre-C-2.5_A-party | M76: 03-Aug-26 04:10 PM | N76: 200058566 | O76: 16-09-2025 | P76: 0 | Q76: 16-09-2025 | R76: 2011 | S76: 200058566
A77: 27bdac70-5b9d-46d2-963d-c72d86ae0aff | B77: b7053c89-98b4-3951-a3a1-c61bda28f0c6 | C77: Reconciled | D77: Invoice Number Matched | E77: ledger | F77: 23-07-2025 | G77: GJ2501016103 | H77: invoice | I77: RV | K77: 12776.16 | L77: PRI-INV1.5_A-company | M77: 03-Aug-26 04:10 PM | N77: 200041895 | O77: 31-07-2025 | P77: 0 | Q77: 23-07-2025 | R77: 2011 | S77: 131510 | T77: 95782129
A78: 280ebc78-4c2e-4064-a4fb-6b0d8cdb0c55 | B78: f2609882-01d3-4ec8-aa12-d6dd35aa8191 | C78: Reconciled | D78: Partial Invoice Number with Date Range | E78: ledger | F78: 14-02-2026 | G78: GJ2501046561 | H78: invoice | I78: RV | K78: 34443.2 | L78: PRI-INV3.1-company | M78: 03-Aug-26 04:10 PM | N78: 1400110157 | O78: 05-03-2026 | P78: 0 | Q78: 14-02-2026 | R78: 2121 | S78: 377110 | T78: 96027858
A79: 28bd8318-88d5-4aeb-993c-3d2d05faae44 | C79: Other entry not booked by Company | D79: Unmatched | E79: ledger | F79: 12-11-2025 | H79: clearing | I79: AB | K79: 55663.4 | L79: Post-P-3.6-party | M79: 03-Aug-26 04:10 PM | N79: 200086152 | O79: 12-11-2025 | P79: 0 | Q79: 12-11-2025 | R79: 2011 | S79: 200086152
A80: 29b85579-6faf-43f5-97c2-052d7795ce05 | B80: c9ecc749-acff-32ad-80b7-5c45cad4fcd1 | C80: Reconciled | D80: Invoice Number Matched | E80: ledger | F80: 21-01-2026 | G80: GJ2501042729 | H80: invoice | I80: RV | K80: 14242.29 | L80: PRI-INV1.5_A-company | M80: 03-Aug-26 04:10 PM | N80: 200126177 | O80: 10-02-2026 | P80: 0 | Q80: 21-01-2026 | R80: 2011 | S80: 347254 | T80: 95997975
A81: 2a17b063-4f6f-480e-905d-a75f2874026c | B81: ccc47501-6c15-4e88-afa6-79454c52a951 | C81: Reconciled | D81: Date Range and Amount Matched | E81: ledger | F81: 08-07-2025 | H81: payment | I81: DZ | J81: /103010300003186-AXIS Bank | K81: -82521.42 | L81: PRI-PAY11.1-company | M81: 03-Aug-26 04:10 PM | N81: 200034767 | O81: 09-07-2025 | P81: 0 | Q81: 08-07-2025 | R81: 2013 | S81: 1400030335 | U81: UTIBN62025070853562047
A82: 2afd2ce6-071b-4456-ab9a-82aa19ee14d5 | B82: 9cbd904f-5700-3871-9921-9f1f23a1dd26 | C82: Write off / Rounding off | D82: Invoice Number Matched | E82: ledger | F82: 25-07-2025 | G82: GJ2501016421 | H82: invoice | I82: RV | K82: 12566.72 | L82: PRI-INV1.5-company | M82: 03-Aug-26 04:10 PM | N82: 200041895 | O82: 31-07-2025 | P82: 0 | Q82: 25-07-2025 | R82: 2011 | S82: 133976 | T82: 95784597
A83: 2bff043f-35aa-49c1-8583-05ff53561880 | B83: b5a9f204-b92c-4cd8-80fa-11ab7201ec58 | C83: Reversal Entries | D83: Reversal Entries | E83: ledger | F83: 25-12-2025 | H83: clearing | I83: AB | K83: 29531 | L83: Pre-C-2.5_A-party | M83: 03-Aug-26 04:10 PM | N83: 200099446 | O83: 25-12-2025 | P83: 0 | Q83: 25-12-2025 | R83: 2011 | S83: 200099446
A84: 2c065656-fad2-46f7-98e8-29ef02d44e77 | B84: 85a5bfe5-9156-4f59-bbd0-0fcb7c546a7e | C84: Reversal Entries | D84: Reversal Entries | E84: ledger | F84: 31-01-2026 | H84: clearing | I84: AB | K84: -15498.94 | L84: Pre-C-2.5_A-party | M84: 03-Aug-26 04:10 PM | N84: 200121181 | O84: 31-01-2026 | P84: 0 | Q84: 31-01-2026 | R84: 2011 | S84: 200121181
A85: 2c81b926-785d-491f-8edf-fafd643ad1b9 | B85: 3bebb504-b542-3e83-8a56-2da499f958e8 | C85: Reconciled | D85: Date and Amount Matched | E85: ledger | F85: 07-08-2025 | H85: payment | I85: DZ | J85: /103010300003186-AXIS Bank | K85: -30788.45 | L85: PRI-PAY10.1-company | M85: 03-Aug-26 04:10 PM | N85: 200046049 | O85: 08-08-2025 | P85: 0 | Q85: 07-08-2025 | R85: 2013 | S85: 1400041041 | U85: UTIBN62025080781675553
A86: 2c825c26-355e-4fb1-8b17-1826506c0a19 | B86: e4af4460-fe95-3dbb-b814-d3f5b88bc4d6 | C86: Write off / Rounding off | D86: Invoice Number Matched | E86: ledger | F86: 01-05-2025 | G86: GJ2501004125 | H86: invoice | I86: RV | K86: 19059.52 | L86: PRI-INV1.5-company | M86: 03-Aug-26 04:10 PM | N86: 200011454 | O86: 17-05-2025 | P86: 0 | Q86: 01-05-2025 | R86: 2011 | S86: 34494 | T86: 95685061
A87: 2cca9b47-bc43-4ae0-990f-430c6e867310 | B87: 9d026677-c54f-429a-9266-f0e4d5241d73 | C87: Reversal Entries | D87: Reversal Entries | E87: ledger | F87: 26-07-2025 | H87: clearing | I87: AB | K87: 57806.85 | L87: Pre-C-2.5_A-party | M87: 03-Aug-26 04:10 PM | N87: 200038962 | O87: 26-07-2025 | P87: 0 | Q87: 26-07-2025 | R87: 2011 | S87: 200038962
A88: 2d133dcf-986b-4c4e-b373-1f29b8236fbc | B88: ef739c6f-bc74-358d-b405-499f1bb75c8d | C88: Reconciled | D88: Invoice Number Matched | E88: ledger | F88: 21-09-2025 | G88: GJ2501024881 | H88: invoice | I88: RV | K88: 16336.73 | L88: PRI-INV1.5_A-company | M88: 03-Aug-26 04:10 PM | N88: 200068101 | O88: 10-10-2025 | P88: 0 | Q88: 21-09-2025 | R88: 2011 | S88: 202803 | T88: 95853456
A89: 2d1b68b2-e677-40db-bd06-00f4643906b3 | B89: 9d760968-ef08-3bab-912c-4590a17d9428 | C89: Reconciled | D89: Invoice Number Matched | E89: ledger | F89: 03-07-2025 | G89: GJ2501013122 | H89: invoice | I89: RV | K89: 13404.5 | L89: PRI-INV1.5_A-company | M89: 03-Aug-26 04:10 PM | N89: 200037013 | O89: 21-07-2025 | P89: 0 | Q89: 03-07-2025 | R89: 2011 | S89: 107833 | T89: 95758433
A90: 2d72b0cc-7cab-49d0-961b-b6c03c4fd2ce | B90: 2638a380-d1d3-4269-b818-9ecfb64d4217 | C90: Reversal Entries | D90: Reversal Entries | E90: ledger | F90: 10-05-2025 | H90: clearing | I90: AB | K90: 40841 | L90: Pre-C-2.5_A-party | M90: 03-Aug-26 04:10 PM | N90: 200010428 | O90: 10-05-2025 | P90: 0 | Q90: 10-05-2025 | R90: 2013 | S90: 200010428
A91: 2f09a670-f8bb-488d-b481-f68bc079c1fb | B91: 7d8439fa-3569-3d4d-8e04-483f90e32539 | C91: TDS Booked by Company | D91: Invoice Number Matched | E91: ledger | F91: 05-09-2025 | G91: GJ2502001991 | H91: invoice | I91: RV | K91: 8260 | L91: PRI-INV1.6-company | M91: 03-Aug-26 04:10 PM | N91: 200086152 | O91: 12-11-2025 | P91: 0 | Q91: 05-09-2025 | R91: 2011 | S91: 183350 | T91: 95833989
A92: 2f6b4d52-d663-455a-8a7e-813872f903ac | B92: b4876d7d-32da-4c2d-8b97-89018f31cac4 | C92: Reversal Entries | D92: Reversal Entries | E92: ledger | F92: 16-10-2025 | H92: clearing | I92: AB | K92: -15498.94 | L92: Pre-C-2.5_A-party | M92: 03-Aug-26 04:10 PM | N92: 200069083 | O92: 16-10-2025 | P92: 0 | Q92: 16-10-2025 | R92: 2011 | S92: 200069083
A93: 2f8d25ca-fa7e-480a-9037-b97cd20732a4 | B93: efe49972-94ba-3d7a-8a22-31a7a98dc7f3 | C93: Reconciled | D93: Invoice Number Matched | E93: ledger | F93: 31-12-2025 | G93: GJ2501039511 | H93: invoice | I93: RV | K93: 16336.73 | L93: PRI-INV1.5_A-company | M93: 03-Aug-26 04:10 PM | N93: 200111423 | O93: 21-01-2026 | P93: 0 | Q93: 31-12-2025 | R93: 2011 | S93: 321383 | T93: 95972095
A94: 30061288-e954-489e-a6dd-8a6fee6238bb | B94: 41468cf6-499f-360d-a95c-d3e680c3880e | C94: Reconciled | D94: Invoice Number Matched | E94: ledger | F94: 24-07-2025 | G94: GJ2501016291 | H94: invoice | I94: RV | K94: 15289.51 | L94: PRI-INV1.5_A-company | M94: 03-Aug-26 04:10 PM | N94: 200041895 | O94: 31-07-2025 | P94: 0 | Q94: 24-07-2025 | R94: 2011 | S94: 132975 | T94: 95783596
A95: 3014f51c-7268-4d5d-b101-9228bb740fb8 | B95: 79756b90-582c-3d89-abba-6e48f7dfb1b1 | C95: Reconciled | D95: Date and Amount Matched | E95: ledger | F95: 16-03-2026 | H95: payment | I95: DZ | J95: NEFT Cr-UTIB0001636-EMCURE PHARMACEUTICALS LIMITED | K95: -66363.1 | L95: PRI-PAY10.1-company | M95: 03-Aug-26 04:10 PM | N95: 1400114142 | O95: 17-03-2026 | P95: 0 | Q95: 17-03-2026 | R95: 2013 | S95: 1400114142 | U95: AXISCN1283769768
A96: 3056e998-f7f0-4652-87ab-64536447b613 | B96: b7aa72a1-1136-31ee-931f-649999502def | C96: Reconciled | D96: Invoice Number Matched | E96: ledger | F96: 19-06-2025 | G96: GJ2501011105 | H96: invoice | I96: RV | K96: 17593.4 | L96: PRI-INV1.5_A-company | M96: 03-Aug-26 04:10 PM | N96: 200027381 | O96: 30-06-2025 | P96: 0 | Q96: 19-06-2025 | R96: 2011 | S96: 91219 | T96: 95741809
A97: 305abaf4-6251-43e2-aba4-5faef4feadf9 | B97: 14deb597-3df5-4d6e-8e72-fe2245cf5db3 | C97: Reversal Entries | D97: Reversal Entries | E97: ledger | F97: 13-06-2025 | H97: clearing | I97: AB | K97: -17383.97 | L97: Pre-C-2.5_A-party | M97: 03-Aug-26 04:10 PM | N97: 200022072 | O97: 13-06-2025 | P97: 0 | Q97: 13-06-2025 | R97: 2011 | S97: 200022072
A98: 30830ff1-31d5-4a07-939d-7f7d808a80f7 | B98: 558c6bcf-926f-4540-8ecf-d62e0b000546 | C98: Reversal Entries | D98: Reversal Entries | E98: ledger | F98: 29-05-2025 | H98: clearing | I98: AB | K98: 31207 | L98: Pre-C-2.5_A-party | M98: 03-Aug-26 04:10 PM | N98: 200014351 | O98: 29-05-2025 | P98: 0 | Q98: 29-05-2025 | R98: 2013 | S98: 200014351
A99: 30fbd80f-c539-459c-ab3e-b45c361fce33 | B99: 81c84be5-4d28-4542-81e1-fba84e2c7f54 | C99: Reconciled | D99: Date Range and Amount Matched | E99: ledger | F99: 26-09-2025 | H99: payment | I99: DZ | J99: /103010300003186-AXIS Bank | K99: -17593 | L99: PRI-PAY11.1-company | M99: 03-Aug-26 04:10 PM | N99: 200060952 | O99: 26-09-2025 | P99: 0 | Q99: 26-09-2025 | R99: 2013 | S99: 1400057212 | U99: UTIBN62025092605993972
A100: 3122328d-4e8f-4214-b6ed-1a5d29b5e118 | C100: Other entry not booked by Company | D100: Unmatched | E100: ledger | F100: 06-05-2025 | H100: clearing | I100: AB | K100: 95505.13 | L100: Post-P-3.6-party | M100: 03-Aug-26 04:10 PM | N100: 200009477 | O100: 06-05-2025 | P100: 0 | Q100: 06-05-2025 | R100: 2013 | S100: 200009477
...
