Workbook

Sheet Summary
A1: Party Name | B1: LYKA LABORATORIES LTD. | C1: Date Tolerance | D1: 0 - 15
A2: Reconciliation Period | B2: 01-Apr-2025 to 31-Mar-2026 | C2: TDS Percentage | D2: 0.0 - 10.0
A3: Statement Type | B3: Ledger | C3: Amount Tolerance | D3: 1.0 Rs
A4: Party Type | B4: Vendor
A5: Reconciliation Date | B5: 19-Jun-26 10:16 AM
A7: Reconciliation Statement
A8: Particulars | B8: Annexure | C8: Amount | D8: No. of Entries | E8: Action Required
A9: Closing Balance Difference | C9: =SUM(C10:C11) -> 0 | D9: =SUM(D10:D11) -> 0
A10: Closing Balance as per Company | C10: =-(SUMIFS(Reconciliation!L:L,Reconciliation!D:D,A10,Reconciliation!F:F,"ledger") +SUMIFS(Reconciliation!S:S,Reconciliation!D:D,A10,Reconciliation!M:M,"ledger")) -> 0 | D10: =COUNTIFS(Reconciliation!D:D,A10,Reconciliation!F:F,"ledger") +COUNTIFS(Reconciliation!D:D,A10,Reconciliation!M:M,"ledger") -> 0
A11: Closing Balance as per Party | C11: =-(SUMIFS(Reconciliation!L:L,Reconciliation!D:D,A11,Reconciliation!F:F,"ledger") +SUMIFS(Reconciliation!S:S,Reconciliation!D:D,A11,Reconciliation!M:M,"ledger")) -> 0 | D11: =COUNTIFS(Reconciliation!D:D,A11,Reconciliation!F:F,"ledger") +COUNTIFS(Reconciliation!D:D,A11,Reconciliation!M:M,"ledger") -> 0
A13: Invoice Difference | C13: =SUM(C14:C15) -> 0 | D13: =SUM(D14:D15) -> 0
A14: Invoice not booked by Company | B14: 1 | C14: =SUMIFS(Reconciliation!L:L,Reconciliation!D:D,A14,Reconciliation!F:F,"ledger") +SUMIFS(Reconciliation!S:S,Reconciliation!D:D,A14,Reconciliation!M:M,"ledger") -> 0 | D14: =COUNTIFS(Reconciliation!D:D,A14,Reconciliation!F:F,"ledger") +COUNTIFS(Reconciliation!D:D,A14,Reconciliation!M:M,"ledger") -> 0 | E14: Vendor to provide the invoice copies
A15: Invoice not booked by Party | B15: 10 | C15: =SUMIFS(Reconciliation!L:L,Reconciliation!D:D,A15,Reconciliation!F:F,"ledger") +SUMIFS(Reconciliation!S:S,Reconciliation!D:D,A15,Reconciliation!M:M,"ledger") -> 0 | D15: =COUNTIFS(Reconciliation!D:D,A15,Reconciliation!F:F,"ledger") +COUNTIFS(Reconciliation!D:D,A15,Reconciliation!M:M,"ledger") -> 0 | E15: Vendor to check the reason for invoice not appearing
A16: Debit Note / Credit Note Difference | C16: =SUM(C17:C17) -> 0 | D16: =SUM(D17:D17) -> 0
A17: Credit Note not booked by Company | B17: 23 | C17: =SUMIFS(Reconciliation!L:L,Reconciliation!D:D,A17,Reconciliation!F:F,"ledger") +SUMIFS(Reconciliation!S:S,Reconciliation!D:D,A17,Reconciliation!M:M,"ledger") -> 0 | D17: =COUNTIFS(Reconciliation!D:D,A17,Reconciliation!F:F,"ledger") +COUNTIFS(Reconciliation!D:D,A17,Reconciliation!M:M,"ledger") -> 0 | E17: Company to book the Debit Note and recover from Vendor
A18: Payment / receipt Difference | C18: =SUM(C19:C20) -> 0 | D18: =SUM(D19:D20) -> 0
A19: Payment not booked by Company | B19: 55 | C19: =SUMIFS(Reconciliation!L:L,Reconciliation!D:D,A19,Reconciliation!F:F,"ledger") +SUMIFS(Reconciliation!S:S,Reconciliation!D:D,A19,Reconciliation!M:M,"ledger") -> 0 | D19: =COUNTIFS(Reconciliation!D:D,A19,Reconciliation!F:F,"ledger") +COUNTIFS(Reconciliation!D:D,A19,Reconciliation!M:M,"ledger") -> 0 | E19: Company to book the payment entries
A20: Payment not booked by Party | B20: 61 | C20: =SUMIFS(Reconciliation!L:L,Reconciliation!D:D,A20,Reconciliation!F:F,"ledger") +SUMIFS(Reconciliation!S:S,Reconciliation!D:D,A20,Reconciliation!M:M,"ledger") -> 0 | D20: =COUNTIFS(Reconciliation!D:D,A20,Reconciliation!F:F,"ledger") +COUNTIFS(Reconciliation!D:D,A20,Reconciliation!M:M,"ledger") -> 0 | E20: Vendor to check the payment details
A21: Other Differences | C21: =SUM(C22:C23) -> 0 | D21: =SUM(D22:D23) -> 0
A22: Other entry not booked by Company | B22: 74 | C22: =SUMIFS(Reconciliation!L:L,Reconciliation!D:D,A22,Reconciliation!F:F,"ledger") +SUMIFS(Reconciliation!S:S,Reconciliation!D:D,A22,Reconciliation!M:M,"ledger") -> 0 | D22: =COUNTIFS(Reconciliation!D:D,A22,Reconciliation!F:F,"ledger") +COUNTIFS(Reconciliation!D:D,A22,Reconciliation!M:M,"ledger") -> 0
A23: Other entry not booked by Party | B23: 79 | C23: =SUMIFS(Reconciliation!L:L,Reconciliation!D:D,A23,Reconciliation!F:F,"ledger") +SUMIFS(Reconciliation!S:S,Reconciliation!D:D,A23,Reconciliation!M:M,"ledger") -> 0 | D23: =COUNTIFS(Reconciliation!D:D,A23,Reconciliation!F:F,"ledger") +COUNTIFS(Reconciliation!D:D,A23,Reconciliation!M:M,"ledger") -> 0
A24: TDS / TCS Difference | C24: =SUM(C25:C26) -> 0 | D24: =SUM(D25:D26) -> 0
A25: TDS Booked by Company | B25: 94 | C25: =SUMIFS(Reconciliation!T:T,Reconciliation!D:D,A25) -SUMIFS(Reconciliation!T:T,Reconciliation!D:D,A25,Reconciliation!F:F,"Brought forward",Reconciliation!M:M,"Brought forward") -SUMIFS(Reconciliation!T:T,Reconciliation!D:D,A25,Reconciliation!F:F,"Brought forward",Reconciliation!I:I,"tds") -SUMIFS(Reconciliation!T:T,Reconciliation!D:D,A25,Reconciliation!M:M,"Brought forward",Reconciliation!P:P,"tds") -> 0 | D25: =COUNTIFS(Reconciliation!D:D,A25) -COUNTIFS(Reconciliation!D:D,A25,Reconciliation!F:F,"Brought forward",Reconciliation!M:M,"Brought forward") -COUNTIFS(Reconciliation!D:D,A25,Reconciliation!F:F,"Brought forward",Reconciliation!I:I,"tds") -COUNTIFS(Reconciliation!D:D,A25,Reconciliation!M:M,"Brought forward",Reconciliation!P:P,"tds") -> 0 | E25: Vendor to book the TDS entries
A26: TDS Booked by Party | B26: 94 | C26: =SUMIFS(Reconciliation!T:T,Reconciliation!D:D,A26) -SUMIFS(Reconciliation!T:T,Reconciliation!D:D,A26,Reconciliation!F:F,"Brought forward",Reconciliation!M:M,"Brought forward") -SUMIFS(Reconciliation!T:T,Reconciliation!D:D,A26,Reconciliation!F:F,"Brought forward",Reconciliation!I:I,"tds") -SUMIFS(Reconciliation!T:T,Reconciliation!D:D,A26,Reconciliation!M:M,"Brought forward",Reconciliation!P:P,"tds") -> 0 | D26: =COUNTIFS(Reconciliation!D:D,A26) -COUNTIFS(Reconciliation!D:D,A26,Reconciliation!F:F,"Brought forward",Reconciliation!M:M,"Brought forward") -COUNTIFS(Reconciliation!D:D,A26,Reconciliation!F:F,"Brought forward",Reconciliation!I:I,"tds") -COUNTIFS(Reconciliation!D:D,A26,Reconciliation!M:M,"Brought forward",Reconciliation!P:P,"tds") -> 0 | E26: Vendor to book the TDS entries
A27: Reversal Entries | C27: =SUM(C28:C28) -> 0 | D27: =SUM(D28:D28) -> 0
A28: Reversal Entries | C28: =SUMIFS(Reconciliation!L:L,Reconciliation!D:D,A28,Reconciliation!F:F,"ledger") +SUMIFS(Reconciliation!S:S,Reconciliation!D:D,A28,Reconciliation!M:M,"ledger") -> 0 | D28: =COUNTIFS(Reconciliation!D:D,A28,Reconciliation!F:F,"ledger") +COUNTIFS(Reconciliation!D:D,A28,Reconciliation!M:M,"ledger") -> 0 | E28: No Action Required
A29: Opening Balance Difference | C29: =SUM(C30:C33) -> 0 | D29: =SUM(D30:D33) -> 0
A30: Opening Balance as per Company | C30: =SUMIFS(Reconciliation!L:L,Reconciliation!D:D,A30,Reconciliation!F:F,"ledger") +SUMIFS(Reconciliation!S:S,Reconciliation!D:D,A30,Reconciliation!M:M,"ledger") -> 0 | D30: =COUNTIFS(Reconciliation!D:D,A30,Reconciliation!F:F,"ledger") +COUNTIFS(Reconciliation!D:D,A30,Reconciliation!M:M,"ledger") -> 0
A31: Opening Balance as per Party | C31: =SUMIFS(Reconciliation!L:L,Reconciliation!D:D,A31,Reconciliation!F:F,"ledger") +SUMIFS(Reconciliation!S:S,Reconciliation!D:D,A31,Reconciliation!M:M,"ledger") -> 0 | D31: =COUNTIFS(Reconciliation!D:D,A31,Reconciliation!F:F,"ledger") +COUNTIFS(Reconciliation!D:D,A31,Reconciliation!M:M,"ledger") -> 0 | E31: Vendor to provide the breakup of Opening Balance
A32: Brought forward entries matched - company | B32: 210 | C32: 0 | D32: 0
A33: Brought forward entries matched - party | B33: 211 | C33: 0 | D33: 0
A34: Calculated Balance | C34: =C13+C16+C18+C21+C24+C27+C29 -> 0
A36: Difference | C36: =C9-C34 -> 0

Sheet Reconciliation
A1: Company Id | B1: Party Id | C1: Matched Id | D1: Status | E1: Classification | F1: Company Statement Type | G1: Company Invoice Date | H1: Company Invoice Number | I1: Company DocType | J1: Company Original DocType | K1: Company Narration | L1: Company Amount | M1: Party Statement Type | N1: Party Invoice Date | O1: Party Invoice Number | P1: Party DocType | Q1: Party Original DocType | R1: Party Narration | S1: Party Amount | T1: Difference | U1: Matched Rule | V1: Reco Data & Time | W1: Remark | X1: Party Code | Y1: Daybook Name | Z1: Company Clearing Document Number | AA1: Company Clearing Date | AB1: Company TDS Amount | AC1: Company Posting Date | AD1: Company Code | AE1: Supplier | AF1: Document Number | AG1: Business Area | AH1: Assignment | AI1: Document Header Text | AJ1: Tax Code | AK1: Year/Month | AL1: Reference | AM1: Profit Center | AN1: Posting Date | AO1: Amount in Doc. Curr. | AP1: Document Currency | AQ1: Local Currency | AR1: Entry Date | AS1: Withhldg Tax Base Amount | AT1: Payment Date
A2: 60d2443b-0fb1-44e4-97fe-53fbdfc65b46 | B2: 4b10c103-35ae-417f-b854-efa1a8945391 | C2: 05185f70-d145-3675-9617-30ad2c62d476 | D2: Reconciled | E2: Amount Matched - Recommended | F2: ledger | G2: 21-08-2025 | H2: ANK2526/DBN00007 | I2: invoice | J2: MA | K2: MENOTROPIN IP (GUF) | L2: -817740 | M2: ledger | N2: 31-10-2025 | O2: ANK2526/DBN00007 | P2: creditNote | Q2: CN | S2: 817740 | T2: 0 | U2: SEC-CN1.1-party | V2: 19-Jun-26 10:16 AM | X2: AAACL0820G | Z2: 7053033057 | AB2: 0 | AD2: EPL | AE2: 5906 | AF2: 6000007609 | AG2: EP00 | AH2: ANK2526/DBN00007 | AI2: ANK2526/DBN00007 | AJ2: IA | AK2: 2025/05 | AL2: ELL2 | AM2: 2500 | AN2: 25-08-2025 | AO2: -817740 | AP2: INR | AQ2: INR | AR2: 25-08-2025 | AS2: -693000 | AT2: 21-08-2025
A3: e3064d9b-36d2-47c3-b614-7a93582dac31 | B3: 4bf4f1e8-4ea0-4ebd-a461-51858d4a1d59 | C3: 05f4488d-878f-3ab2-a045-a82fee6d3bcb | D3: TDS Booked by Party | E3: Date and Amount Matched - Recommended | F3: ledger | G3: 16-05-2025 | H3: 7053007500 | I3: payment | J3: KZ | L3: 1359585 | M3: ledger | N3: 16-05-2025 | O3: UTIBN62025051618331475 | P3: payment | Q3: Receipt | S3: -1360800 | T3: -1215 | U3: SEC-PAY3.1-company | V3: 19-Jun-26 10:16 AM | X3: AAACL0820G | Z3: 7053007500 | AB3: 0 | AD3: EPL | AE3: 5276 | AF3: 7053007500 | AG3: EP00 | AH3: 20250516-SJW10 | AI3: 20250516-SJW10 | AK3: 2025/02 | AM3: ENNOVA | AN3: 16-05-2025 | AO3: 1359585 | AP3: INR | AQ3: INR | AR3: 16-05-2025 | AS3: 1215000 | AT3: 16-05-2025
A4: 1db31cc9-1852-40e3-bee5-b9bac353c1f8 | B4: af5535ab-0511-49c1-9292-8a5e1ca4c2b7 | C4: 0ea3ba69-0b5b-3e90-be9d-f02df002b4d7 | D4: Reconciled | E4: Date and Amount Matched | F4: ledger | G4: 25-07-2025 | H4: 7053020673 | I4: payment | J4: KZ | L4: 3940384 | M4: ledger | N4: 25-07-2025 | O4: UTIBR72025072500076328 | P4: payment | Q4: Receipt | S4: -3940384 | T4: 0 | U4: PRI-PAY10.1-company | V4: 19-Jun-26 10:16 AM | X4: AAACL0820G | Z4: 7053020673 | AB4: 0 | AD4: EPL | AE4: 5906 | AF4: 7053020673 | AG4: EP00 | AH4: 20250725-SJH10 | AI4: 20250725-SJH10 | AK4: 2025/04 | AM4: XENNEA | AN4: 25-07-2025 | AO4: 3940384 | AP4: INR | AQ4: INR | AR4: 25-07-2025 | AS4: 3518200 | AT4: 25-07-2025
A5: 06b4cbc1-df7c-4dc2-a5e5-e3ed11468e91 | B5: 45a5cece-d771-4b25-a062-d0c539fffa26 | C5: 1395c5ae-873f-3f8b-ae53-ab71616636e5 | D5: TDS Booked by Party | E5: Multiple Based on Date | F5: ledger | G5: 08-10-2025 | H5: 7053032927 | I5: payment | J5: KZ | L5: 99742 | M5: ledger | N5: 08-10-2025 | O5: UTIBR72025100800060307 | P5: payment | Q5: Receipt | S5: -258892 | T5: 0 | U5: PRI-PAY5.2-company | V5: 19-Jun-26 10:16 AM | X5: AAACL0820G | Z5: 7053032927 | AB5: 0 | AD5: EPL | AE5: 5159 | AF5: 7053032927 | AG5: EP00 | AH5: 20251008-SJH10 | AI5: 20251008-SJH10 | AK5: 2025/07 | AM5: 2500 | AN5: 08-10-2025 | AO5: 99742 | AP5: INR | AQ5: INR | AR5: 08-10-2025 | AS5: 90675 | AT5: 08-10-2025
A6: 77c42784-11ca-4039-a04e-9fc050e211d9 | B6: c0ac7d01-7b9c-40c6-abca-c0fdf6d3a1c1 | C6: 1395c5ae-873f-3f8b-ae53-ab71616636e5 | D6: TDS Booked by Party | E6: Multiple Based on Date | F6: ledger | G6: 08-10-2025 | H6: 7053032930 | I6: payment | J6: KZ | L6: 257573.8 | M6: ledger | N6: 08-10-2025 | O6: AXISCN1112025593 | P6: payment | Q6: Receipt | S6: -101556 | T6: 0 | U6: PRI-PAY5.2-company | V6: 19-Jun-26 10:16 AM | X6: AAACL0820G | Z6: 7053032930 | AB6: 0 | AD6: EPL | AE6: 5276 | AF6: 7053032930 | AG6: EP00 | AH6: 20251008-SJH10 | AI6: 20251008-SJH10 | AK6: 2025/07 | AM6: 2500 | AN6: 08-10-2025 | AO6: 257573.8 | AP6: INR | AQ6: INR | AR6: 08-10-2025 | AS6: 222190 | AT6: 08-10-2025
A7: c9413937-a0a2-440e-afed-243116b6bb39 | B7: e052f7df-7a34-409c-820d-426b4b035581 | C7: 1395c5ae-873f-3f8b-ae53-ab71616636e5 | D7: TDS Booked by Party | E7: Multiple Based on Date | F7: ledger | G7: 08-10-2025 | H7: 7053033057 | I7: payment | J7: KZ | L7: 817740 | M7: ledger | N7: 08-10-2025 | O7: AXISCN1112157656 | P7: payment | Q7: Receipt | S7: -817740 | T7: -3132.2 | U7: PRI-PAY5.2-company | V7: 19-Jun-26 10:16 AM | X7: AAACL0820G | Z7: 7053033057 | AB7: 0 | AD7: EPL | AE7: 5906 | AF7: 7053033057 | AG7: EP00 | AH7: 20251008-MSESJ | AI7: 20251008-MSESJ | AK7: 2025/07 | AM7: 2500 | AN7: 08-10-2025 | AO7: 817740 | AP7: INR | AQ7: INR | AR7: 08-10-2025 | AS7: 693000 | AT7: 08-10-2025
A8: ee54b17a-3187-41c3-ad47-a9f5f3bb14a8 | B8: f1fc1d2c-fb00-477d-8a75-09008d81a667 | C8: 16fef953-aaae-3c19-8966-746b3c3f8cfe | D8: Reconciled | E8: Invoice Number Matched | F8: ledger | G8: 30-04-2025 | H8: ANK2526/GIS00091 | I8: invoice | J8: MF | K8: MATERNA DEPOT 3.75 MG INJ.[P2P]NSCH-ONCO | L8: -3940384 | M8: ledger | N8: 30-04-2025 | O8: ANK2526/GIS00091 | P8: invoice | Q8: Sale | S8: 3940384 | T8: 0 | U8: PRI-INV1.5_A-company | V8: 19-Jun-26 10:16 AM | X8: AAACL0820G | Z8: 7053020673 | AB8: 0 | AD8: EPL | AE8: 5906 | AF8: 6006000193 | AG8: EP00 | AH8: ANK2526/GIS00091 | AI8: ANK2526/GIS00091 | AJ8: I1 | AK8: 2025/02 | AL8: EMHC | AM8: XENNEA | AN8: 13-05-2025 | AO8: -3940384 | AP8: INR | AQ8: INR | AR8: 13-05-2025 | AS8: -3518200 | AT8: 12-05-2025
A9: 017f564b-f905-4d5a-9000-0baf92ea446c | B9: 9a50f4c0-c21a-4aad-960a-713d5c03e0b6 | C9: 1991f216-b6cf-4890-8202-8b48ceaa8400 | D9: TDS Booked by Party | E9: Payment Matched - Recommended | F9: ledger | G9: 24-09-2025 | H9: 7053030340 | I9: payment | J9: KZ | L9: 1024095.5 | M9: ledger | N9: 25-09-2025 | O9: AXISCN1096036481 | P9: payment | Q9: Receipt | S9: -1042715.5 | T9: -18620 | U9: SEC-PAY4.1-company | V9: 19-Jun-26 10:16 AM | X9: AAACL0820G | Z9: 7053030340 | AB9: 0 | AD9: EPL | AE9: 5159 | AF9: 7053030340 | AG9: EP00 | AH9: 20250924-MSMSJ | AI9: 20250924-MSMSJ | AK9: 2025/06 | AM9: 2500 | AN9: 24-09-2025 | AO9: 1024095.52 | AP9: INR | AQ9: INR | AR9: 24-09-2025 | AS9: 930996 | AT9: 24-09-2025
A10: 524bc8e0-a4a8-42e8-b23d-c1f23686de5a | B10: 186ecf5a-6b8f-46dc-affc-8da4ff6898d7 | C10: 23202ed6-9dcb-4c15-beab-145bc4a547de | D10: TDS Booked by Party | E10: Payment Matched - Recommended | F10: ledger | G10: 22-01-2026 | H10: 7053054141 | I10: payment | J10: KZ | L10: 413433 | M10: ledger | N10: 23-01-2026 | O10: UTIBR72026012300040395 | P10: payment | Q10: Receipt | S10: -413827 | T10: -394 | U10: SEC-PAY4.1-company | V10: 19-Jun-26 10:16 AM | X10: AAACL0820G | Z10: 7053054141 | AB10: 0 | AD10: EPL | AE10: 5276 | AF10: 7053054141 | AG10: EP00 | AH10: 20260122-SJW10 | AI10: 20260122-SJW10 | AK10: 2025/10 | AM10: ENNOVA | AN10: 22-01-2026 | AO10: 413433 | AP10: INR | AQ10: INR | AR10: 22-01-2026 | AS10: 394120.94 | AT10: 22-01-2026
A11: 4496d1c4-1e8a-4d2d-968c-d797ac14155c | B11: 03c26d9f-6c72-4e5f-bfec-675ae5dc3ecd | C11: 2399b5aa-899a-3e44-8e5f-4d09a538a2c3 | D11: TDS Booked by Company | E11: Invoice Number Matched | F11: ledger | G11: 21-04-2025 | H11: ANK2526/SER00001 | I11: invoice | J11: MI | K11: 421111714 MATERNA - HCG 5000 IU | L11: -1860607 | M11: ledger | N11: 21-04-2025 | O11: ANK2526/SER00001 | P11: invoice | Q11: Other | S11: 1894233.6 | T11: 33626.6 | U11: PRI-INV1.6-company | V11: 19-Jun-26 10:16 AM | X11: AAACL0820G | Z11: 7053012813 | AB11: -33626 | AD11: EPL | AE11: 5159 | AF11: 6008004363 | AG11: EP00 | AH11: ANK2526/SER00001 | AI11: ANK2526/SER00001 | AJ11: IA | AK11: 2025/02 | AL11: ELL2 | AM11: 2500 | AN11: 16-05-2025 | AO11: -1860607 | AP11: INR | AQ11: INR | AR11: 16-05-2025 | AS11: -1681280 | AT11: 21-05-2025
A12: 1bdafe07-41ec-47b3-baed-36acb746303a | B12: 3c3607e3-b64d-4e2d-8c7c-98b4f01adbac | C12: 252dae23-d549-3aa6-a82d-35d32098b55f | D12: TDS Booked by Company | E12: Invoice Number Matched | F12: ledger | G12: 29-01-2026 | H12: ANK2526/GIS00934 | I12: invoice | J12: MF | K12: REBEZ IV INJECTION [P TO P] | L12: -1370813 | M12: ledger | N12: 29-01-2026 | O12: ANK2526/GIS00934 | P12: invoice | Q12: Sale | S12: 1372120 | T12: 1307 | U12: PRI-INV1.6-company | V12: 19-Jun-26 10:16 AM | X12: AAACL0820G | Z12: 7053002431 | AB12: -1307 | AD12: EPL | AE12: 5276 | AF12: 6006002082 | AG12: EP00 | AH12: ANK2526/GIS00934 | AI12: ANK2526/GIS00934 | AJ12: I3 | AK12: 2025/11 | AL12: EMHC | AM12: ENNOVA | AN12: 02-02-2026 | AO12: -1370813 | AP12: INR | AQ12: INR | AR12: 02-02-2026 | AS12: -1306780.94 | AT12: 30-01-2026
A13: 823a6688-4523-4a8e-9948-a9933e848717 | B13: 8c1a1eab-34db-4f50-8dd1-f0029d456470 | C13: 272317a6-3e17-325e-9f62-8625bbbb07c3 | D13: TDS Booked by Party | E13: Multiple Based on Date | F13: ledger | G13: 21-01-2026 | H13: 7053053702 | I13: payment | J13: KZ | L13: 594152 | M13: ledger | N13: 21-01-2026 | O13: UTIBR72026012100004817 | P13: payment | Q13: Receipt | S13: -604396 | T13: 0 | U13: PRI-PAY5.2-company | V13: 19-Jun-26 10:16 AM | X13: AAACL0820G | Z13: 7053053702 | AB13: 0 | AD13: EPL | AE13: 5276 | AF13: 7053053702 | AG13: EP00 | AH13: 20260121-SJH10 | AI13: 20260121-SJH10 | AK13: 2025/10 | AM13: 2500 | AN13: 21-01-2026 | AO13: 594152 | AP13: INR | AQ13: INR | AR13: 21-01-2026 | AS13: 512200 | AT13: 21-01-2026
A14: af58096c-cbad-44b4-b5a8-a14cd3630f2b | B14: 95c1917c-7ae0-4de2-b5f4-d43cd30002ab | C14: 272317a6-3e17-325e-9f62-8625bbbb07c3 | D14: TDS Booked by Party | E14: Multiple Based on Date | F14: ledger | G14: 21-01-2026 | H14: 7053053708 | I14: payment | J14: KZ | L14: 3398760 | M14: ledger | N14: 21-01-2026 | O14: UTIBR72026012100004816 | P14: payment | Q14: Receipt | S14: -3402000 | T14: -13484 | U14: PRI-PAY5.2-company | V14: 19-Jun-26 10:16 AM | X14: AAACL0820G | Z14: 7053053708 | AB14: 0 | AD14: EPL | AE14: 5906 | AF14: 7053053708 | AG14: EP00 | AH14: 20260121-SJH10 | AI14: 20260121-SJH10 | AK14: 2025/10 | AM14: CRITI_CARE | AN14: 21-01-2026 | AO14: 3398760 | AP14: INR | AQ14: INR | AR14: 21-01-2026 | AS14: 3240000 | AT14: 21-01-2026
A15: 450bd921-1a8d-4845-b2ae-bf1216fd9198 | B15: 2eff2df9-aac2-4397-a9c7-638e6ac9253a | C15: 2a78bd4d-795a-39e0-b2e2-25d82ab37a71 | D15: TDS Booked by Company | E15: Invoice Number Matched | F15: ledger | G15: 16-03-2026 | H15: ANK2526/SER00080 | I15: invoice | J15: MI | K15: 421111716 MATERNA - HMG 75 IU | L15: -1372125 | M15: ledger | N15: 16-03-2026 | O15: ANK2526/SER00080 | P15: invoice | Q15: Other | S15: 1398768 | T15: 26643 | U15: PRI-INV1.6-company | V15: 19-Jun-26 10:16 AM | X15: AAACL0820G | AB15: -26643 | AD15: EPL | AE15: 5159 | AF15: 6008042702 | AG15: EP00 | AH15: ANK2526/SER00080 | AI15: ANK2526/SER00080 | AJ15: IG | AK15: 2025/12 | AL15: ELL2 | AM15: 2500 | AN15: 20-03-2026 | AO15: -1372125 | AP15: INR | AQ15: INR | AR15: 20-03-2026 | AS15: -1332160 | AT15: 02-04-2026
A16: bfacda10-298a-45fb-a0b8-561ea38f192b | B16: d7ed3f6c-6931-4855-85b0-e1359d7f45cc | C16: 2f904425-1935-38d4-b518-fd53aca1c625 | D16: TDS Booked by Company | E16: Invoice Number Matched | F16: ledger | G16: 26-06-2025 | H16: ANK2526/SER00025 | I16: invoice | J16: MI | K16: 420002214 PANPURE I.V. 20 MG DO | L16: -508860 | M16: ledger | N16: 26-06-2025 | O16: ANK2526/SER00025 | P16: invoice | Q16: Other | S16: 518112 | T16: 9252 | U16: PRI-INV1.6-company | V16: 19-Jun-26 10:16 AM | X16: AAACL0820G | Z16: 7053031634 | AB16: -9252 | AD16: EPL | AE16: 5159 | AF16: 6008010168 | AG16: EP00 | AH16: ANK2526/SER00025 | AI16: ANK2526/SER00025 | AJ16: IA | AK16: 2025/04 | AL16: ELL2 | AM16: 2500 | AN16: 01-07-2025 | AO16: -508860 | AP16: INR | AQ16: INR | AR16: 01-07-2025 | AS16: -462600 | AT16: 15-07-2025
A17: ffb7e322-b11e-418d-8624-0c78428ff4bc | B17: 5ce800c0-06e5-4125-a988-a782f27d2933 | C17: 30c02a2c-73e5-4135-843c-26b6c22ef8ec | D17: TDS Booked by Party | E17: Multiple Based on Invoice Number and Date Range | F17: ledger | G17: 26-05-2025 | H17: 7053009079 | I17: payment | J17: KZ | L17: 1812780 | M17: ledger | N17: 30-05-2025 | O17: AXISCN0983739554 | P17: payment | Q17: Receipt | S17: -1816778.9 | T17: 0 | U17: PRI-PAY13.1-company | V17: 19-Jun-26 10:16 AM | X17: AAACL0820G | Z17: 7053009079 | AB17: 0 | AD17: EPL | AE17: 5276 | AF17: 7053009079 | AG17: EP00 | AH17: 20250526-SJW01 | AI17: 20250526-SJW01 | AK17: 2025/02 | AM17: ENNOVA | AN17: 26-05-2025 | AO17: 1812780 | AP17: INR | AQ17: INR | AR17: 26-05-2025 | AS17: 1620000 | AT17: 26-05-2025
B18: c3e2afb1-e631-4f35-9c16-28866885aed8 | C18: 30c02a2c-73e5-4135-843c-26b6c22ef8ec | D18: TDS Booked by Party | E18: Multiple Based on Invoice Number and Date Range | F18: ledger | L18: 0 | M18: ledger | N18: 30-05-2025 | O18: AXISCN0983739555 | P18: payment | Q18: Receipt | S18: -624.96 | T18: -4623.84 | U18: PRI-PAY13.1-company | V18: 19-Jun-26 10:16 AM | X18: AAACL0820G | AB18: 0
A19: 19cf0320-a7d6-4632-93f9-3aa8ebabefda | B19: 356677a1-0763-4f5f-b67d-9fa67464a66e | C19: 33b8f008-c93f-3a19-a5a5-37851b94ef77 | D19: TDS Booked by Company | E19: Invoice Number Matched | F19: ledger | G19: 10-12-2025 | H19: ANK2526/GIS00839 | I19: invoice | J19: MF | K19: REBEZ IV INJECTION [P TO P] | L19: -1666450 | M19: ledger | N19: 10-12-2025 | O19: ANK2526/GIS00839 | P19: invoice | Q19: Sale | S19: 1668039 | T19: 1589 | U19: PRI-INV1.6-company | V19: 19-Jun-26 10:16 AM | X19: AAACL0820G | Z19: 7053058597 | AB19: -1589 | AD19: EPL | AE19: 5276 | AF19: 6006001732 | AG19: EP00 | AH19: ANK2526/GIS00839 | AI19: ANK2526/GIS00839 | AJ19: I3 | AK19: 2025/09 | AL19: EMHC | AM19: ENNOVA | AN19: 19-12-2025 | AO19: -1666450 | AP19: INR | AQ19: INR | AR19: 19-12-2025 | AS19: -1588608.56 | AT19: 11-12-2025
A20: e2c99a70-4d15-48ef-b920-e2e1303ed043 | B20: dfa78401-46da-4c19-8814-55f73efb5a9d | C20: 3a6a07f5-c8d0-3111-8209-202a899a258e | D20: TDS Booked by Party | E20: Date and Amount Matched - Recommended | F20: ledger | G20: 12-02-2026 | H20: 7053058597 | I20: payment | J20: KZ | L20: 1666450 | M20: ledger | N20: 12-02-2026 | O20: UTIBR72026021200092359 | P20: payment | Q20: Receipt | S20: -1668039 | T20: -1589 | U20: SEC-PAY3.1-company | V20: 19-Jun-26 10:16 AM | X20: AAACL0820G | Z20: 7053058597 | AB20: 0 | AD20: EPL | AE20: 5276 | AF20: 7053058597 | AG20: EP00 | AH20: 20260212-SJW10 | AI20: 20260212-SJW10 | AK20: 2025/11 | AM20: ENNOVA | AN20: 12-02-2026 | AO20: 1666450 | AP20: INR | AQ20: INR | AR20: 12-02-2026 | AS20: 1588608.56 | AT20: 12-02-2026
A21: 31bbc752-4579-4f0a-8c60-93d9f4763baa | B21: 81bba397-4096-40c8-b7e2-b7017396a2d5 | C21: 4121dcea-21e1-39ea-b2ae-617ac8d404e6 | D21: TDS Booked by Company | E21: Invoice Number Matched | F21: ledger | G21: 27-11-2025 | H21: ANK2526/GIS00786 | I21: invoice | J21: MF | K21: EMTIG INJECTION [P TO P] | L21: -1707537 | M21: ledger | N21: 27-11-2025 | O21: ANK2526/GIS00786 | P21: invoice | Q21: Sale | S21: 1709165 | T21: 1628 | U21: PRI-INV1.6-company | V21: 19-Jun-26 10:16 AM | X21: AAACL0820G | Z21: 7053053708 | AB21: -1628 | AD21: EPL | AE21: 5906 | AF21: 6006001720 | AG21: EP00 | AH21: ANK2526/GIS00786 | AI21: ANK2526/GIS00786 | AJ21: I3 | AK21: 2025/09 | AL21: EMHC | AM21: CRITI_CARE | AN21: 19-12-2025 | AO21: -1707537 | AP21: INR | AQ21: INR | AR21: 19-12-2025 | AS21: -1627776.2 | AT21: 06-12-2025
A22: 01b0bfca-76c7-41e4-b373-b8f58d7c5a86 | B22: 1e1bce79-95dd-4cc6-8b1b-ff4d93cc6372 | C22: 4d6f23b7-dd76-3d73-b15f-1e43a867c178 | D22: TDS Booked by Party | E22: Date and Amount Matched - Recommended | F22: ledger | G22: 17-04-2025 | H22: 7053002545 | I22: payment | J22: KZ | L22: 7298494 | M22: ledger | N22: 17-04-2025 | O22: UTIBR72025041700038257 | P22: payment | Q22: Receipt | S22: -7305016 | T22: -6522 | U22: SEC-PAY3.1-company | V22: 19-Jun-26 10:16 AM | X22: AAACL0820G | Z22: 7053002545 | AB22: 0 | AD22: EPL | AE22: 5906 | AF22: 7053002545 | AG22: EP00 | AH22: 20250417-SJH10 | AI22: 20250417-SJH10 | AK22: 2025/01 | AM22: CRITI_CARE | AN22: 17-04-2025 | AO22: 7298494 | AP22: INR | AQ22: INR | AR22: 17-04-2025 | AS22: 6522335.6799999997 | AT22: 17-04-2025
A23: 168a257c-6f08-46b6-9608-0725e376ecba | B23: 4cabb64d-c453-46f4-808e-9156760af86e | C23: 5a843abf-e9ca-324c-afd1-0dedba4227f0 | D23: TDS Booked by Company | E23: Invoice Number Matched | F23: ledger | G23: 26-11-2025 | H23: ANK2526/GIS00781 | I23: invoice | J23: MF | K23: REBEZ IV INJECTION [P TO P] | L23: -292718 | M23: ledger | N23: 26-11-2025 | O23: ANK2526/GIS00781 | P23: invoice | Q23: Sale | S23: 292997 | T23: 279 | U23: PRI-INV1.6-company | V23: 19-Jun-26 10:16 AM | X23: AAACL0820G | Z23: 7053054141 | AB23: -279 | AD23: EPL | AE23: 5276 | AF23: 6006001724 | AG23: EP00 | AH23: ANK2526/GIS00781 | AI23: ANK2526/GIS00781 | AJ23: I3 | AK23: 2025/09 | AL23: EMHC | AM23: ENNOVA | AN23: 19-12-2025 | AO23: -292718 | AP23: INR | AQ23: INR | AR23: 19-12-2025 | AS23: -279044.75 | AT23: 08-12-2025
A24: 7c3db2b5-709b-419a-9fee-1ff7747aea8a | B24: 6a61b6ee-0eba-480f-ba9a-db85633f5e91 | C24: 5c4816a8-ac14-3e72-9090-a3b72bad22e7 | D24: TDS Booked by Party | E24: Date and Amount Matched - Recommended | F24: ledger | G24: 01-10-2025 | H24: 7053031634 | I24: payment | J24: KZ | L24: 1070387 | M24: ledger | N24: 01-10-2025 | O24: AXISCN1103265077 | P24: payment | Q24: Receipt | S24: -1089849.6 | T24: -19462.6 | U24: SEC-PAY3.1-company | V24: 19-Jun-26 10:16 AM | X24: AAACL0820G | Z24: 7053031634 | AB24: 0 | AD24: EPL | AE24: 5159 | AF24: 7053031634 | AG24: EP00 | AH24: 20251001-SJH11 | AI24: 20251001-SJH11 | AK24: 2025/07 | AM24: 2500 | AN24: 01-10-2025 | AO24: 1070387 | AP24: INR | AQ24: INR | AR24: 01-10-2025 | AS24: 973080 | AT24: 01-10-2025
A25: 40a85208-dcf4-496e-bfaa-a1aa50d87efd | B25: 412b0cf1-2b9a-4f3d-b552-fb96018b8efd | C25: 5e3d74eb-1238-31a5-b9ea-68850a0ee4b8 | D25: TDS Booked by Company | E25: Invoice Number Matched | F25: ledger | G25: 21-08-2025 | H25: ANK2526/SER00049 | I25: invoice | J25: KR | K25: LYKA RATE DIFFERENCE | L25: -99742 | M25: ledger | N25: 21-08-2025 | O25: ANK2526/SER00049 | P25: invoice | Q25: Other | S25: 101556 | T25: 1814 | U25: PRI-INV1.6-company | V25: 19-Jun-26 10:16 AM | X25: AAACL0820G | Z25: 7053032927 | AB25: -1814 | AD25: EPL | AE25: 5159 | AF25: 7043041053 | AG25: EP00 | AH25: ANK2526/SER00049 | AJ25: IH | AK25: 2025/06 | AL25: 2025159442 | AM25: 2500 | AN25: 10-09-2025 | AO25: -99742 | AP25: INR | AQ25: INR | AR25: 10-09-2025 | AS25: -90675 | AT25: 25-09-2025
A26: d1150970-655c-4d2c-b033-cd90711105ce | B26: e95e28a5-d3f0-4f82-9ff8-0b8b5698664d | C26: 60345083-22dc-399c-9caf-fadd92d4175f | D26: TDS Booked by Party | E26: Date and Amount Matched - Recommended | F26: ledger | G26: 10-10-2025 | H26: 7053033678 | I26: payment | J26: KZ | L26: 2460902 | M26: ledger | N26: 10-10-2025 | O26: AXISCN1114230662 | P26: payment | Q26: Receipt | S26: -2505646.1 | T26: -44744.08 | U26: SEC-PAY3.1-company | V26: 19-Jun-26 10:16 AM | X26: AAACL0820G | Z26: 7053033678 | AB26: 0 | AD26: EPL | AE26: 5159 | AF26: 7053033678 | AG26: EP00 | AH26: 20251010-MSMSJ | AI26: 20251010-MSMSJ | AK26: 2025/07 | AM26: 2500 | AN26: 10-10-2025 | AO26: 2460902 | AP26: INR | AQ26: INR | AR26: 10-10-2025 | AS26: 2237184 | AT26: 10-10-2025
A27: 25c35bca-1693-4cb9-90b0-065e84c3251d | B27: e2f002de-023e-4431-af63-6f673f3fc3cb | C27: 61a89e37-90ac-4087-8224-63e799811c06 | D27: TDS Booked by Party | E27: Payment Matched - Recommended | F27: ledger | G27: 17-10-2025 | H27: 7053036126 | I27: payment | J27: KZ | L27: 3917289 | M27: ledger | N27: 18-10-2025 | O27: AXISCN1122982304 | P27: payment | Q27: Receipt | S27: -3920000 | T27: -2711 | U27: SEC-PAY4.1-company | V27: 19-Jun-26 10:16 AM | X27: AAACL0820G | Z27: 7053036126 | AB27: 0 | AD27: EPL | AE27: 5906 | AF27: 7053036126 | AG27: EP00 | AH27: 20251017-MSESJ | AI27: 20251017-MSESJ | AK27: 2025/07 | AM27: XENNEA | AN27: 17-10-2025 | AO27: 3917289 | AP27: INR | AQ27: INR | AR27: 17-10-2025 | AS27: 3500000 | AT27: 17-10-2025
A28: 5d4248ec-7a4e-4fcd-bcc9-3fa3cbd79825 | B28: 80f49ab0-4efa-4eda-b1aa-723f9a2e2702 | C28: 7515671b-9a76-3276-8caa-36e894b60403 | D28: TDS Booked by Company | E28: Invoice Number Matched | F28: ledger | G28: 30-11-2025 | H28: ANK2526/GIS00823 | I28: invoice | J28: MF | K28: REBEZ IV INJECTION [P TO P] | L28: -834164 | M28: ledger | N28: 30-11-2025 | O28: ANK2526/GIS00823 | P28: invoice | Q28: Sale | S28: 834959 | T28: 795 | U28: PRI-INV1.6-company | V28: 19-Jun-26 10:16 AM | X28: AAACL0820G | Z28: 7053055928 | AB28: -795 | AD28: EPL | AE28: 5276 | AF28: 6006001769 | AG28: EP00 | AH28: ANK2526/GIS00823 | AI28: ANK2526/GIS00823 | AJ28: I3 | AK28: 2025/09 | AL28: EMHC | AM28: ENNOVA | AN28: 22-12-2025 | AO28: -834164 | AP28: INR | AQ28: INR | AR28: 22-12-2025 | AS28: -795199.06 | AT28: 11-12-2025
A29: e88999b1-05ec-4268-bbbc-5119f6a8b867 | B29: 3df3999c-3eae-447e-86eb-ace45ffe1656 | C29: 7969e88d-93c3-3ac6-a71b-a5a023490392 | D29: TDS Booked by Company | E29: Invoice Number Matched | F29: ledger | G29: 31-10-2025 | H29: ANK2526/GIS00697 | I29: invoice | J29: MF | K29: EMTIG INJECTION [P TO P] | L29: -3480330 | M29: ledger | N29: 31-10-2025 | O29: ANK2526/GIS00697 | P29: invoice | Q29: Sale | S29: 3483648 | T29: 3318 | U29: PRI-INV1.6-company | V29: 19-Jun-26 10:16 AM | X29: AAACL0820G | Z29: 7053052271 | AB29: -3318 | AD29: EPL | AE29: 5906 | AF29: 6006001534 | AG29: EP00 | AH29: ANK2526/GIS00697 | AI29: ANK2526/GIS00697 | AJ29: I3 | AK29: 2025/08 | AL29: EMHC | AM29: CRITI_CARE | AN29: 19-11-2025 | AO29: -3480330 | AP29: INR | AQ29: INR | AR29: 19-11-2025 | AS29: -3317760 | AT29: 13-11-2025
A30: 74df1aa3-bc82-40e6-b13c-9ad2dd46ec10 | B30: d151a706-c557-4177-ace4-ad6f0c530f1d | C30: 7f4b4023-d438-3660-b28b-f92d110c9b33 | D30: TDS Booked by Company | E30: Invoice Number Matched | F30: ledger | G30: 19-07-2025 | H30: ANK2526/SER00034 | I30: invoice | J30: MI | K30: 421111715 MATERNA - HCG 10000 | L30: -561527 | M30: ledger | N30: 19-07-2025 | O30: ANK2526/SER00034 | P30: invoice | Q30: Other | S30: 571737.6 | T30: 10210.6 | U30: PRI-INV1.6-company | V30: 19-Jun-26 10:16 AM | X30: AAACL0820G | Z30: 7053031634 | AB30: -10210 | AD30: EPL | AE30: 5159 | AF30: 6008014035 | AG30: EP00 | AH30: ANK2526/SER00034 | AI30: ANK2526/SER00034 | AJ30: IA | AK30: 2025/04 | AL30: ELP3 | AM30: 2500 | AN30: 31-07-2025 | AO30: -561527 | AP30: INR | AQ30: INR | AR30: 31-07-2025 | AS30: -510480 | AT30: 13-08-2025
A31: feffc451-9eb3-4171-8faf-000859405a38 | B31: fad17af0-baf0-4352-a9e7-25d790de30fe | C31: 80ae845c-e9fa-33be-bd86-890140fe421e | D31: TDS Booked by Company | E31: Invoice Number Matched | F31: ledger | G31: 26-11-2025 | H31: ANK2526/GIS00782 | I31: invoice | J31: MF | K31: REBEZ IV INJECTION [P TO P] | L31: -120715 | M31: ledger | N31: 26-11-2025 | O31: ANK2526/GIS00782 | P31: invoice | Q31: Sale | S31: 120830 | T31: 115 | U31: PRI-INV1.6-company | V31: 19-Jun-26 10:16 AM | X31: AAACL0820G | Z31: 7053054141 | AB31: -115 | AD31: EPL | AE31: 5276 | AF31: 6006001725 | AG31: EP00 | AH31: ANK2526/GIS00782 | AI31: ANK2526/GIS00782 | AJ31: I3 | AK31: 2025/09 | AL31: EMHC | AM31: ENNOVA | AN31: 19-12-2025 | AO31: -120715 | AP31: INR | AQ31: INR | AR31: 19-12-2025 | AS31: -115076.19 | AT31: 08-12-2025
A32: bc391e80-a6e0-453d-a423-c7da6adc84f0 | B32: c81bf6c0-b64d-488b-bee6-59e4ad1faaec | C32: 9286c9af-9bb2-3567-b2b7-fdf0c45b4115 | D32: TDS Booked by Party | E32: Multiple Based on Invoice Number | F32: ledger | G32: 14-01-2026 | H32: 7053052271 | I32: payment | J32: KZ | L32: 3480330 | M32: ledger | N32: 14-01-2026 | O32: UTIBR72026011400000543 | P32: payment | Q32: Receipt | S32: -232460 | T32: 0 | U32: PRI-PAY5.1-company | V32: 19-Jun-26 10:16 AM | X32: AAACL0820G | Z32: 7053052271 | AB32: 0 | AD32: EPL | AE32: 5906 | AF32: 7053052271 | AG32: EP00 | AH32: 20260114-SJH01 | AI32: 20260114-SJH01 | AK32: 2025/10 | AM32: CRITI_CARE | AN32: 14-01-2026 | AO32: 3480330 | AP32: INR | AQ32: INR | AR32: 14-01-2026 | AS32: 3317760 | AT32: 14-01-2026
B33: f1bfb71a-578f-499f-b334-3d225c80979b | C33: 9286c9af-9bb2-3567-b2b7-fdf0c45b4115 | D33: TDS Booked by Party | E33: Multiple Based on Invoice Number | F33: ledger | L33: 0 | M33: ledger | N33: 14-01-2026 | O33: UTIBR72026011400000544 | P33: payment | Q33: Receipt | S33: -3483648 | T33: -235778 | U33: PRI-PAY5.1-company | V33: 19-Jun-26 10:16 AM | X33: AAACL0820G | AB33: 0
A34: 70d5264b-d33f-4983-93dd-ef6ff1535b45 | B34: 363f9169-6096-452e-9b08-14f89e80ab75 | C34: 96ca066f-f3dd-31d1-8565-a73b4c76be09 | D34: TDS Booked by Company | E34: Invoice Number Matched | F34: ledger | G34: 02-08-2025 | H34: ANK2526/SER00045 | I34: invoice | J34: MI | K34: Job Work Charge - AUG 2025 | L34: -1227.92 | M34: ledger | N34: 02-08-2025 | O34: ANK2526/SER00045 | P34: invoice | Q34: Other | S34: 1249.92 | T34: 22 | U34: PRI-INV1.6-company | V34: 19-Jun-26 10:16 AM | X34: AAACL0820G | Z34: 7053032930 | AB34: -22 | AD34: EPL | AE34: 5276 | AF34: 6008018400 | AG34: EP00 | AH34: ANK2526/SER00045 | AI34: ANK2526/SER00045 | AJ34: IA | AK34: 2025/06 | AL34: EGUA | AM34: 2500 | AN34: 18-09-2025 | AO34: -1227.92 | AP34: INR | AQ34: INR | AR34: 18-09-2025 | AS34: -1116 | AT34: 29-08-2025
A35: 72d032ec-9e10-4e0c-9d88-adf0df871a90 | B35: f3934940-c201-4051-9bf2-3ce66b5a27b5 | C35: 9b7b3f14-1268-37bd-8f97-a800357d4974 | D35: TDS Booked by Party | E35: Date and Amount Matched - Recommended | F35: ledger | G35: 30-01-2026 | H35: 7053055928 | I35: payment | J35: KZ | L35: 834164 | M35: ledger | N35: 30-01-2026 | O35: AXISCN1235469725 | P35: payment | Q35: Receipt | S35: -834959 | T35: -795 | U35: SEC-PAY3.1-company | V35: 19-Jun-26 10:16 AM | X35: AAACL0820G | Z35: 7053055928 | AB35: 0 | AD35: EPL | AE35: 5276 | AF35: 7053055928 | AG35: EP00 | AH35: 20260130-SJW10 | AI35: 20260130-SJW10 | AK35: 2025/10 | AM35: ENNOVA | AN35: 30-01-2026 | AO35: 834164 | AP35: INR | AQ35: INR | AR35: 30-01-2026 | AS35: 795199.06 | AT35: 30-01-2026
A36: 274e1989-5f2e-4316-bc94-97976325e7fc | B36: 00367562-24a4-4f8f-80ff-9f982a2591e7 | C36: aa3c61b5-9854-3fe2-9fd7-381cdb7a3021 | D36: TDS Booked by Company | E36: Invoice Number Matched | F36: ledger | G36: 27-11-2025 | H36: ANK2526/GIS00787 | I36: invoice | J36: MF | K36: EMTIG INJECTION [P TO P] | L36: -1691223 | M36: ledger | N36: 27-11-2025 | O36: ANK2526/GIS00787 | P36: invoice | Q36: Sale | S36: 1692835 | T36: 1612 | U36: PRI-INV1.6-company | V36: 19-Jun-26 10:16 AM | X36: AAACL0820G | Z36: 7053053708 | AB36: -1612 | AD36: EPL | AE36: 5906 | AF36: 6006001721 | AG36: EP00 | AH36: ANK2526/GIS00787 | AI36: ANK2526/GIS00787 | AJ36: I3 | AK36: 2025/09 | AL36: EMHC | AM36: CRITI_CARE | AN36: 19-12-2025 | AO36: -1691223 | AP36: INR | AQ36: INR | AR36: 19-12-2025 | AS36: -1612223.8 | AT36: 06-12-2025
A37: 5f10247c-e587-427f-949f-e2e1ffaa410d | B37: 50e3b35b-9047-4be7-af36-0db993f961e8 | C37: c11d5c55-e4a0-3b4f-8aaa-7a1cd55e7744 | D37: TDS Booked by Company | E37: Invoice Number Matched | F37: ledger | G37: 31-07-2025 | H37: ANK2526/SER00044 | I37: invoice | J37: MI | K37: 420005883 SOPRAPEN I.V. 20 MG G | L37: -86526.2 | M37: ledger | N37: 31-07-2025 | O37: ANK2526/SER00044 | P37: invoice | Q37: Other | S37: 88099.2 | T37: 1573 | U37: PRI-INV1.6-company | V37: 19-Jun-26 10:16 AM | X37: AAACL0820G | Z37: 7053030340 | AB37: -1573 | AD37: EPL | AE37: 5159 | AF37: 6008016111 | AG37: EP00 | AH37: ANK2526/SER00044 | AI37: ANK2526/SER00044 | AJ37: IA | AK37: 2025/05 | AL37: ELL2 | AM37: 2500 | AN37: 18-08-2025 | AO37: -86526.2 | AP37: INR | AQ37: INR | AR37: 18-08-2025 | AS37: -78660 | AT37: 26-08-2025
A38: 215b6c63-0821-4a1d-9607-b462e3341c7b | B38: d1d4383f-e165-4af5-886e-e48c124cc044 | C38: c873a8dd-4fbf-3f48-98a8-4474546891b4 | D38: TDS Booked by Company | E38: Invoice Number Matched | F38: ledger | G38: 31-08-2025 | H38: ANK2526/GIS00545 | I38: invoice | J38: MF | K38: MATERNA DEPOT 3.75 MG INJ.[P2P]NSCH-ONCO | L38: -3917289 | M38: ledger | N38: 31-08-2025 | O38: ANK2526/GIS00545 | P38: invoice | Q38: Sale | S38: 3920000 | T38: 2711 | U38: PRI-INV1.6-company | V38: 19-Jun-26 10:16 AM | X38: AAACL0820G | Z38: 7053036126 | AB38: -2711 | AD38: EPL | AE38: 5906 | AF38: 6006001091 | AG38: EP00 | AH38: ANK2526/GIS00545 | AI38: ANK2526/GIS00545 | AJ38: I1 | AK38: 2025/06 | AL38: EMHC | AM38: XENNEA | AN38: 08-09-2025 | AO38: -3917289 | AP38: INR | AQ38: INR | AR38: 08-09-2025 | AS38: -3500000 | AT38: 05-09-2025
A39: 16064676-ddc3-4045-a068-cd796accf406 | B39: 6483bfe6-60a2-48ca-a5d3-f39bda2b6cfb | C39: c8f17e1c-3a7a-39ec-8269-5746cfc5a4f8 | D39: TDS Booked by Party | E39: Date and Amount Matched - Recommended | F39: ledger | G39: 17-06-2025 | H39: 7053012813 | I39: payment | J39: KZ | L39: 1860607 | M39: ledger | N39: 17-06-2025 | O39: AXISCN0994733294 | P39: payment | Q39: Receipt | S39: -1894233.6 | T39: -33626.6 | U39: SEC-PAY3.1-company | V39: 19-Jun-26 10:16 AM | X39: AAACL0820G | Z39: 7053012813 | AB39: 0 | AD39: EPL | AE39: 5159 | AF39: 7053012813 | AG39: EP00 | AH39: 20250617-SJH10 | AI39: 20250617-SJH10 | AK39: 2025/03 | AM39: 2500 | AN39: 17-06-2025 | AO39: 1860607 | AP39: INR | AQ39: INR | AR39: 17-06-2025 | AS39: 1681280 | AT39: 17-06-2025
A40: ee2df619-aa96-4c09-9f21-aa502ad154b7 | B40: ee94a38b-95f5-497b-9848-3949e3dc4007 | C40: cc26e4c9-ecf9-33ca-a270-2d0bb50578bc | D40: TDS Booked by Company | E40: Invoice Number Matched | F40: ledger | G40: 21-08-2025 | H40: ANK2526/SER00050 | I40: invoice | J40: MI | K40: 421111714 MATERNA - HCG 5000 IU | L40: -2460902 | M40: ledger | N40: 21-08-2025 | O40: ANK2526/SER00050 | P40: invoice | Q40: Other | S40: 2505646.1 | T40: 44744.08 | U40: PRI-INV1.6-company | V40: 19-Jun-26 10:16 AM | X40: AAACL0820G | Z40: 7053033678 | AB40: -44744 | AD40: EPL | AE40: 5159 | AF40: 6008017857 | AG40: EP00 | AH40: ANK2526/SER00050 | AI40: ANK2526/SER00050 | AJ40: IA | AK40: 2025/06 | AL40: ELL2 | AM40: 2500 | AN40: 01-09-2025 | AO40: -2460902 | AP40: INR | AQ40: INR | AR40: 01-09-2025 | AS40: -2237184 | AT40: 13-09-2025
A41: eb499910-3892-42be-97e6-0ca5eb6ab8ee | B41: 51022052-eebc-4fbc-a428-096361b8a8c3 | C41: d770e8f0-576e-355f-b490-2555388f5d28 | D41: TDS Booked by Party | E41: Date and Amount Matched - Recommended | F41: ledger | G41: 06-11-2025 | H41: 7053038636 | I41: payment | J41: KZ | L41: 1555560 | M41: ledger | N41: 06-11-2025 | O41: UTIBR72025110600053262 | P41: payment | Q41: Receipt | S41: -1582380 | T41: -26820 | U41: SEC-PAY3.1-company | V41: 19-Jun-26 10:16 AM | X41: AAACL0820G | Z41: 7053038636 | AB41: 0 | AD41: EPL | AE41: 5276 | AF41: 7053038636 | AG41: EP00 | AH41: 20251106-SJH11 | AI41: 20251106-SJH11 | AK41: 2025/08 | AM41: 2500 | AN41: 06-11-2025 | AO41: 1555560 | AP41: INR | AQ41: INR | AR41: 06-11-2025 | AS41: 1341000 | AT41: 06-11-2025
A42: 626097b2-3743-4a8b-96db-a3f8c3a8fabf | B42: 90df11c7-89a9-4ada-bf91-5bcbc9c0d2c8 | C42: d844a4c4-df8d-3fb4-a542-9b3262225213 | D42: TDS Booked by Company | E42: Invoice Number Matched | F42: ledger | G42: 22-01-2026 | H42: ANK2526/GIS00923 | I42: invoice | J42: MF | K42: EMTIG INJECTION [P TO P] | L42: -3422325 | M42: ledger | N42: 22-01-2026 | O42: ANK2526/GIS00923 | P42: invoice | Q42: Sale | S42: 3425587 | T42: 3262 | U42: PRI-INV1.6-company | V42: 19-Jun-26 10:16 AM | X42: AAACL0820G | Z42: 7053001173 | AB42: -3262 | AD42: EPL | AE42: 5906 | AF42: 6006002054 | AG42: EP00 | AH42: ANK2526/GIS00923 | AI42: ANK2526/GIS00923 | AJ42: I3 | AK42: 2025/10 | AL42: EMHC | AM42: CRITI_CARE | AN42: 29-01-2026 | AO42: -3422325 | AP42: INR | AQ42: INR | AR42: 29-01-2026 | AS42: -3262463.8 | AT42: 28-01-2026
A43: b2e347ad-12a7-49e8-b77b-8588201eb191 | B43: f8ecbfc7-0224-4122-8ad2-06231f412d43 | C43: e2732d49-1980-36ce-9173-91c7827c949c | D43: TDS Booked by Party | E43: Date and Amount Matched - Recommended | F43: ledger | G43: 21-05-2025 | H43: 7053008353 | I43: payment | J43: KZ | L43: 1066852 | M43: ledger | N43: 21-05-2025 | O43: AXISCN0979676342 | P43: payment | Q43: Receipt | S43: -1085246 | T43: -18394 | U43: SEC-PAY3.1-company | V43: 19-Jun-26 10:16 AM | X43: AAACL0820G | Z43: 7053008353 | AB43: 0 | AD43: EPL | AE43: 5276 | AF43: 7053008353 | AG43: EP00 | AH43: 20250521-SJH01 | AI43: 20250521-SJH01 | AK43: 2025/02 | AM43: 2500 | AN43: 21-05-2025 | AO43: 1066852 | AP43: INR | AQ43: INR | AR43: 21-05-2025 | AS43: 919700 | AT43: 21-05-2025
A44: a0968703-cc23-44af-b031-f718ce9e84ce | B44: 4b5709cd-1408-4b7e-8e81-53c786fe9b81 | C44: e817c417-e8ce-344a-9cf1-b855d2c82a41 | D44: TDS Booked by Party | E44: Date and Amount Matched - Recommended | F44: ledger | G44: 01-07-2025 | H44: 7053015183 | I44: payment | J44: KZ | L44: 14267.66 | M44: ledger | N44: 01-07-2025 | O44: AXISCN1007743339 | P44: payment | Q44: Receipt | S44: -14514 | T44: -246.34 | U44: SEC-PAY3.1-company | V44: 19-Jun-26 10:16 AM | X44: AAACL0820G | Z44: 7053015183 | AB44: 0 | AD44: EPL | AE44: 5276 | AF44: 7053015183 | AG44: EP00 | AH44: 20250701-SJH12 | AI44: 20250701-SJH12 | AK44: 2025/04 | AM44: 2500 | AN44: 01-07-2025 | AO44: 14267.66 | AP44: INR | AQ44: INR | AR44: 01-07-2025 | AS44: 12299.72 | AT44: 01-07-2025
A45: 2543a07b-06f5-4707-8f6b-ea16f5988c18 | B45: 8578df19-94dc-4a2a-bedc-d18320afb9d5 | C45: ebc65537-cc7d-3651-8d18-ac57f49ee624 | D45: TDS Booked by Company | E45: Invoice Number Matched | F45: ledger | G45: 31-07-2025 | H45: ANK2526/SER00043 | I45: invoice | J45: MI | K45: 421111717 MATERNA - HMG 150 IU | L45: -937569.32 | M45: ledger | N45: 31-07-2025 | O45: ANK2526/SER00043 | P45: invoice | Q45: Other | S45: 954616.32 | T45: 17047 | U45: PRI-INV1.6-company | V45: 19-Jun-26 10:16 AM | X45: AAACL0820G | Z45: 7053030340 | AB45: -17047 | AD45: EPL | AE45: 5159 | AF45: 6008016110 | AG45: EP00 | AH45: ANK2526/SER00043 | AI45: ANK2526/SER00043 | AJ45: IA | AK45: 2025/05 | AL45: ELL2 | AM45: 2500 | AN45: 18-08-2025 | AO45: -937569.32 | AP45: INR | AQ45: INR | AR45: 18-08-2025 | AS45: -852336 | AT45: 26-08-2025
A46: 3bc802fe-64c7-4942-bdfb-ab0ec16fcfda | B46: 9782919a-be50-4cfb-864f-ab41855d5646 | C46: ee43bf8d-99e2-31e1-ad3a-20c1cb03a504 | D46: TDS Booked by Company | E46: Invoice Number Matched | F46: ledger | G46: 23-01-2026 | H46: ANK2526/GIS00926 | I46: invoice | J46: MF | K46: REBEZ IV INJECTION [P TO P] | L46: -1612661 | M46: ledger | N46: 23-01-2026 | O46: ANK2526/GIS00926 | P46: invoice | Q46: Sale | S46: 1614198 | T46: 1537 | U46: PRI-INV1.6-company | V46: 19-Jun-26 10:16 AM | X46: AAACL0820G | Z46: 7053002431 | AB46: -1537 | AD46: EPL | AE46: 5276 | AF46: 6006002034 | AG46: EP00 | AH46: ANK2526/GIS00926 | AI46: ANK2526/GIS00926 | AJ46: I3 | AK46: 2025/10 | AL46: EMHC | AM46: ENNOVA | AN46: 28-01-2026 | AO46: -1612661 | AP46: INR | AQ46: INR | AR46: 28-01-2026 | AS46: -1537331.43 | AT46: 27-01-2026
A47: 0f9f61f7-2b34-4dfe-aee8-d2dc688d3fa6 | B47: 83d8b82f-3094-49cf-9377-fc9d3deeb24d | C47: f7bbdf7e-4187-3925-a070-e1e08ff0b17d | D47: TDS Booked by Company | E47: Invoice Number Matched | F47: ledger | G47: 03-07-2025 | H47: ANK2526/SER00028 | I47: invoice | J47: MI | K47: Job Work Charge - JULY 2025 | L47: -1841.88 | M47: ledger | N47: 03-07-2025 | O47: ANK2526/SER00028 | P47: invoice | Q47: Other | S47: 1874.88 | T47: 33 | U47: PRI-INV1.6-company | V47: 19-Jun-26 10:16 AM | X47: AAACL0820G | Z47: 7053032930 | AB47: -33 | AD47: EPL | AE47: 5276 | AF47: 6008018350 | AG47: EP00 | AH47: ANK2526/SER00028 | AI47: ANK2526/SER00028 | AJ47: IA | AK47: 2025/06 | AL47: EGUA | AM47: 2500 | AN47: 18-09-2025 | AO47: -1841.88 | AP47: INR | AQ47: INR | AR47: 18-09-2025 | AS47: -1674 | AT47: 02-09-2025
A48: 073c24a8-8d2a-4cc7-b7f7-698dd4cb4b5a | D48: Invoice not booked by Party | E48: Unmatched | F48: ledger | G48: 27-11-2025 | H48: ANK2526/DBN00008 | I48: invoice | J48: MI | K48: Testing & analytical charges | L48: -594152 | S48: 0 | T48: -594152 | U48: Post-C-3.1-company | V48: 19-Jun-26 10:16 AM | X48: AAACL0820G | Z48: 7053053702 | AB48: -10244 | AD48: EPL | AE48: 5276 | AF48: 6008034648 | AG48: EP00 | AH48: ANK2526/DBN00008 | AI48: ANK2526/DBN00008 | AJ48: II | AK48: 2025/10 | AL48: EGUA | AM48: 2500 | AN48: 19-01-2026 | AO48: -594152 | AP48: INR | AQ48: INR | AR48: 19-01-2026 | AS48: -512200 | AT48: 14-01-2026
A49: 262de2aa-e944-480c-b1fc-b95c5ac2a185 | D49: Opening Balance as per Company | E49: Opening Balance | F49: ledger | G49: 01-04-2025 | I49: openingBalance | J49: Op | L49: -14608899 | S49: 0 | T49: -14608899 | V49: 19-Jun-26 10:16 AM | X49: AAACL0820G | AB49: 0 | AN49: 01-04-2025 | AO49: -14608898.92
A50: 39dbb1dc-74fc-4a82-81c0-d022eb6cf108 | D50: Payment not booked by Party | E50: Unmatched | F50: ledger | G50: 08-04-2025 | H50: 7053001046 | I50: payment | J50: KZ | L50: 730800 | S50: 0 | T50: 730800 | U50: Post-C-3.2-company | V50: 19-Jun-26 10:16 AM | X50: AAACL0820G | Z50: 7053001046 | AB50: 0 | AD50: EPL | AE50: 5276 | AF50: 7053001046 | AG50: EP00 | AH50: 20250408-SJH12 | AI50: 20250408-SJH12 | AK50: 2025/01 | AM50: 2500 | AN50: 08-04-2025 | AO50: 730800 | AP50: INR | AQ50: INR | AR50: 08-04-2025 | AS50: 630000 | AT50: 08-04-2025
A51: 3a213d6f-712e-42f0-b8e3-4afe16d6c1df | D51: Closing Balance as per Company | E51: Closing Balance | F51: ledger | G51: 31-03-2026 | I51: closingBalance | J51: CL | L51: 8712726 | S51: 0 | T51: 8712726 | V51: 19-Jun-26 10:16 AM | X51: AAACL0820G | AB51: 0 | AN51: 31-03-2026 | AO51: 8712725.9999999981
A52: 3da2bcee-2cbd-4a91-8f1f-7fd7fbf27f05 | D52: Payment not booked by Party | E52: Unmatched | F52: ledger | G52: 31-03-2026 | H52: 7053068167 | I52: payment | J52: KZ | L52: 473280 | S52: 0 | T52: 473280 | U52: Post-C-3.2-company | V52: 19-Jun-26 10:16 AM | X52: AAACL0820G | Z52: 7053068167 | AB52: 0 | AD52: EPL | AE52: 5276 | AF52: 7053068167 | AG52: EP00 | AH52: 20260331-SJH10 | AI52: 20260331-SJH10 | AK52: 2025/12 | AM52: 2500 | AN52: 31-03-2026 | AO52: 473280 | AP52: INR | AQ52: INR | AR52: 31-03-2026 | AS52: 408000 | AT52: 31-03-2026
A53: 484c0899-5552-42fe-a29f-e62c7cb48391 | D53: Payment not booked by Party | E53: Unmatched | F53: ledger | G53: 29-05-2025 | H53: 7053009823 | I53: payment | J53: KZ | L53: 613.96 | S53: 0 | T53: 613.96 | U53: Post-C-3.2-company | V53: 19-Jun-26 10:16 AM | X53: AAACL0820G | Z53: 7053009823 | AB53: 0 | AD53: EPL | AE53: 5276 | AF53: 7053009823 | AG53: EP00 | AH53: 20250529-SJH02 | AI53: 20250529-SJH02 | AK53: 2025/02 | AM53: 2500 | AN53: 29-05-2025 | AO53: 613.96 | AP53: INR | AQ53: INR | AR53: 29-05-2025 | AS53: 558 | AT53: 29-05-2025
A54: 5fb50060-14bd-48e8-9301-272140c55ab4 | D54: Invoice not booked by Party | E54: Unmatched | F54: ledger | G54: 31-07-2025 | H54: ANK2526/DBN00005 | I54: invoice | J54: MI | K54: Testing Charges for EGUA | L54: -254504 | S54: 0 | T54: -254504 | U54: Post-C-3.1-company | V54: 19-Jun-26 10:16 AM | X54: AAACL0820G | Z54: 7053032930 | AB54: -4388 | AD54: EPL | AE54: 5276 | AF54: 6008018394 | AG54: EP00 | AH54: ANK2526/DBN00005 | AI54: ANK2526/DBN00005 | AJ54: IA | AK54: 2025/06 | AL54: EGUA | AM54: 2500 | AN54: 11-09-2025 | AO54: -254504 | AP54: INR | AQ54: INR | AR54: 11-09-2025 | AS54: -219400 | AT54: 29-08-2025
A55: 66848aa3-8721-45f9-8f07-7fcdafb4f510 | D55: Other entry not booked by Party | E55: Unmatched | F55: ledger | G55: 31-03-2026 | I55: journal | J55: SA | K55: Testing & Analytical | L55: -179242 | S55: 0 | T55: -179242 | U55: Post-C-3.5-company | V55: 19-Jun-26 10:16 AM | X55: AAACL0820G | Z55: 7001002085 | AB55: -3658 | AD55: EPL | AE55: 5276 | AF55: 7078317821 | AG55: EP00 | AH55: 2526/DBN00009-PROV | AI55: ANK2526/DBN00009 | AJ55: V0 | AK55: 2025/12 | AL55: MARCH PROV-26 | AN55: 31-03-2026 | AO55: -179242 | AP55: INR | AQ55: INR | AR55: 11-04-2026 | AS55: -182900 | AT55: 15-05-2026
A56: 74d9080b-e369-46b4-9ccb-72f40b32f1a5 | D56: Payment not booked by Party | E56: Unmatched | F56: ledger | G56: 12-05-2025 | H56: 7053006480 | I56: payment | J56: KZ | L56: 898127 | S56: 0 | T56: 898127 | U56: Post-C-3.2-company | V56: 19-Jun-26 10:16 AM | X56: AAACL0820G | Z56: 7053006480 | AB56: 0 | AD56: EPL | AE56: 5159 | AF56: 7053006480 | AG56: EP00 | AH56: 20250512-SJH10 | AI56: 20250512-SJH10 | AK56: 2025/02 | AM56: 2500 | AN56: 12-05-2025 | AO56: 898127 | AP56: INR | AQ56: INR | AR56: 12-05-2025 | AS56: 816480 | AT56: 12-05-2025
A57: 804cc679-de19-4f73-a584-49b62b5dd4db | D57: Opening Balance as per Company | E57: Opening Balance | F57: ledger | G57: 14-10-2024 | H57: ANK2425/SER00052 | I57: invoice | J57: MI | K57: 421111714 MATERNA - HCG 5000 IU | L57: -898127 | S57: 0 | T57: -898127 | U57: Pre-C-1.1 | V57: 19-Jun-26 10:16 AM | X57: AAACL0820G | Z57: 7053006480 | AB57: -16330 | AD57: EPL | AE57: 5159 | AF57: 6008002633 | AG57: EP00 | AH57: ANK2425/SER00052 | AI57: ANK2425/SER00052 | AJ57: IA | AK57: 2025/02 | AL57: ELL2 | AM57: 2500 | AN57: 02-05-2025 | AO57: -898127 | AP57: INR | AQ57: INR | AR57: 02-05-2025 | AS57: -816480 | AT57: 27-03-2025
A58: 8a49aa96-c2ab-4471-89a5-2a3188aa2216 | D58: Payment not booked by Party | E58: Unmatched | F58: ledger | G58: 29-05-2025 | H58: 7053009822 | I58: payment | J58: KZ | L58: 1784336 | S58: 0 | T58: 1784336 | U58: Post-C-3.2-company | V58: 19-Jun-26 10:16 AM | X58: AAACL0820G | Z58: 7053009822 | AB58: 0 | AD58: EPL | AE58: 5159 | AF58: 7053009822 | AG58: EP00 | AH58: 20250529-SJH02 | AI58: 20250529-SJH02 | AK58: 2025/02 | AM58: 2500 | AN58: 29-05-2025 | AO58: 1784335.96 | AP58: INR | AQ58: INR | AR58: 29-05-2025 | AS58: 1622124 | AT58: 29-05-2025
A59: a394fbd0-1313-4234-b850-d30ff082d74b | D59: Other entry not booked by Party | E59: Unmatched | F59: ledger | G59: 31-03-2026 | I59: journal | J59: SA | K59: Job work | L59: -520360 | S59: 0 | T59: -520360 | U59: Post-C-3.5-company | V59: 19-Jun-26 10:16 AM | X59: AAACL0820G | Z59: 7001008009 | AB59: -10620 | AD59: EPL | AE59: 5159 | AF59: 7078317936 | AG59: EP00 | AH59: ANK2526/SER00081-P | AI59: ANK2526/SER00081 | AJ59: V0 | AK59: 2025/12 | AL59: MARCH PROV-26 | AN59: 31-03-2026 | AO59: -520360 | AP59: INR | AQ59: INR | AR59: 11-04-2026 | AS59: -530980 | AT59: 15-05-2026
A60: b3110aad-4e00-47eb-98b4-53d6f61b7088 | D60: Invoice not booked by Party | E60: Unmatched | F60: ledger | G60: 06-10-2025 | H60: ANK2526/DBN00006 | I60: invoice | J60: MI | K60: Testing Charges | L60: -228520 | S60: 0 | T60: -228520 | U60: Post-C-3.1-company | V60: 19-Jun-26 10:16 AM | X60: AAACL0820G | Z60: 7053052258 | AB60: -3940 | AD60: EPL | AE60: 5276 | AF60: 6008025967 | AG60: EP00 | AH60: ANK2526/DBN00006 | AI60: ANK2526/DBN00006 | AJ60: II | AK60: 2025/08 | AL60: EGUA | AM60: 2500 | AN60: 18-11-2025 | AO60: -228520 | AP60: INR | AQ60: INR | AR60: 18-11-2025 | AS60: -197000 | AT60: 10-01-2026
A61: b7e4d0db-be08-40c0-acda-5ce824a8256a | D61: Opening Balance as per Company | E61: Opening Balance | F61: ledger | G61: 25-03-2025 | H61: ANK2425/DNB00008 | I61: invoice | J61: MI | K61: Testing Charges of ribsome reeaserch | L61: -366212 | S61: 0 | T61: -366212 | U61: Pre-C-1.1 | V61: 19-Jun-26 10:16 AM | X61: AAACL0820G | Z61: 7053008353 | AB61: -6314 | AD61: EPL | AE61: 5276 | AF61: 6008003129 | AG61: EP00 | AH61: ANK2425/DNB00008 | AI61: ANK2425/DNB00008 | AJ61: IA | AK61: 2025/02 | AL61: EGUA | AM61: 2500 | AN61: 13-05-2025 | AO61: -366212 | AP61: INR | AQ61: INR | AR61: 13-05-2025 | AS61: -315700 | AT61: 06-05-2025
A62: c259686b-8169-4e00-a872-b4fa7f08123f | D62: Invoice not booked by Party | E62: Unmatched | F62: ledger | G62: 30-04-2025 | H62: ANK2526/DNB00001 | I62: invoice | J62: MI | K62: Debit Note(Job work Charge) - 30.04.2025 | L62: -14267.66 | S62: 0 | T62: -14267.66 | U62: Post-C-3.1-company | V62: 19-Jun-26 10:16 AM | X62: AAACL0820G | Z62: 7053015183 | AB62: -246 | AD62: EPL | AE62: 5276 | AF62: 6008007146 | AG62: EP00 | AH62: ANK2526/DNB00001 | AI62: ANK2526/DNB00001 | AJ62: IA | AK62: 2025/03 | AL62: EGUA | AM62: 2500 | AN62: 11-06-2025 | AO62: -14267.66 | AP62: INR | AQ62: INR | AR62: 11-06-2025 | AS62: -12299.72 | AT62: 05-06-2025
A63: d33cdc7d-5f77-4869-8028-863e1c13fa15 | D63: Payment not booked by Party | E63: Unmatched | F63: ledger | G63: 14-01-2026 | H63: 7053052258 | I63: payment | J63: KZ | L63: 228520 | S63: 0 | T63: 228520 | U63: Post-C-3.2-company | V63: 19-Jun-26 10:16 AM | X63: AAACL0820G | Z63: 7053052258 | AB63: 0 | AD63: EPL | AE63: 5276 | AF63: 7053052258 | AG63: EP00 | AH63: 20260114-SJH01 | AI63: 20260114-SJH01 | AK63: 2025/10 | AM63: 2500 | AN63: 14-01-2026 | AO63: 228520 | AP63: INR | AQ63: INR | AR63: 14-01-2026 | AS63: 197000 | AT63: 14-01-2026
A64: da1f6ac3-73fd-4107-8171-cf14d6b7bbb0 | D64: Other entry not booked by Party | E64: Unmatched | F64: ledger | G64: 31-03-2026 | I64: journal | J64: SA | K64: Testing & Analytical | L64: -235200 | S64: 0 | T64: -235200 | U64: Post-C-3.5-company | V64: 19-Jun-26 10:16 AM | X64: AAACL0820G | Z64: 7001002096 | AB64: -4800 | AD64: EPL | AE64: 5276 | AF64: 7078317822 | AG64: EP00 | AH64: 2526/DBN00016-PROV | AI64: ANK2526/DBN00016 | AJ64: V0 | AK64: 2025/12 | AL64: MARCH PROV-26 | AN64: 31-03-2026 | AO64: -235200 | AP64: INR | AQ64: INR | AR64: 11-04-2026 | AS64: -240000 | AT64: 15-05-2026
A65: e14afd12-c455-4ae4-be8b-db0b357dbac4 | D65: Invoice not booked by Party | E65: Unmatched | F65: ledger | G65: 27-01-2026 | H65: ANK2526/DBN00012 | I65: invoice | J65: MI | K65: Testing and analytical Charges | L65: -473280 | S65: 0 | T65: -473280 | U65: Post-C-3.1-company | V65: 19-Jun-26 10:16 AM | X65: AAACL0820G | Z65: 7053068167 | AB65: -8160 | AD65: EPL | AE65: 5276 | AF65: 6008043123 | AG65: EP00 | AH65: ANK2526/DBN00012 | AI65: ANK2526/DBN00012 | AJ65: II | AK65: 2025/12 | AL65: EGUA | AM65: 2500 | AN65: 23-03-2026 | AO65: -473280 | AP65: INR | AQ65: INR | AR65: 23-03-2026 | AS65: -408000 | AT65: 16-03-2026
A66: e4d5a91a-46b4-4d2d-9502-565a9e772ded | D66: Invoice not booked by Party | E66: Unmatched | F66: ledger | G66: 10-07-2025 | H66: ANK2526/DNB00003 | I66: invoice | J66: MI | K66: Testing Charges July 25 | L66: -1555560 | S66: 0 | T66: -1555560 | U66: Post-C-3.1-company | V66: 19-Jun-26 10:16 AM | X66: AAACL0820G | Z66: 7053038636 | AB66: -26820 | AD66: EPL | AE66: 5276 | AF66: 6008024230 | AG66: EP00 | AH66: ANK2526/DNB00003 | AI66: ANK2526/DNB00003 | AJ66: II | AK66: 2025/07 | AL66: ANK2526/DNB00003 | AM66: 2500 | AN66: 27-10-2025 | AO66: -1555560 | AP66: INR | AQ66: INR | AR66: 28-10-2025 | AS66: -1341000 | AT66: 17-10-2025
A67: f34a070e-e679-4049-80b8-68848063d92e | D67: Payment not booked by Party | E67: Unmatched | F67: ledger | G67: 08-04-2025 | H67: 7053001045 | I67: payment | J67: KZ | L67: 921650 | S67: 0 | T67: 921650 | U67: Post-C-3.2-company | V67: 19-Jun-26 10:16 AM | X67: AAACL0820G | Z67: 7053001045 | AB67: 0 | AD67: EPL | AE67: 5159 | AF67: 7053001045 | AG67: EP00 | AH67: 20250408-SJH12 | AI67: 20250408-SJH12 | AK67: 2025/01 | AM67: 2500 | AN67: 08-04-2025 | AO67: 921650 | AP67: INR | AQ67: INR | AR67: 08-04-2025 | AS67: 837864 | AT67: 08-04-2025
B68: 0ca58a7f-65da-4e3e-a0ec-1d98d9e3a5f4 | D68: Credit Note not booked by Company | E68: Unmatched | L68: 0 | M68: ledger | N68: 14-03-2026 | O68: ANK2526/DBN00016 | P68: creditNote | Q68: CN | S68: 283200 | T68: 283200 | U68: Post-P-3.4-party | V68: 19-Jun-26 10:16 AM | AB68: 0
B69: 289ad3fb-1769-409a-909a-3cec95cef9d5 | D69: Credit Note not booked by Company | E69: Unmatched | L69: 0 | M69: ledger | N69: 10-07-2025 | O69: DNB00011 | P69: creditNote | Q69: CN | S69: 1582380 | T69: 1582380 | U69: Post-P-3.4-party | V69: 19-Jun-26 10:16 AM | AB69: 0
B70: 2b2ced9b-b480-4be7-a59a-1a5ae8f5bc89 | D70: Credit Note not booked by Company | E70: Unmatched | L70: 0 | M70: ledger | N70: 27-01-2026 | O70: ANK2526/DBN00012 | P70: creditNote | Q70: CN | S70: 481440 | T70: 481440 | U70: Post-P-3.4-party | V70: 19-Jun-26 10:16 AM | AB70: 0
B71: 51e03a91-560b-460b-b310-15e4b684e22e | D71: Credit Note not booked by Company | E71: Unmatched | L71: 0 | M71: ledger | N71: 31-07-2025 | O71: ANK2526/DBN00005 | P71: creditNote | Q71: CN | S71: 258892 | T71: 258892 | U71: Post-P-3.4-party | V71: 19-Jun-26 10:16 AM | AB71: 0
B72: 59fb819b-d76f-4aef-bd08-7e3dbf42f0c4 | D72: Invoice not booked by Company | E72: Unmatched | L72: 0 | M72: ledger | N72: 27-03-2026 | O72: ANK2526/SER00081 | P72: invoice | Q72: Other | S72: 557529 | T72: 557529 | U72: Post-P-3.1-party | V72: 19-Jun-26 10:16 AM | AB72: 0
B73: 5f77d353-a5e7-40cc-a460-0d1a90be31dc | D73: Credit Note not booked by Company | E73: Unmatched | L73: 0 | M73: ledger | N73: 27-11-2025 | O73: ANK2526/DBN00008 | P73: creditNote | Q73: CN | S73: 604396 | T73: 604396 | U73: Post-P-3.4-party | V73: 19-Jun-26 10:16 AM | AB73: 0
B74: 647bee11-a5ff-4a23-870f-f583d6cf62b8 | D74: Other entry not booked by Company | E74: Unmatched | L74: 0 | M74: ledger | N74: 30-09-2025 | O74: DEBTORS WRITE OFF | P74: journal | Q74: Journal | S74: 25440 | T74: 25440 | U74: Post-P-3.5-party | V74: 19-Jun-26 10:16 AM | AB74: 0
B75: 699bd5e5-b0b1-4afe-8de7-ca8f3322ccdd | D75: Payment not booked by Company | E75: Unmatched | L75: 0 | M75: ledger | N75: 27-05-2025 | O75: AXISCN0981979347 | P75: payment | Q75: Receipt | S75: -1814400 | T75: -1814400 | U75: Post-P-3.2-party | V75: 19-Jun-26 10:16 AM | AB75: 0
B76: 71edf8a4-9888-4518-bcac-ae43e5ea8193 | D76: Credit Note not booked by Company | E76: Unmatched | L76: 0 | M76: ledger | N76: 06-10-2025 | O76: ANK2526/DBN00006 | P76: creditNote | Q76: CN | S76: 232460 | T76: 232460 | U76: Post-P-3.4-party | V76: 19-Jun-26 10:16 AM | AB76: 0
B77: 7c6c5123-ba1b-483a-b795-ac9d11e632ab | D77: Payment not booked by Company | E77: Unmatched | L77: 0 | M77: ledger | N77: 13-05-2025 | O77: UTIBN62025051387607677 | P77: payment | Q77: Receipt | S77: -914457.6 | T77: -914457.6 | U77: Post-P-3.2-party | V77: 19-Jun-26 10:16 AM | AB77: 0
B78: 7fd61a63-5c6f-4418-8e12-d7b417b9492a | D78: Credit Note not booked by Company | E78: Unmatched | L78: 0 | M78: ledger | N78: 20-02-2026 | O78: ANK2526/DBN00015 | P78: creditNote | Q78: CN | S78: 388928 | T78: 388928 | U78: Post-P-3.4-party | V78: 19-Jun-26 10:16 AM | AB78: 0
B79: a9c1ac6e-0179-4c48-aa04-92b6534f0220 | D79: Payment not booked by Company | E79: Unmatched | L79: 0 | M79: ledger | N79: 11-04-2025 | O79: UTIBN62025041155260266 | P79: payment | Q79: Receipt | S79: -743400 | T79: -743400 | U79: Post-P-3.2-party | V79: 19-Jun-26 10:16 AM | AB79: 0
... B81: e13ee45f-1714-42a1-8a12-427f9993b620 | D81: Credit Note not booked by Company | E81: Unmatched | L81: 0 | M81: ledger | N81: 13-12-2025 | O81: ANK2526/DBN00009 | P81: creditNote | Q81: CN | S81: 215822 | T81: 215822 | U81: Post-P-3.4-party | V81: 19-Jun-26 10:16 AM | AB81: 0
B82: 06a587ff-f941-4454-b4a2-1ed0e8d7e52a | D82: Opening Balance as per Party | E82: Opening Balance | L82: 0 | M82: ledger | N82: 01-04-2025 | P82: openingBalance | Q82: OP | S82: 0 | T82: 0 | V82: 19-Jun-26 10:16 AM | AB82: 0
B83: 23129740-91f2-4a2a-98ec-c5c6334ba4c1 | D83: Opening Balance as per Party | E83: Opening Balance | L83: 0 | M83: ledger | N83: 01-04-2025 | P83: openingBalance | Q83: OP | S83: 0 | T83: 0 | V83: 19-Jun-26 10:16 AM | AB83: 0
B84: e1e53cff-685a-4cba-9676-0a1d0e3aa863 | D84: Closing Balance as per Party | E84: Closing Balance | L84: 0 | M84: ledger | P84: closingBalance | Q84: Closing | S84: 6242052.8 | T84: 6242052.8 | V84: 19-Jun-26 10:16 AM | AB84: 0
B85: 54c64096-ea61-4f44-9146-bd38fc6090d0 | C85: b995ec42-83e7-45de-88e3-bb8b492089fb | D85: TDS Booked by Party | E85: TDS Booked by Party | L85: 0 | M85: ledger | N85: 31-03-2026 | O85: TDS ANK2526/GIS00926 | P85: tds | Q85: TDS | S85: -1537 | T85: -1537 | U85: Pre-P-2.3-party | V85: 19-Jun-26 10:16 AM | AB85: 0
B86: 9870be35-0fc7-442d-866b-dec7a75ddd57 | C86: b995ec42-83e7-45de-88e3-bb8b492089fb | D86: TDS Booked by Party | E86: TDS Booked by Party | L86: 0 | M86: ledger | N86: 31-03-2026 | O86: TDS ANK2526/GIS00934 | P86: tds | Q86: TDS | S86: -1307 | T86: -1307 | U86: Pre-P-2.3-party | V86: 19-Jun-26 10:16 AM | AB86: 0
B87: b9dcae01-168d-49d8-a84f-53ecc4177168 | C87: b995ec42-83e7-45de-88e3-bb8b492089fb | D87: TDS Booked by Party | E87: TDS Booked by Party | L87: 0 | M87: ledger | N87: 31-03-2026 | O87: TDS ANK2526/GIS00923 | P87: tds | Q87: TDS | S87: -3262.46 | T87: -3262.46 | U87: Pre-P-2.3-party | V87: 19-Jun-26 10:16 AM | AB87: 0
B88: df1331d7-652e-411d-9518-195aafb24082 | C88: b995ec42-83e7-45de-88e3-bb8b492089fb | D88: TDS Booked by Party | E88: TDS Booked by Party | L88: 0 | M88: ledger | N88: 31-03-2026 | O88: TDS DEDUCTED | P88: tds | Q88: TDS | S88: -8458 | T88: -8458 | U88: Pre-P-2.3-party | V88: 19-Jun-26 10:16 AM | AB88: 0
B89: 096969f5-7eef-4cdb-a885-804b75a33c6a | C89: fe174b22-f955-4952-b288-f248fc883a1e | D89: Reversal Entries | E89: Reversal Entries | L89: 0 | M89: ledger | N89: 19-08-2025 | O89: DR. CR. ADJ. | P89: journal | Q89: Journal | S89: 9748 | T89: 9748 | U89: Pre-P-4.3-party | V89: 19-Jun-26 10:16 AM | AB89: 0
B90: 2a8aac29-b524-4b8a-944d-868033f460cc | C90: 44257a85-da72-4d62-91bd-30587b951126 | D90: Reversal Entries | E90: Reversal Entries | L90: 0 | M90: ledger | N90: 30-04-2025 | O90: ANK2526/DBN00001 | P90: creditNote | Q90: CN | S90: 14514 | T90: 14514 | U90: Pre-P-4.3-party | V90: 19-Jun-26 10:16 AM | AB90: 0
B91: 5825f306-91b8-4fa5-9a02-a57eb7571296 | C91: 44257a85-da72-4d62-91bd-30587b951126 | D91: Reversal Entries | E91: Reversal Entries | L91: 0 | M91: ledger | N91: 30-04-2025 | O91: ANK2526/CRN00004 | P91: creditNote | Q91: CN | S91: -14514 | T91: -14514 | U91: Pre-P-4.3-party | V91: 19-Jun-26 10:16 AM | AB91: 0
B92: 63f11a62-2cc4-487e-9811-55b130390539 | C92: fe174b22-f955-4952-b288-f248fc883a1e | D92: Reversal Entries | E92: Reversal Entries | L92: 0 | M92: ledger | N92: 19-08-2025 | O92: DR. CR. ADJ. | P92: journal | Q92: Journal | S92: -9748 | T92: -9748 | U92: Pre-P-4.3-party | V92: 19-Jun-26 10:16 AM | AB92: 0

Sheet 1
A1: Party Id | B1: Matched Id | C1: Status | D1: Classification | E1: Company Statement Type | F1: Company Invoice Date | G1: Company Invoice Number | H1: Company DocType | I1: Company Original DocType | J1: Company Amount | K1: Party Statement Type | L1: Party Invoice Date | M1: Party Invoice Number | N1: Party DocType | O1: Party Original DocType | P1: Party Amount | Q1: Difference | R1: Party Clearing Document Number | S1: Party Clearing Date | T1: Party TDS Amount | U1: Party Posting Date
A2: 59fb819b-d76f-4aef-bd08-7e3dbf42f0c4 | C2: Invoice not booked by Company | D2: Unmatched | J2: 0 | K2: ledger | L2: 27-03-2026 | M2: ANK2526/SER00081 | N2: invoice | O2: Other | P2: 557529 | Q2: 557529

Sheet 10
A1: Company Id | B1: Matched Id | C1: Status | D1: Classification | E1: Company Statement Type | F1: Company Invoice Date | G1: Company Invoice Number | H1: Company DocType | I1: Company Original DocType | J1: Company Amount | K1: Party Statement Type | L1: Party Invoice Date | M1: Party Invoice Number | N1: Party DocType | O1: Party Original DocType | P1: Party Amount | Q1: Difference | R1: Company Clearing Document Number | S1: Company Clearing Date | T1: Company TDS Amount | U1: Company Posting Date
A2: e14afd12-c455-4ae4-be8b-db0b357dbac4 | C2: Invoice not booked by Party | D2: Unmatched | E2: ledger | F2: 27-01-2026 | G2: ANK2526/DBN00012 | H2: invoice | I2: MI | J2: -473280 | P2: 0 | Q2: -473280 | R2: 7053068167 | T2: -8160
A3: 5fb50060-14bd-48e8-9301-272140c55ab4 | C3: Invoice not booked by Party | D3: Unmatched | E3: ledger | F3: 31-07-2025 | G3: ANK2526/DBN00005 | H3: invoice | I3: MI | J3: -254504 | P3: 0 | Q3: -254504 | R3: 7053032930 | T3: -4388
A4: e4d5a91a-46b4-4d2d-9502-565a9e772ded | C4: Invoice not booked by Party | D4: Unmatched | E4: ledger | F4: 10-07-2025 | G4: ANK2526/DNB00003 | H4: invoice | I4: MI | J4: -1555560 | P4: 0 | Q4: -1555560 | R4: 7053038636 | T4: -26820
A5: 073c24a8-8d2a-4cc7-b7f7-698dd4cb4b5a | C5: Invoice not booked by Party | D5: Unmatched | E5: ledger | F5: 27-11-2025 | G5: ANK2526/DBN00008 | H5: invoice | I5: MI | J5: -594152 | P5: 0 | Q5: -594152 | R5: 7053053702 | T5: -10244
A6: b3110aad-4e00-47eb-98b4-53d6f61b7088 | C6: Invoice not booked by Party | D6: Unmatched | E6: ledger | F6: 06-10-2025 | G6: ANK2526/DBN00006 | H6: invoice | I6: MI | J6: -228520 | P6: 0 | Q6: -228520 | R6: 7053052258 | T6: -3940
A7: c259686b-8169-4e00-a872-b4fa7f08123f | C7: Invoice not booked by Party | D7: Unmatched | E7: ledger | F7: 30-04-2025 | G7: ANK2526/DNB00001 | H7: invoice | I7: MI | J7: -14267.66 | P7: 0 | Q7: -14267.66 | R7: 7053015183 | T7: -246

Sheet 23
A1: Party Id | B1: Matched Id | C1: Status | D1: Classification | E1: Company Statement Type | F1: Company Invoice Date | G1: Company Invoice Number | H1: Company DocType | I1: Company Original DocType | J1: Company Amount | K1: Party Statement Type | L1: Party Invoice Date | M1: Party Invoice Number | N1: Party DocType | O1: Party Original DocType | P1: Party Amount | Q1: Difference | R1: Party Clearing Document Number | S1: Party Clearing Date | T1: Party TDS Amount | U1: Party Posting Date
A2: 289ad3fb-1769-409a-909a-3cec95cef9d5 | C2: Credit Note not booked by Company | D2: Unmatched | J2: 0 | K2: ledger | L2: 10-07-2025 | M2: DNB00011 | N2: creditNote | O2: CN | P2: 1582380 | Q2: 1582380
A3: 51e03a91-560b-460b-b310-15e4b684e22e | C3: Credit Note not booked by Company | D3: Unmatched | J3: 0 | K3: ledger | L3: 31-07-2025 | M3: ANK2526/DBN00005 | N3: creditNote | O3: CN | P3: 258892 | Q3: 258892
A4: 5f77d353-a5e7-40cc-a460-0d1a90be31dc | C4: Credit Note not booked by Company | D4: Unmatched | J4: 0 | K4: ledger | L4: 27-11-2025 | M4: ANK2526/DBN00008 | N4: creditNote | O4: CN | P4: 604396 | Q4: 604396
A5: 7fd61a63-5c6f-4418-8e12-d7b417b9492a | C5: Credit Note not booked by Company | D5: Unmatched | J5: 0 | K5: ledger | L5: 20-02-2026 | M5: ANK2526/DBN00015 | N5: creditNote | O5: CN | P5: 388928 | Q5: 388928
A6: 0ca58a7f-65da-4e3e-a0ec-1d98d9e3a5f4 | C6: Credit Note not booked by Company | D6: Unmatched | J6: 0 | K6: ledger | L6: 14-03-2026 | M6: ANK2526/DBN00016 | N6: creditNote | O6: CN | P6: 283200 | Q6: 283200
A7: 71edf8a4-9888-4518-bcac-ae43e5ea8193 | C7: Credit Note not booked by Company | D7: Unmatched | J7: 0 | K7: ledger | L7: 06-10-2025 | M7: ANK2526/DBN00006 | N7: creditNote | O7: CN | P7: 232460 | Q7: 232460
A8: e13ee45f-1714-42a1-8a12-427f9993b620 | C8: Credit Note not booked by Company | D8: Unmatched | J8: 0 | K8: ledger | L8: 13-12-2025 | M8: ANK2526/DBN00009 | N8: creditNote | O8: CN | P8: 215822 | Q8: 215822
A9: 2b2ced9b-b480-4be7-a59a-1a5ae8f5bc89 | C9: Credit Note not booked by Company | D9: Unmatched | J9: 0 | K9: ledger | L9: 27-01-2026 | M9: ANK2526/DBN00012 | N9: creditNote | O9: CN | P9: 481440 | Q9: 481440

Sheet 55
A1: Party Id | B1: Matched Id | C1: Status | D1: Classification | E1: Company Statement Type | F1: Company Invoice Date | G1: Company Invoice Number | H1: Company DocType | I1: Company Original DocType | J1: Company Amount | K1: Party Statement Type | L1: Party Invoice Date | M1: Party Invoice Number | N1: Party DocType | O1: Party Original DocType | P1: Party Amount | Q1: Difference | R1: Party Clearing Document Number | S1: Party Clearing Date | T1: Party TDS Amount | U1: Party Posting Date
A2: 699bd5e5-b0b1-4afe-8de7-ca8f3322ccdd | C2: Payment not booked by Company | D2: Unmatched | J2: 0 | K2: ledger | L2: 27-05-2025 | M2: AXISCN0981979347 | N2: payment | O2: Receipt | P2: -1814400 | Q2: -1814400
A3: a9c1ac6e-0179-4c48-aa04-92b6534f0220 | C3: Payment not booked by Company | D3: Unmatched | J3: 0 | K3: ledger | L3: 11-04-2025 | M3: UTIBN62025041155260266 | N3: payment | O3: Receipt | P3: -743400 | Q3: -743400
A4: 7c6c5123-ba1b-483a-b795-ac9d11e632ab | C4: Payment not booked by Company | D4: Unmatched | J4: 0 | K4: ledger | L4: 13-05-2025 | M4: UTIBN62025051387607677 | N4: payment | O4: Receipt | P4: -914457.6 | Q4: -914457.6
A5: b7683659-9606-4d14-a006-f256e3cdadab | C5: Payment not booked by Company | D5: Unmatched | J5: 0 | K5: ledger | L5: 11-04-2025 | M5: UTIBN62025041155258988 | N5: payment | O5: Receipt | P5: -938407.68 | Q5: -938407.68

Sheet 61
A1: Company Id | B1: Matched Id | C1: Status | D1: Classification | E1: Company Statement Type | F1: Company Invoice Date | G1: Company Invoice Number | H1: Company DocType | I1: Company Original DocType | J1: Company Amount | K1: Party Statement Type | L1: Party Invoice Date | M1: Party Invoice Number | N1: Party DocType | O1: Party Original DocType | P1: Party Amount | Q1: Difference | R1: Company Clearing Document Number | S1: Company Clearing Date | T1: Company TDS Amount | U1: Company Posting Date
A2: 8a49aa96-c2ab-4471-89a5-2a3188aa2216 | C2: Payment not booked by Party | D2: Unmatched | E2: ledger | F2: 29-05-2025 | G2: 7053009822 | H2: payment | I2: KZ | J2: 1784336 | P2: 0 | Q2: 1784336 | R2: 7053009822 | T2: 0
A3: f34a070e-e679-4049-80b8-68848063d92e | C3: Payment not booked by Party | D3: Unmatched | E3: ledger | F3: 08-04-2025 | G3: 7053001045 | H3: payment | I3: KZ | J3: 921650 | P3: 0 | Q3: 921650 | R3: 7053001045 | T3: 0
A4: d33cdc7d-5f77-4869-8028-863e1c13fa15 | C4: Payment not booked by Party | D4: Unmatched | E4: ledger | F4: 14-01-2026 | G4: 7053052258 | H4: payment | I4: KZ | J4: 228520 | P4: 0 | Q4: 228520 | R4: 7053052258 | T4: 0
A5: 39dbb1dc-74fc-4a82-81c0-d022eb6cf108 | C5: Payment not booked by Party | D5: Unmatched | E5: ledger | F5: 08-04-2025 | G5: 7053001046 | H5: payment | I5: KZ | J5: 730800 | P5: 0 | Q5: 730800 | R5: 7053001046 | T5: 0
A6: 3da2bcee-2cbd-4a91-8f1f-7fd7fbf27f05 | C6: Payment not booked by Party | D6: Unmatched | E6: ledger | F6: 31-03-2026 | G6: 7053068167 | H6: payment | I6: KZ | J6: 473280 | P6: 0 | Q6: 473280 | R6: 7053068167 | T6: 0
A7: 484c0899-5552-42fe-a29f-e62c7cb48391 | C7: Payment not booked by Party | D7: Unmatched | E7: ledger | F7: 29-05-2025 | G7: 7053009823 | H7: payment | I7: KZ | J7: 613.96 | P7: 0 | Q7: 613.96 | R7: 7053009823 | T7: 0
A8: 74d9080b-e369-46b4-9ccb-72f40b32f1a5 | C8: Payment not booked by Party | D8: Unmatched | E8: ledger | F8: 12-05-2025 | G8: 7053006480 | H8: payment | I8: KZ | J8: 898127 | P8: 0 | Q8: 898127 | R8: 7053006480 | T8: 0

Sheet 74
A1: Party Id | B1: Matched Id | C1: Status | D1: Classification | E1: Company Statement Type | F1: Company Invoice Date | G1: Company Invoice Number | H1: Company DocType | I1: Company Original DocType | J1: Company Amount | K1: Party Statement Type | L1: Party Invoice Date | M1: Party Invoice Number | N1: Party DocType | O1: Party Original DocType | P1: Party Amount | Q1: Difference | R1: Party Clearing Document Number | S1: Party Clearing Date | T1: Party TDS Amount | U1: Party Posting Date
A2: 647bee11-a5ff-4a23-870f-f583d6cf62b8 | C2: Other entry not booked by Company | D2: Unmatched | J2: 0 | K2: ledger | L2: 30-09-2025 | M2: DEBTORS WRITE OFF | N2: journal | O2: Journal | P2: 25440 | Q2: 25440

Sheet 79
A1: Company Id | B1: Matched Id | C1: Status | D1: Classification | E1: Company Statement Type | F1: Company Invoice Date | G1: Company Invoice Number | H1: Company DocType | I1: Company Original DocType | J1: Company Amount | K1: Party Statement Type | L1: Party Invoice Date | M1: Party Invoice Number | N1: Party DocType | O1: Party Original DocType | P1: Party Amount | Q1: Difference | R1: Company Clearing Document Number | S1: Company Clearing Date | T1: Company TDS Amount | U1: Company Posting Date
A2: 66848aa3-8721-45f9-8f07-7fcdafb4f510 | C2: Other entry not booked by Party | D2: Unmatched | E2: ledger | F2: 31-03-2026 | H2: journal | I2: SA | J2: -179242 | P2: 0 | Q2: -179242 | R2: 7001002085 | T2: -3658
A3: da1f6ac3-73fd-4107-8171-cf14d6b7bbb0 | C3: Other entry not booked by Party | D3: Unmatched | E3: ledger | F3: 31-03-2026 | H3: journal | I3: SA | J3: -235200 | P3: 0 | Q3: -235200 | R3: 7001002096 | T3: -4800
A4: a394fbd0-1313-4234-b850-d30ff082d74b | C4: Other entry not booked by Party | D4: Unmatched | E4: ledger | F4: 31-03-2026 | H4: journal | I4: SA | J4: -520360 | P4: 0 | Q4: -520360 | R4: 7001008009 | T4: -10620

Sheet 94
A1: Company Id | B1: Party Id | C1: Matched Id | D1: Status | E1: Classification | F1: Company Statement Type | G1: Company Invoice Date | H1: Company Invoice Number | I1: Company DocType | J1: Company Original DocType | K1: Company Narration | L1: Company Amount | M1: Party Statement Type | N1: Party Invoice Date | O1: Party Invoice Number | P1: Party DocType | Q1: Party Original DocType | R1: Party Narration | S1: Party Amount | T1: Difference
A2: 274e1989-5f2e-4316-bc94-97976325e7fc | B2: 00367562-24a4-4f8f-80ff-9f982a2591e7 | C2: aa3c61b5-9854-3fe2-9fd7-381cdb7a3021 | D2: TDS Booked by Company | E2: Invoice Number Matched | F2: ledger | G2: 27-11-2025 | H2: ANK2526/GIS00787 | I2: invoice | J2: MF | K2: EMTIG INJECTION [P TO P] | L2: -1691223 | M2: ledger | N2: 27-11-2025 | O2: ANK2526/GIS00787 | P2: invoice | Q2: Sale | S2: 1692835 | T2: 1612
A3: 4496d1c4-1e8a-4d2d-968c-d797ac14155c | B3: 03c26d9f-6c72-4e5f-bfec-675ae5dc3ecd | C3: 2399b5aa-899a-3e44-8e5f-4d09a538a2c3 | D3: TDS Booked by Company | E3: Invoice Number Matched | F3: ledger | G3: 21-04-2025 | H3: ANK2526/SER00001 | I3: invoice | J3: MI | K3: 421111714 MATERNA - HCG 5000 IU | L3: -1860607 | M3: ledger | N3: 21-04-2025 | O3: ANK2526/SER00001 | P3: invoice | Q3: Other | S3: 1894233.6 | T3: 33626.6
A4: 450bd921-1a8d-4845-b2ae-bf1216fd9198 | B4: 2eff2df9-aac2-4397-a9c7-638e6ac9253a | C4: 2a78bd4d-795a-39e0-b2e2-25d82ab37a71 | D4: TDS Booked by Company | E4: Invoice Number Matched | F4: ledger | G4: 16-03-2026 | H4: ANK2526/SER00080 | I4: invoice | J4: MI | K4: 421111716 MATERNA - HMG 75 IU | L4: -1372125 | M4: ledger | N4: 16-03-2026 | O4: ANK2526/SER00080 | P4: invoice | Q4: Other | S4: 1398768 | T4: 26643
A5: 19cf0320-a7d6-4632-93f9-3aa8ebabefda | B5: 356677a1-0763-4f5f-b67d-9fa67464a66e | C5: 33b8f008-c93f-3a19-a5a5-37851b94ef77 | D5: TDS Booked by Company | E5: Invoice Number Matched | F5: ledger | G5: 10-12-2025 | H5: ANK2526/GIS00839 | I5: invoice | J5: MF | K5: REBEZ IV INJECTION [P TO P] | L5: -1666450 | M5: ledger | N5: 10-12-2025 | O5: ANK2526/GIS00839 | P5: invoice | Q5: Sale | S5: 1668039 | T5: 1589
A6: 70d5264b-d33f-4983-93dd-ef6ff1535b45 | B6: 363f9169-6096-452e-9b08-14f89e80ab75 | C6: 96ca066f-f3dd-31d1-8565-a73b4c76be09 | D6: TDS Booked by Company | E6: Invoice Number Matched | F6: ledger | G6: 02-08-2025 | H6: ANK2526/SER00045 | I6: invoice | J6: MI | K6: Job Work Charge - AUG 2025 | L6: -1227.92 | M6: ledger | N6: 02-08-2025 | O6: ANK2526/SER00045 | P6: invoice | Q6: Other | S6: 1249.92 | T6: 22
A7: 1bdafe07-41ec-47b3-baed-36acb746303a | B7: 3c3607e3-b64d-4e2d-8c7c-98b4f01adbac | C7: 252dae23-d549-3aa6-a82d-35d32098b55f | D7: TDS Booked by Company | E7: Invoice Number Matched | F7: ledger | G7: 29-01-2026 | H7: ANK2526/GIS00934 | I7: invoice | J7: MF | K7: REBEZ IV INJECTION [P TO P] | L7: -1370813 | M7: ledger | N7: 29-01-2026 | O7: ANK2526/GIS00934 | P7: invoice | Q7: Sale | S7: 1372120 | T7: 1307
A8: e88999b1-05ec-4268-bbbc-5119f6a8b867 | B8: 3df3999c-3eae-447e-86eb-ace45ffe1656 | C8: 7969e88d-93c3-3ac6-a71b-a5a023490392 | D8: TDS Booked by Company | E8: Invoice Number Matched | F8: ledger | G8: 31-10-2025 | H8: ANK2526/GIS00697 | I8: invoice | J8: MF | K8: EMTIG INJECTION [P TO P] | L8: -3480330 | M8: ledger | N8: 31-10-2025 | O8: ANK2526/GIS00697 | P8: invoice | Q8: Sale | S8: 3483648 | T8: 3318
A9: 40a85208-dcf4-496e-bfaa-a1aa50d87efd | B9: 412b0cf1-2b9a-4f3d-b552-fb96018b8efd | C9: 5e3d74eb-1238-31a5-b9ea-68850a0ee4b8 | D9: TDS Booked by Company | E9: Invoice Number Matched | F9: ledger | G9: 21-08-2025 | H9: ANK2526/SER00049 | I9: invoice | J9: KR | K9: LYKA RATE DIFFERENCE | L9: -99742 | M9: ledger | N9: 21-08-2025 | O9: ANK2526/SER00049 | P9: invoice | Q9: Other | S9: 101556 | T9: 1814
A10: 168a257c-6f08-46b6-9608-0725e376ecba | B10: 4cabb64d-c453-46f4-808e-9156760af86e | C10: 5a843abf-e9ca-324c-afd1-0dedba4227f0 | D10: TDS Booked by Company | E10: Invoice Number Matched | F10: ledger | G10: 26-11-2025 | H10: ANK2526/GIS00781 | I10: invoice | J10: MF | K10: REBEZ IV INJECTION [P TO P] | L10: -292718 | M10: ledger | N10: 26-11-2025 | O10: ANK2526/GIS00781 | P10: invoice | Q10: Sale | S10: 292997 | T10: 279
A11: 5f10247c-e587-427f-949f-e2e1ffaa410d | B11: 50e3b35b-9047-4be7-af36-0db993f961e8 | C11: c11d5c55-e4a0-3b4f-8aaa-7a1cd55e7744 | D11: TDS Booked by Company | E11: Invoice Number Matched | F11: ledger | G11: 31-07-2025 | H11: ANK2526/SER00044 | I11: invoice | J11: MI | K11: 420005883 SOPRAPEN I.V. 20 MG G | L11: -86526.2 | M11: ledger | N11: 31-07-2025 | O11: ANK2526/SER00044 | P11: invoice | Q11: Other | S11: 88099.2 | T11: 1573
A12: 5d4248ec-7a4e-4fcd-bcc9-3fa3cbd79825 | B12: 80f49ab0-4efa-4eda-b1aa-723f9a2e2702 | C12: 7515671b-9a76-3276-8caa-36e894b60403 | D12: TDS Booked by Company | E12: Invoice Number Matched | F12: ledger | G12: 30-11-2025 | H12: ANK2526/GIS00823 | I12: invoice | J12: MF | K12: REBEZ IV INJECTION [P TO P] | L12: -834164 | M12: ledger | N12: 30-11-2025 | O12: ANK2526/GIS00823 | P12: invoice | Q12: Sale | S12: 834959 | T12: 795
A13: 31bbc752-4579-4f0a-8c60-93d9f4763baa | B13: 81bba397-4096-40c8-b7e2-b7017396a2d5 | C13: 4121dcea-21e1-39ea-b2ae-617ac8d404e6 | D13: TDS Booked by Company | E13: Invoice Number Matched | F13: ledger | G13: 27-11-2025 | H13: ANK2526/GIS00786 | I13: invoice | J13: MF | K13: EMTIG INJECTION [P TO P] | L13: -1707537 | M13: ledger | N13: 27-11-2025 | O13: ANK2526/GIS00786 | P13: invoice | Q13: Sale | S13: 1709165 | T13: 1628
... A22: feffc451-9eb3-4171-8faf-000859405a38 | B22: fad17af0-baf0-4352-a9e7-25d790de30fe | C22: 80ae845c-e9fa-33be-bd86-890140fe421e | D22: TDS Booked by Company | E22: Invoice Number Matched | F22: ledger | G22: 26-11-2025 | H22: ANK2526/GIS00782 | I22: invoice | J22: MF | K22: REBEZ IV INJECTION [P TO P] | L22: -120715 | M22: ledger | N22: 26-11-2025 | O22: ANK2526/GIS00782 | P22: invoice | Q22: Sale | S22: 120830 | T22: 115
A23: 524bc8e0-a4a8-42e8-b23d-c1f23686de5a | B23: 186ecf5a-6b8f-46dc-affc-8da4ff6898d7 | C23: 23202ed6-9dcb-4c15-beab-145bc4a547de | D23: TDS Booked by Party | E23: Payment Matched - Recommended | F23: ledger | G23: 22-01-2026 | H23: 7053054141 | I23: payment | J23: KZ | L23: 413433 | M23: ledger | N23: 23-01-2026 | O23: UTIBR72026012300040395 | P23: payment | Q23: Receipt | S23: -413827 | T23: -394
A24: 01b0bfca-76c7-41e4-b373-b8f58d7c5a86 | B24: 1e1bce79-95dd-4cc6-8b1b-ff4d93cc6372 | C24: 4d6f23b7-dd76-3d73-b15f-1e43a867c178 | D24: TDS Booked by Party | E24: Date and Amount Matched - Recommended | F24: ledger | G24: 17-04-2025 | H24: 7053002545 | I24: payment | J24: KZ | L24: 7298494 | M24: ledger | N24: 17-04-2025 | O24: UTIBR72025041700038257 | P24: payment | Q24: Receipt | S24: -7305016 | T24: -6522
A25: 06b4cbc1-df7c-4dc2-a5e5-e3ed11468e91 | B25: 45a5cece-d771-4b25-a062-d0c539fffa26 | C25: 1395c5ae-873f-3f8b-ae53-ab71616636e5 | D25: TDS Booked by Party | E25: Multiple Based on Date | F25: ledger | G25: 08-10-2025 | H25: 7053032927 | I25: payment | J25: KZ | L25: 99742 | M25: ledger | N25: 08-10-2025 | O25: UTIBR72025100800060307 | P25: payment | Q25: Receipt | S25: 0 | T25: 0
A26: c9413937-a0a2-440e-afed-243116b6bb39 | B26: c0ac7d01-7b9c-40c6-abca-c0fdf6d3a1c1 | C26: 1395c5ae-873f-3f8b-ae53-ab71616636e5 | D26: TDS Booked by Party | E26: Multiple Based on Date | F26: ledger | G26: 08-10-2025 | H26: 7053033057 | I26: payment | J26: KZ | L26: 817740 | M26: ledger | N26: 08-10-2025 | O26: AXISCN1112025593 | P26: payment | Q26: Receipt | S26: 0 | T26: 0
A27: 77c42784-11ca-4039-a04e-9fc050e211d9 | B27: e052f7df-7a34-409c-820d-426b4b035581 | C27: 1395c5ae-873f-3f8b-ae53-ab71616636e5 | D27: TDS Booked by Party | E27: Multiple Based on Date | F27: ledger | G27: 08-10-2025 | H27: 7053032930 | I27: payment | J27: KZ | L27: 257573.8 | M27: ledger | N27: 08-10-2025 | O27: AXISCN1112157656 | P27: payment | Q27: Receipt | S27: -1178188 | T27: -3132.2
A28: a0968703-cc23-44af-b031-f718ce9e84ce | B28: 4b5709cd-1408-4b7e-8e81-53c786fe9b81 | C28: e817c417-e8ce-344a-9cf1-b855d2c82a41 | D28: TDS Booked by Party | E28: Date and Amount Matched - Recommended | F28: ledger | G28: 01-07-2025 | H28: 7053015183 | I28: payment | J28: KZ | L28: 14267.66 | M28: ledger | N28: 01-07-2025 | O28: AXISCN1007743339 | P28: payment | Q28: Receipt | S28: -14514 | T28: -246.34
A29: e3064d9b-36d2-47c3-b614-7a93582dac31 | B29: 4bf4f1e8-4ea0-4ebd-a461-51858d4a1d59 | C29: 05f4488d-878f-3ab2-a045-a82fee6d3bcb | D29: TDS Booked by Party | E29: Date and Amount Matched - Recommended | F29: ledger | G29: 16-05-2025 | H29: 7053007500 | I29: payment | J29: KZ | L29: 1359585 | M29: ledger | N29: 16-05-2025 | O29: UTIBN62025051618331475 | P29: payment | Q29: Receipt | S29: -1360800 | T29: -1215
A30: eb499910-3892-42be-97e6-0ca5eb6ab8ee | B30: 51022052-eebc-4fbc-a428-096361b8a8c3 | C30: d770e8f0-576e-355f-b490-2555388f5d28 | D30: TDS Booked by Party | E30: Date and Amount Matched - Recommended | F30: ledger | G30: 06-11-2025 | H30: 7053038636 | I30: payment | J30: KZ | L30: 1555560 | M30: ledger | N30: 06-11-2025 | O30: UTIBR72025110600053262 | P30: payment | Q30: Receipt | S30: -1582380 | T30: -26820
A31: ffb7e322-b11e-418d-8624-0c78428ff4bc | B31: 5ce800c0-06e5-4125-a988-a782f27d2933 | C31: 30c02a2c-73e5-4135-843c-26b6c22ef8ec | D31: TDS Booked by Party | E31: Multiple Based on Invoice Number and Date Range | F31: ledger | G31: 26-05-2025 | H31: 7053009079 | I31: payment | J31: KZ | L31: 1812780 | M31: ledger | N31: 30-05-2025 | O31: AXISCN0983739554 | P31: payment | Q31: Receipt | S31: -1817403.8 | T31: -4623.84
A32: 16064676-ddc3-4045-a068-cd796accf406 | B32: 6483bfe6-60a2-48ca-a5d3-f39bda2b6cfb | C32: c8f17e1c-3a7a-39ec-8269-5746cfc5a4f8 | D32: TDS Booked by Party | E32: Date and Amount Matched - Recommended | F32: ledger | G32: 17-06-2025 | H32: 7053012813 | I32: payment | J32: KZ | L32: 1860607 | M32: ledger | N32: 17-06-2025 | O32: AXISCN0994733294 | P32: payment | Q32: Receipt | S32: -1894233.6 | T32: -33626.6
A33: 7c3db2b5-709b-419a-9fee-1ff7747aea8a | B33: 6a61b6ee-0eba-480f-ba9a-db85633f5e91 | C33: 5c4816a8-ac14-3e72-9090-a3b72bad22e7 | D33: TDS Booked by Party | E33: Date and Amount Matched - Recommended | F33: ledger | G33: 01-10-2025 | H33: 7053031634 | I33: payment | J33: KZ | L33: 1070387 | M33: ledger | N33: 01-10-2025 | O33: AXISCN1103265077 | P33: payment | Q33: Receipt | S33: -1089849.6 | T33: -19462.6
A34: 823a6688-4523-4a8e-9948-a9933e848717 | B34: 8c1a1eab-34db-4f50-8dd1-f0029d456470 | C34: 272317a6-3e17-325e-9f62-8625bbbb07c3 | D34: TDS Booked by Party | E34: Multiple Based on Date | F34: ledger | G34: 21-01-2026 | H34: 7053053702 | I34: payment | J34: KZ | L34: 594152 | M34: ledger | N34: 21-01-2026 | O34: UTIBR72026012100004817 | P34: payment | Q34: Receipt | S34: 0 | T34: 0
... A42: b2e347ad-12a7-49e8-b77b-8588201eb191 | B42: f8ecbfc7-0224-4122-8ad2-06231f412d43 | C42: e2732d49-1980-36ce-9173-91c7827c949c | D42: TDS Booked by Party | E42: Date and Amount Matched - Recommended | F42: ledger | G42: 21-05-2025 | H42: 7053008353 | I42: payment | J42: KZ | L42: 1066852 | M42: ledger | N42: 21-05-2025 | O42: AXISCN0979676342 | P42: payment | Q42: Receipt | S42: -1085246 | T42: -18394
B43: 54c64096-ea61-4f44-9146-bd38fc6090d0 | D43: TDS Booked by Party | E43: TDS Booked by Party | L43: 0 | M43: ledger | N43: 31-03-2026 | O43: TDS ANK2526/GIS00926 | P43: tds | Q43: TDS | S43: -1537 | T43: -1537
B44: b9dcae01-168d-49d8-a84f-53ecc4177168 | D44: TDS Booked by Party | E44: TDS Booked by Party | L44: 0 | M44: ledger | N44: 31-03-2026 | O44: TDS ANK2526/GIS00923 | P44: tds | Q44: TDS | S44: -3262.46 | T44: -3262.46
B45: df1331d7-652e-411d-9518-195aafb24082 | D45: TDS Booked by Party | E45: TDS Booked by Party | L45: 0 | M45: ledger | N45: 31-03-2026 | O45: TDS DEDUCTED | P45: tds | Q45: TDS | S45: -8458 | T45: -8458
B46: 9870be35-0fc7-442d-866b-dec7a75ddd57 | D46: TDS Booked by Party | E46: TDS Booked by Party | L46: 0 | M46: ledger | N46: 31-03-2026 | O46: TDS ANK2526/GIS00934 | P46: tds | Q46: TDS | S46: -1307 | T46: -1307

Sheet Party
A1: Party Id | B1: Matched Id | C1: Status | D1: Classification | E1: Party Statement Type | F1: Party Invoice Date | G1: Party Invoice Number | H1: Party DocType | I1: Party Original DocType | J1: Party Narration | K1: Party Amount | L1: Matched Rule | M1: Reco Data & Time | N1: Party Clearing Document Number | O1: Party Clearing Date | P1: Party TDS Amount | Q1: Party Posting Date | R1: TXLDKEY | S1: Transaction Id. | T1: Ref Date | U1: Balance Amt.
A2: 00367562-24a4-4f8f-80ff-9f982a2591e7 | B2: aa3c61b5-9854-3fe2-9fd7-381cdb7a3021 | C2: TDS Booked by Company | D2: Invoice Number Matched | E2: ledger | F2: 27-11-2025 | G2: ANK2526/GIS00787 | H2: invoice | I2: Sale | K2: 1692835 | L2: PRI-INV1.6-company | M2: 19-Jun-26 10:16 AM | P2: 0 | R2: 2025-11-272ANK/2526/ISO/SPP/00259001 | S2: ANK/2526/ISO/SPP/00259 | T2: 27-11-2025 | U2: 7299475
A3: 03c26d9f-6c72-4e5f-bfec-675ae5dc3ecd | B3: 2399b5aa-899a-3e44-8e5f-4d09a538a2c3 | C3: TDS Booked by Company | D3: Invoice Number Matched | E3: ledger | F3: 21-04-2025 | G3: ANK2526/SER00001 | H3: invoice | I3: Other | K3: 1894233.6 | L3: PRI-INV1.6-company | M3: 19-Jun-26 10:16 AM | P3: 0 | R3: 2025-04-212ANK/2526/SLD/SVB/00001001 | S3: ANK/2526/SLD/SVB/00001 | T3: 21-04-2025 | U3: 5736655.04
A4: 06a587ff-f941-4454-b4a2-1ed0e8d7e52a | C4: Opening Balance as per Party | D4: Opening Balance | E4: ledger | F4: 01-04-2025 | H4: openingBalance | I4: OP | K4: 0 | M4: 19-Jun-26 10:16 AM | P4: 0 | R4: 2025-04-011 | S4: Opening Balance | T4: 30-12-1899 | U4: 10445028
A5: 096969f5-7eef-4cdb-a885-804b75a33c6a | B5: fe174b22-f955-4952-b288-f248fc883a1e | C5: Reversal Entries | D5: Reversal Entries | E5: ledger | F5: 19-08-2025 | G5: DR. CR. ADJ. | H5: journal | I5: Journal | K5: 9748 | L5: Pre-P-4.3-party | M5: 19-Jun-26 10:16 AM | P5: 0 | R5: 2025-08-192ANK/2526/JVD/GJV/00155001 | S5: ANK/2526/JVD/GJV/00155 | T5: 19-08-2025 | U5: -25440
A6: 0ca58a7f-65da-4e3e-a0ec-1d98d9e3a5f4 | C6: Credit Note not booked by Company | D6: Unmatched | E6: ledger | F6: 14-03-2026 | G6: ANK2526/DBN00016 | H6: creditNote | I6: CN | K6: 283200 | L6: Post-P-3.4-party | M6: 19-Jun-26 10:16 AM | P6: 0 | R6: 2026-03-142ANK/2526/SDC/SD1/00015001 | S6: ANK/2526/SDC/SD1/00015 | T6: 14-03-2026 | U6: 1373566.8
A7: 186ecf5a-6b8f-46dc-affc-8da4ff6898d7 | B7: 23202ed6-9dcb-4c15-beab-145bc4a547de | C7: TDS Booked by Party | D7: Payment Matched - Recommended | E7: ledger | F7: 23-01-2026 | G7: UTIBR72026012300040395 | H7: payment | I7: Receipt | K7: -413827 | L7: SEC-PAY4.1-company | M7: 19-Jun-26 10:16 AM | P7: 0 | R7: 2026-01-232ANK/2526/BDR/YB1/00788001 | S7: ANK/2526/BDR/YB1/00788 | T7: 23-01-2026 | U7: 5928585
A8: 1e1bce79-95dd-4cc6-8b1b-ff4d93cc6372 | B8: 4d6f23b7-dd76-3d73-b15f-1e43a867c178 | C8: TDS Booked by Party | D8: Date and Amount Matched - Recommended | E8: ledger | F8: 17-04-2025 | G8: UTIBR72025041700038257 | H8: payment | I8: Receipt | K8: -7305016 | L8: SEC-PAY3.1-company | M8: 19-Jun-26 10:16 AM | P8: 0 | R8: 2025-04-172ANK/2526/BDR/YB1/00032001 | S8: ANK/2526/BDR/YB1/00032 | T8: 17-04-2025 | U8: 3140012
A9: 23129740-91f2-4a2a-98ec-c5c6334ba4c1 | C9: Opening Balance as per Party | D9: Opening Balance | E9: ledger | F9: 01-04-2025 | H9: openingBalance | I9: OP | K9: 0 | M9: 19-Jun-26 10:16 AM | P9: 0 | R9: 2025-04-011 | S9: Opening Balance | T9: 30-12-1899 | U9: 5524229.1200000001
A10: 289ad3fb-1769-409a-909a-3cec95cef9d5 | C10: Credit Note not booked by Company | D10: Unmatched | E10: ledger | F10: 10-07-2025 | G10: DNB00011 | H10: creditNote | I10: CN | K10: 1582380 | L10: Post-P-3.4-party | M10: 19-Jun-26 10:16 AM | P10: 0 | R10: 2025-07-102ANK/2526/SDC/SD1/00003001 | S10: ANK/2526/SDC/SD1/00003 | T10: 10-07-2025 | U10: 2113166.88
A11: 2a8aac29-b524-4b8a-944d-868033f460cc | B11: 44257a85-da72-4d62-91bd-30587b951126 | C11: Reversal Entries | D11: Reversal Entries | E11: ledger | F11: 30-04-2025 | G11: ANK2526/DBN00001 | H11: creditNote | I11: CN | K11: 14514 | L11: Pre-P-4.3-party | M11: 19-Jun-26 10:16 AM | P11: 0 | R11: 2025-04-302ANK/2526/SDC/SD1/00001001 | S11: ANK/2526/SDC/SD1/00001 | T11: 30-04-2025 | U11: 5736655.04
A12: 2b2ced9b-b480-4be7-a59a-1a5ae8f5bc89 | C12: Credit Note not booked by Company | D12: Unmatched | E12: ledger | F12: 27-01-2026 | G12: ANK2526/DBN00012 | H12: creditNote | I12: CN | K12: 481440 | L12: Post-P-3.4-party | M12: 19-Jun-26 10:16 AM | P12: 0 | R12: 2026-01-272ANK/2526/SDC/SD1/00011001 | S12: ANK/2526/SDC/SD1/00011 | T12: 27-01-2026 | U12: 701438.8
A13: 2eff2df9-aac2-4397-a9c7-638e6ac9253a | B13: 2a78bd4d-795a-39e0-b2e2-25d82ab37a71 | C13: TDS Booked by Company | D13: Invoice Number Matched | E13: ledger | F13: 16-03-2026 | G13: ANK2526/SER00080 | H13: invoice | I13: Other | K13: 1398768 | L13: PRI-INV1.6-company | M13: 19-Jun-26 10:16 AM | P13: 0 | R13: 2026-03-162ANK/2526/SLD/SVB/00080001 | S13: ANK/2526/SLD/SVB/00080 | T13: 16-03-2026 | U13: 2772334.8
A14: 356677a1-0763-4f5f-b67d-9fa67464a66e | B14: 33b8f008-c93f-3a19-a5a5-37851b94ef77 | C14: TDS Booked by Company | D14: Invoice Number Matched | E14: ledger | F14: 10-12-2025 | G14: ANK2526/GIS00839 | H14: invoice | I14: Sale | K14: 1668039 | L14: PRI-INV1.6-company | M14: 19-Jun-26 10:16 AM | P14: 0 | R14: 2025-12-102ANK/2526/ISO/SPP/00273001 | S14: ANK/2526/ISO/SPP/00273 | T14: 10-12-2025 | U14: 9802473
A15: 363f9169-6096-452e-9b08-14f89e80ab75 | B15: 96ca066f-f3dd-31d1-8565-a73b4c76be09 | C15: TDS Booked by Company | D15: Invoice Number Matched | E15: ledger | F15: 02-08-2025 | G15: ANK2526/SER00045 | H15: invoice | I15: Other | K15: 1249.92 | L15: PRI-INV1.6-company | M15: 19-Jun-26 10:16 AM | P15: 0 | R15: 2025-08-022ANK/2526/SLD/SVB/00045001 | S15: ANK/2526/SLD/SVB/00045 | T15: 02-08-2025 | U15: 3987761.92
A16: 3c3607e3-b64d-4e2d-8c7c-98b4f01adbac | B16: 252dae23-d549-3aa6-a82d-35d32098b55f | C16: TDS Booked by Company | D16: Invoice Number Matched | E16: ledger | F16: 29-01-2026 | G16: ANK2526/GIS00934 | H16: invoice | I16: Sale | K16: 1372120 | L16: PRI-INV1.6-company | M16: 19-Jun-26 10:16 AM | P16: 0 | R16: 2026-01-292ANK/2526/ISO/SPP/00310001 | S16: ANK/2526/ISO/SPP/00310 | T16: 29-01-2026 | U16: 8914903
A17: 3df3999c-3eae-447e-86eb-ace45ffe1656 | B17: 7969e88d-93c3-3ac6-a71b-a5a023490392 | C17: TDS Booked by Company | D17: Invoice Number Matched | E17: ledger | F17: 31-10-2025 | G17: ANK2526/GIS00697 | H17: invoice | I17: Sale | K17: 3483648 | L17: PRI-INV1.6-company | M17: 19-Jun-26 10:16 AM | P17: 0 | R17: 2025-10-312ANK/2526/ISO/SPP/00230001 | S17: ANK/2526/ISO/SPP/00230 | T17: 31-10-2025 | U17: 3483648
A18: 412b0cf1-2b9a-4f3d-b552-fb96018b8efd | B18: 5e3d74eb-1238-31a5-b9ea-68850a0ee4b8 | C18: TDS Booked by Company | D18: Invoice Number Matched | E18: ledger | F18: 21-08-2025 | G18: ANK2526/SER00049 | H18: invoice | I18: Other | K18: 101556 | L18: PRI-INV1.6-company | M18: 19-Jun-26 10:16 AM | P18: 0 | R18: 2025-08-212ANK/2526/SLD/SVB/00049001 | S18: ANK/2526/SLD/SVB/00049 | T18: 22-08-2025 | U18: 4079569.92
A19: 45a5cece-d771-4b25-a062-d0c539fffa26 | B19: 1395c5ae-873f-3f8b-ae53-ab71616636e5 | C19: TDS Booked by Party | D19: Multiple Based on Date | E19: ledger | F19: 08-10-2025 | G19: UTIBR72025100800060307 | H19: payment | I19: Receipt | K19: -258892 | L19: PRI-PAY5.2-company | M19: 19-Jun-26 10:16 AM | P19: 0 | R19: 2025-10-082ANK/2526/BDR/YB1/00549001 | S19: ANK/2526/BDR/YB1/00549 | T19: 08-10-2025 | U19: 4324662.88
A20: 4b10c103-35ae-417f-b854-efa1a8945391 | B20: 05185f70-d145-3675-9617-30ad2c62d476 | C20: Reconciled | D20: Amount Matched - Recommended | E20: ledger | F20: 31-10-2025 | G20: ANK2526/DBN00007 | H20: creditNote | I20: CN | K20: 817740 | L20: SEC-CN1.1-party | M20: 19-Jun-26 10:16 AM | P20: 0 | R20: 2025-10-312ANK/2526/SDC/SD1/00006001 | S20: ANK/2526/SDC/SD1/00006 | T20: 31-10-2025 | U20: 1819016.8
A21: 4b5709cd-1408-4b7e-8e81-53c786fe9b81 | B21: e817c417-e8ce-344a-9cf1-b855d2c82a41 | C21: TDS Booked by Party | D21: Date and Amount Matched - Recommended | E21: ledger | F21: 01-07-2025 | G21: AXISCN1007743339 | H21: payment | I21: Receipt | K21: -14514 | L21: SEC-PAY3.1-company | M21: 19-Jun-26 10:16 AM | P21: 0 | R21: 2025-07-012ANK/2526/BDR/YB1/00248001 | S21: ANK/2526/BDR/YB1/00248 | T21: 01-07-2025 | U21: 528912
A22: 4bf4f1e8-4ea0-4ebd-a461-51858d4a1d59 | B22: 05f4488d-878f-3ab2-a045-a82fee6d3bcb | C22: TDS Booked by Party | D22: Date and Amount Matched - Recommended | E22: ledger | F22: 16-05-2025 | G22: UTIBN62025051618331475 | H22: payment | I22: Receipt | K22: -1360800 | L22: SEC-PAY3.1-company | M22: 19-Jun-26 10:16 AM | P22: 0 | R22: 2025-05-162ANK/2526/BDR/YB1/00098001 | S22: ANK/2526/BDR/YB1/00098 | T22: 16-05-2025 | U22: 5719596
A23: 4cabb64d-c453-46f4-808e-9156760af86e | B23: 5a843abf-e9ca-324c-afd1-0dedba4227f0 | C23: TDS Booked by Company | D23: Invoice Number Matched | E23: ledger | F23: 26-11-2025 | G23: ANK2526/GIS00781 | H23: invoice | I23: Sale | K23: 292997 | L23: PRI-INV1.6-company | M23: 19-Jun-26 10:16 AM | P23: 0 | R23: 2025-11-262ANK/2526/ISO/SPP/00255001 | S23: ANK/2526/ISO/SPP/00255 | T23: 26-11-2025 | U23: 3776645
A24: 50e3b35b-9047-4be7-af36-0db993f961e8 | B24: c11d5c55-e4a0-3b4f-8aaa-7a1cd55e7744 | C24: TDS Booked by Company | D24: Invoice Number Matched | E24: ledger | F24: 31-07-2025 | G24: ANK2526/SER00044 | H24: invoice | I24: Other | K24: 88099.2 | L24: PRI-INV1.6-company | M24: 19-Jun-26 10:16 AM | P24: 0 | R24: 2025-07-312ANK/2526/SLD/SVB/00044001 | S24: ANK/2526/SLD/SVB/00044 | T24: 31-07-2025 | U24: 3986512
A25: 51022052-eebc-4fbc-a428-096361b8a8c3 | B25: d770e8f0-576e-355f-b490-2555388f5d28 | C25: TDS Booked by Party | D25: Date and Amount Matched - Recommended | E25: ledger | F25: 06-11-2025 | G25: UTIBR72025110600053262 | H25: payment | I25: Receipt | K25: -1582380 | L25: SEC-PAY3.1-company | M25: 19-Jun-26 10:16 AM | P25: 0 | R25: 2025-11-062ANK/2526/BDR/YB1/00608001 | S25: ANK/2526/BDR/YB1/00608 | T25: 06-11-2025 | U25: 236636.79999999999
A26: 51e03a91-560b-460b-b310-15e4b684e22e | C26: Credit Note not booked by Company | D26: Unmatched | E26: ledger | F26: 31-07-2025 | G26: ANK2526/DBN00005 | H26: creditNote | I26: CN | K26: 258892 | L26: Post-P-3.4-party | M26: 19-Jun-26 10:16 AM | P26: 0 | R26: 2025-07-312ANK/2526/SDC/SD1/00004001 | S26: ANK/2526/SDC/SD1/00004 | T26: 31-07-2025 | U26: 2943796.48
A27: 54c64096-ea61-4f44-9146-bd38fc6090d0 | B27: b995ec42-83e7-45de-88e3-bb8b492089fb | C27: TDS Booked by Party | D27: TDS Booked by Party | E27: ledger | F27: 31-03-2026 | G27: TDS ANK2526/GIS00926 | H27: tds | I27: TDS | K27: -1537 | L27: Pre-P-2.3-party | M27: 19-Jun-26 10:16 AM | P27: 0 | R27: 2026-03-312ANK/2526/JVD/GJV/00604002 | S27: ANK/2526/JVD/GJV/00604 | T27: 31-03-2026 | U27: 6407105.54
A28: 5825f306-91b8-4fa5-9a02-a57eb7571296 | B28: 44257a85-da72-4d62-91bd-30587b951126 | C28: Reversal Entries | D28: Reversal Entries | E28: ledger | F28: 30-04-2025 | G28: ANK2526/CRN00004 | H28: creditNote | I28: CN | K28: -14514 | L28: Pre-P-4.3-party | M28: 19-Jun-26 10:16 AM | P28: 0 | R28: 2025-04-302ANK/2526/SDC/SC1/00001001 | S28: ANK/2526/SDC/SC1/00001 | T28: 30-04-2025 | U28: 5722141.04
A29: 59fb819b-d76f-4aef-bd08-7e3dbf42f0c4 | C29: Invoice not booked by Company | D29: Unmatched | E29: ledger | F29: 27-03-2026 | G29: ANK2526/SER00081 | H29: invoice | I29: Other | K29: 557529 | L29: Post-P-3.1-party | M29: 19-Jun-26 10:16 AM | P29: 0 | R29: 2026-03-272ANK/2526/SLD/SVB/00081001 | S29: ANK/2526/SLD/SVB/00081 | T29: 27-03-2026 | U29: 3329863.8
A30: 5ce800c0-06e5-4125-a988-a782f27d2933 | B30: 30c02a2c-73e5-4135-843c-26b6c22ef8ec | C30: TDS Booked by Party | D30: Multiple Based on Invoice Number and Date Range | E30: ledger | F30: 30-05-2025 | G30: AXISCN0983739554 | H30: payment | I30: Receipt | K30: -1816778.9 | L30: PRI-PAY13.1-company | M30: 19-Jun-26 10:16 AM | P30: 0 | R30: 2025-05-302ANK/2526/BDR/YB1/00145001 | S30: ANK/2526/BDR/YB1/00145 | T30: 30-05-2025 | U30: 1920172.56
A31: 5f77d353-a5e7-40cc-a460-0d1a90be31dc | C31: Credit Note not booked by Company | D31: Unmatched | E31: ledger | F31: 27-11-2025 | G31: ANK2526/DBN00008 | H31: creditNote | I31: CN | K31: 604396 | L31: Post-P-3.4-party | M31: 19-Jun-26 10:16 AM | P31: 0 | R31: 2025-11-272ANK/2526/SDC/SD1/00007001 | S31: ANK/2526/SDC/SD1/00007 | T31: 27-11-2025 | U31: 841032.8
A32: 63f11a62-2cc4-487e-9811-55b130390539 | B32: fe174b22-f955-4952-b288-f248fc883a1e | C32: Reversal Entries | D32: Reversal Entries | E32: ledger | F32: 19-08-2025 | G32: DR. CR. ADJ. | H32: journal | I32: Journal | K32: -9748 | L32: Pre-P-4.3-party | M32: 19-Jun-26 10:16 AM | P32: 0 | R32: 2025-08-192ANK/2526/JVD/GJV/00155002 | S32: ANK/2526/JVD/GJV/00155 | T32: 19-08-2025 | U32: 3978013.92
A33: 647bee11-a5ff-4a23-870f-f583d6cf62b8 | C33: Other entry not booked by Company | D33: Unmatched | E33: ledger | F33: 30-09-2025 | G33: DEBTORS WRITE OFF | H33: journal | I33: Journal | K33: 25440 | L33: Post-P-3.5-party | M33: 19-Jun-26 10:16 AM | P33: 0 | R33: 2025-09-302LHO/2526/JVD/GJV/00771001 | S33: LHO/2526/JVD/GJV/00771 | T33: 30-09-2025 | U33: 3920000
A34: 6483bfe6-60a2-48ca-a5d3-f39bda2b6cfb | B34: c8f17e1c-3a7a-39ec-8269-5746cfc5a4f8 | C34: TDS Booked by Party | D34: Date and Amount Matched - Recommended | E34: ledger | F34: 17-06-2025 | G34: AXISCN0994733294 | H34: payment | I34: Receipt | K34: -1894233.6 | L34: SEC-PAY3.1-company | M34: 19-Jun-26 10:16 AM | P34: 0 | R34: 2025-06-172ANK/2526/BDR/YB1/00189001 | S34: ANK/2526/BDR/YB1/00189 | T34: 17-06-2025 | U34: 25314
A35: 699bd5e5-b0b1-4afe-8de7-ca8f3322ccdd | C35: Payment not booked by Company | D35: Unmatched | E35: ledger | F35: 27-05-2025 | G35: AXISCN0981979347 | H35: payment | I35: Receipt | K35: -1814400 | L35: Post-P-3.2-party | M35: 19-Jun-26 10:16 AM | P35: 0 | R35: 2025-05-272ANK/2526/BDR/YB1/00125001 | S35: ANK/2526/BDR/YB1/00125 | T35: 27-05-2025 | U35: 3905196
A36: 6a61b6ee-0eba-480f-ba9a-db85633f5e91 | B36: 5c4816a8-ac14-3e72-9090-a3b72bad22e7 | C36: TDS Booked by Party | D36: Date and Amount Matched - Recommended | E36: ledger | F36: 01-10-2025 | G36: AXISCN1103265077 | H36: payment | I36: Receipt | K36: -1089849.6 | L36: SEC-PAY3.1-company | M36: 19-Jun-26 10:16 AM | P36: 0 | R36: 2025-10-012ANK/2526/BDR/YB1/00540001 | S36: ANK/2526/BDR/YB1/00540 | T36: 01-10-2025 | U36: 4452650.88
A37: 71edf8a4-9888-4518-bcac-ae43e5ea8193 | C37: Credit Note not booked by Company | D37: Unmatched | E37: ledger | F37: 06-10-2025 | G37: ANK2526/DBN00006 | H37: creditNote | I37: CN | K37: 232460 | L37: Post-P-3.4-party | M37: 19-Jun-26 10:16 AM | P37: 0 | R37: 2025-10-062ANK/2526/SDC/SD1/00005001 | S37: ANK/2526/SDC/SD1/00005 | T37: 06-10-2025 | U37: 4685110.88
A38: 7c6c5123-ba1b-483a-b795-ac9d11e632ab | C38: Payment not booked by Company | D38: Unmatched | E38: ledger | F38: 13-05-2025 | G38: UTIBN62025051387607677 | H38: payment | I38: Receipt | K38: -914457.6 | L38: Post-P-3.2-party | M38: 19-Jun-26 10:16 AM | P38: 0 | R38: 2025-05-132ANK/2526/BDR/YB1/00086001 | S38: ANK/2526/BDR/YB1/00086 | T38: 13-05-2025 | U38: 4822197.4400000004
A39: 7fd61a63-5c6f-4418-8e12-d7b417b9492a | C39: Credit Note not booked by Company | D39: Unmatched | E39: ledger | F39: 20-02-2026 | G39: ANK2526/DBN00015 | H39: creditNote | I39: CN | K39: 388928 | L39: Post-P-3.4-party | M39: 19-Jun-26 10:16 AM | P39: 0 | R39: 2026-02-202ANK/2526/SDC/SD1/00014001 | S39: ANK/2526/SDC/SD1/00014 | T39: 20-02-2026 | U39: 1090366.8
A40: 80f49ab0-4efa-4eda-b1aa-723f9a2e2702 | B40: 7515671b-9a76-3276-8caa-36e894b60403 | C40: TDS Booked by Company | D40: Invoice Number Matched | E40: ledger | F40: 30-11-2025 | G40: ANK2526/GIS00823 | H40: invoice | I40: Sale | K40: 834959 | L40: PRI-INV1.6-company | M40: 19-Jun-26 10:16 AM | P40: 0 | R40: 2025-11-302ANK/2526/ISO/SPP/00267001 | S40: ANK/2526/ISO/SPP/00267 | T40: 30-11-2025 | U40: 8134434
A41: 81bba397-4096-40c8-b7e2-b7017396a2d5 | B41: 4121dcea-21e1-39ea-b2ae-617ac8d404e6 | C41: TDS Booked by Company | D41: Invoice Number Matched | E41: ledger | F41: 27-11-2025 | G41: ANK2526/GIS00786 | H41: invoice | I41: Sale | K41: 1709165 | L41: PRI-INV1.6-company | M41: 19-Jun-26 10:16 AM | P41: 0 | R41: 2025-11-272ANK/2526/ISO/SPP/00258001 | S41: ANK/2526/ISO/SPP/00258 | T41: 27-11-2025 | U41: 5606640
A42: 83d8b82f-3094-49cf-9377-fc9d3deeb24d | B42: f7bbdf7e-4187-3925-a070-e1e08ff0b17d | C42: TDS Booked by Company | D42: Invoice Number Matched | E42: ledger | F42: 03-07-2025 | G42: ANK2526/SER00028 | H42: invoice | I42: Other | K42: 1874.88 | L42: PRI-INV1.6-company | M42: 19-Jun-26 10:16 AM | P42: 0 | R42: 2025-07-032ANK/2526/SLD/SVB/00028001 | S42: ANK/2526/SLD/SVB/00028 | T42: 03-07-2025 | U42: 530786.88
A43: 8578df19-94dc-4a2a-bedc-d18320afb9d5 | B43: ebc65537-cc7d-3651-8d18-ac57f49ee624 | C43: TDS Booked by Company | D43: Invoice Number Matched | E43: ledger | F43: 31-07-2025 | G43: ANK2526/SER00043 | H43: invoice | I43: Other | K43: 954616.32 | L43: PRI-INV1.6-company | M43: 19-Jun-26 10:16 AM | P43: 0 | R43: 2025-07-312ANK/2526/SLD/SVB/00043001 | S43: ANK/2526/SLD/SVB/00043 | T43: 31-07-2025 | U43: 3898412.8
A44: 8c1a1eab-34db-4f50-8dd1-f0029d456470 | B44: 272317a6-3e17-325e-9f62-8625bbbb07c3 | C44: TDS Booked by Party | D44: Multiple Based on Date | E44: ledger | F44: 21-01-2026 | G44: UTIBR72026012100004817 | H44: payment | I44: Receipt | K44: -604396 | L44: PRI-PAY5.2-company | M44: 19-Jun-26 10:16 AM | P44: 0 | R44: 2026-01-212ANK/2526/BDR/YB1/00780001 | S44: ANK/2526/BDR/YB1/00780 | T44: 21-01-2026 | U44: 219998.8
A45: 90df11c7-89a9-4ada-bf91-5bcbc9c0d2c8 | B45: d844a4c4-df8d-3fb4-a542-9b3262225213 | C45: TDS Booked by Company | D45: Invoice Number Matched | E45: ledger | F45: 22-01-2026 | G45: ANK2526/GIS00923 | H45: invoice | I45: Sale | K45: 3425587 | L45: PRI-INV1.6-company | M45: 19-Jun-26 10:16 AM | P45: 0 | R45: 2026-01-222ANK/2526/ISO/SPP/00306001 | S45: ANK/2526/ISO/SPP/00306 | T45: 22-01-2026 | U45: 6342412
A46: 95c1917c-7ae0-4de2-b5f4-d43cd30002ab | B46: 272317a6-3e17-325e-9f62-8625bbbb07c3 | C46: TDS Booked by Party | D46: Multiple Based on Date | E46: ledger | F46: 21-01-2026 | G46: UTIBR72026012100004816 | H46: payment | I46: Receipt | K46: -3402000 | L46: PRI-PAY5.2-company | M46: 19-Jun-26 10:16 AM | P46: 0 | R46: 2026-01-212ANK/2526/BDR/YB1/00781001 | S46: ANK/2526/BDR/YB1/00781 | T46: 21-01-2026 | U46: 2916825
A47: 9782919a-be50-4cfb-864f-ab41855d5646 | B47: ee43bf8d-99e2-31e1-ad3a-20c1cb03a504 | C47: TDS Booked by Company | D47: Invoice Number Matched | E47: ledger | F47: 23-01-2026 | G47: ANK2526/GIS00926 | H47: invoice | I47: Sale | K47: 1614198 | L47: PRI-INV1.6-company | M47: 19-Jun-26 10:16 AM | P47: 0 | R47: 2026-01-232ANK/2526/ISO/SPP/00308001 | S47: ANK/2526/ISO/SPP/00308 | T47: 23-01-2026 | U47: 7542783
A48: 9870be35-0fc7-442d-866b-dec7a75ddd57 | B48: b995ec42-83e7-45de-88e3-bb8b492089fb | C48: TDS Booked by Party | D48: TDS Booked by Party | E48: ledger | F48: 31-03-2026 | G48: TDS ANK2526/GIS00934 | H48: tds | I48: TDS | K48: -1307 | L48: Pre-P-2.3-party | M48: 19-Jun-26 10:16 AM | P48: 0 | R48: 2026-03-312ANK/2526/JVD/GJV/00605002 | S48: ANK/2526/JVD/GJV/00605 | T48: 31-03-2026 | U48: 6405798.54
A49: 9a50f4c0-c21a-4aad-960a-713d5c03e0b6 | B49: 1991f216-b6cf-4890-8202-8b48ceaa8400 | C49: TDS Booked by Party | D49: Payment Matched - Recommended | E49: ledger | F49: 25-09-2025 | G49: AXISCN1096036481 | H49: payment | I49: Receipt | K49: -1042715.5 | L49: SEC-PAY4.1-company | M49: 19-Jun-26 10:16 AM | P49: 0 | R49: 2025-09-252ANK/2526/BDR/YB1/00510001 | S49: ANK/2526/BDR/YB1/00510 | T49: 24-09-2025 | U49: 5542500.4800000004
A50: a9c1ac6e-0179-4c48-aa04-92b6534f0220 | C50: Payment not booked by Company | D50: Unmatched | E50: ledger | F50: 11-04-2025 | G50: UTIBN62025041155260266 | H50: payment | I50: Receipt | K50: -743400 | L50: Post-P-3.2-party | M50: 19-Jun-26 10:16 AM | P50: 0 | R50: 2025-04-112ANK/2526/BDR/YB1/00013001 | S50: ANK/2526/BDR/YB1/00013 | T50: 11-04-2025 | U50: 3842421.44
A51: af5535ab-0511-49c1-9292-8a5e1ca4c2b7 | B51: 0ea3ba69-0b5b-3e90-be9d-f02df002b4d7 | C51: Reconciled | D51: Date and Amount Matched | E51: ledger | F51: 25-07-2025 | G51: UTIBR72025072500076328 | H51: payment | I51: Receipt | K51: -3940384 | L51: PRI-PAY10.1-company | M51: 19-Jun-26 10:16 AM | P51: 0 | R51: 2025-07-252ANK/2526/BDR/YB1/00331001 | S51: ANK/2526/BDR/YB1/00331 | T51: 25-07-2025 | U51: -35188
A52: b7683659-9606-4d14-a006-f256e3cdadab | C52: Payment not booked by Company | D52: Unmatched | E52: ledger | F52: 11-04-2025 | G52: UTIBN62025041155258988 | H52: payment | I52: Receipt | K52: -938407.68 | L52: Post-P-3.2-party | M52: 19-Jun-26 10:16 AM | P52: 0 | R52: 2025-04-112ANK/2526/BDR/YB1/00012001 | S52: ANK/2526/BDR/YB1/00012 | T52: 11-04-2025 | U52: 4585821.4400000004
A53: b9dcae01-168d-49d8-a84f-53ecc4177168 | B53: b995ec42-83e7-45de-88e3-bb8b492089fb | C53: TDS Booked by Party | D53: TDS Booked by Party | E53: ledger | F53: 31-03-2026 | G53: TDS ANK2526/GIS00923 | H53: tds | I53: TDS | K53: -3262.46 | L53: Pre-P-2.3-party | M53: 19-Jun-26 10:16 AM | P53: 0 | R53: 2026-03-312ANK/2526/JVD/GJV/00603002 | S53: ANK/2526/JVD/GJV/00603 | T53: 31-03-2026 | U53: 6408642.54
A54: c0ac7d01-7b9c-40c6-abca-c0fdf6d3a1c1 | B54: 1395c5ae-873f-3f8b-ae53-ab71616636e5 | C54: TDS Booked by Party | D54: Multiple Based on Date | E54: ledger | F54: 08-10-2025 | G54: AXISCN1112025593 | H54: payment | I54: Receipt | K54: -101556 | L54: PRI-PAY5.2-company | M54: 19-Jun-26 10:16 AM | P54: 0 | R54: 2025-10-082ANK/2526/BDR/YB1/00548001 | S54: ANK/2526/BDR/YB1/00548 | T54: 08-10-2025 | U54: 4583554.88
A55: c3e2afb1-e631-4f35-9c16-28866885aed8 | B55: 30c02a2c-73e5-4135-843c-26b6c22ef8ec | C55: TDS Booked by Party | D55: Multiple Based on Invoice Number and Date Range | E55: ledger | F55: 30-05-2025 | G55: AXISCN0983739555 | H55: payment | I55: Receipt | K55: -624.96 | L55: PRI-PAY13.1-company | M55: 19-Jun-26 10:16 AM | P55: 0 | R55: 2025-05-302ANK/2526/BDR/YB1/00146001 | S55: ANK/2526/BDR/YB1/00146 | T55: 30-05-2025 | U55: 1919547.6
A56: c81bf6c0-b64d-488b-bee6-59e4ad1faaec | B56: 9286c9af-9bb2-3567-b2b7-fdf0c45b4115 | C56: TDS Booked by Party | D56: Multiple Based on Invoice Number | E56: ledger | F56: 14-01-2026 | G56: UTIBR72026011400000543 | H56: payment | I56: Receipt | K56: -232460 | L56: PRI-PAY5.1-company | M56: 19-Jun-26 10:16 AM | P56: 0 | R56: 2026-01-142ANK/2526/BDR/YB1/00763001 | S56: ANK/2526/BDR/YB1/00763 | T56: 14-01-2026 | U56: 824394.8
A57: d151a706-c557-4177-ace4-ad6f0c530f1d | B57: 7f4b4023-d438-3660-b28b-f92d110c9b33 | C57: TDS Booked by Company | D57: Invoice Number Matched | E57: ledger | F57: 19-07-2025 | G57: ANK2526/SER00034 | H57: invoice | I57: Other | K57: 571737.6 | L57: PRI-INV1.6-company | M57: 19-Jun-26 10:16 AM | P57: 0 | R57: 2025-07-192ANK/2526/SLD/SVB/00034001 | S57: ANK/2526/SLD/SVB/00034 | T57: 19-07-2025 | U57: 2684904.48
A58: d1d4383f-e165-4af5-886e-e48c124cc044 | B58: c873a8dd-4fbf-3f48-98a8-4474546891b4 | C58: TDS Booked by Company | D58: Invoice Number Matched | E58: ledger | F58: 31-08-2025 | G58: ANK2526/GIS00545 | H58: invoice | I58: Sale | K58: 3920000 | L58: PRI-INV1.6-company | M58: 19-Jun-26 10:16 AM | P58: 0 | R58: 2025-08-312ANK/2526/ISO/SPP/00174001 | S58: ANK/2526/ISO/SPP/00174 | T58: 31-08-2025 | U58: 3894560
A59: d7ed3f6c-6931-4855-85b0-e1359d7f45cc | B59: 2f904425-1935-38d4-b518-fd53aca1c625 | C59: TDS Booked by Company | D59: Invoice Number Matched | E59: ledger | F59: 26-06-2025 | G59: ANK2526/SER00025 | H59: invoice | I59: Other | K59: 518112 | L59: PRI-INV1.6-company | M59: 19-Jun-26 10:16 AM | P59: 0 | R59: 2025-06-262ANK/2526/SLD/SVB/00025001 | S59: ANK/2526/SLD/SVB/00025 | T59: 26-06-2025 | U59: 543426
A60: df1331d7-652e-411d-9518-195aafb24082 | B60: b995ec42-83e7-45de-88e3-bb8b492089fb | C60: TDS Booked by Party | D60: TDS Booked by Party | E60: ledger | F60: 31-03-2026 | G60: TDS DEDUCTED | H60: tds | I60: TDS | K60: -8458 | L60: Pre-P-2.3-party | M60: 19-Jun-26 10:16 AM | P60: 0 | R60: 2026-03-312ANK/2526/JVD/GJV/00609002 | S60: ANK/2526/JVD/GJV/00609 | T60: 31-03-2026 | U60: 3321405.8
A61: dfa78401-46da-4c19-8814-55f73efb5a9d | B61: 3a6a07f5-c8d0-3111-8209-202a899a258e | C61: TDS Booked by Party | D61: Date and Amount Matched - Recommended | E61: ledger | F61: 12-02-2026 | G61: UTIBR72026021200092359 | H61: payment | I61: Receipt | K61: -1668039 | L61: SEC-PAY3.1-company | M61: 19-Jun-26 10:16 AM | P61: 0 | R61: 2026-02-122ANK/2526/BDR/YB1/00839001 | S61: ANK/2526/BDR/YB1/00839 | T61: 12-02-2026 | U61: 6411905
A62: e052f7df-7a34-409c-820d-426b4b035581 | B62: 1395c5ae-873f-3f8b-ae53-ab71616636e5 | C62: TDS Booked by Party | D62: Multiple Based on Date | E62: ledger | F62: 08-10-2025 | G62: AXISCN1112157656 | H62: payment | I62: Receipt | K62: -817740 | L62: PRI-PAY5.2-company | M62: 19-Jun-26 10:16 AM | P62: 0 | R62: 2025-10-082ANK/2526/BDR/YB1/00574001 | S62: ANK/2526/BDR/YB1/00574 | T62: 30-12-1899 | U62: 3506922.88
A63: e13ee45f-1714-42a1-8a12-427f9993b620 | C63: Credit Note not booked by Company | D63: Unmatched | E63: ledger | F63: 13-12-2025 | G63: ANK2526/DBN00009 | H63: creditNote | I63: CN | K63: 215822 | L63: Post-P-3.4-party | M63: 19-Jun-26 10:16 AM | P63: 0 | R63: 2025-12-132ANK/2526/SDC/SD1/00008001 | S63: ANK/2526/SDC/SD1/00008 | T63: 13-12-2025 | U63: 1056854.8
A64: e1e53cff-685a-4cba-9676-0a1d0e3aa863 | C64: Closing Balance as per Party | D64: Closing Balance | E64: ledger | H64: closingBalance | I64: Closing | K64: 6242052.8 | M64: 19-Jun-26 10:16 AM | P64: 0 | R64: Closing | S64: Closing
A65: e2f002de-023e-4431-af63-6f673f3fc3cb | B65: 61a89e37-90ac-4087-8224-63e799811c06 | C65: TDS Booked by Party | D65: Payment Matched - Recommended | E65: ledger | F65: 18-10-2025 | G65: AXISCN1122982304 | H65: payment | I65: Receipt | K65: -3920000 | L65: SEC-PAY4.1-company | M65: 19-Jun-26 10:16 AM | P65: 0 | R65: 2025-10-182ANK/2526/BDR/YB1/00563001 | S65: ANK/2526/BDR/YB1/00563 | T65: 18-10-2025 | U65: 0
A66: e95e28a5-d3f0-4f82-9ff8-0b8b5698664d | B66: 60345083-22dc-399c-9caf-fadd92d4175f | C66: TDS Booked by Party | D66: Date and Amount Matched - Recommended | E66: ledger | F66: 10-10-2025 | G66: AXISCN1114230662 | H66: payment | I66: Receipt | K66: -2505646.1 | L66: SEC-PAY3.1-company | M66: 19-Jun-26 10:16 AM | P66: 0 | R66: 2025-10-102ANK/2526/BDR/YB1/00554001 | S66: ANK/2526/BDR/YB1/00554 | T66: 10-10-2025 | U66: 1001276.8
A67: ee94a38b-95f5-497b-9848-3949e3dc4007 | B67: cc26e4c9-ecf9-33ca-a270-2d0bb50578bc | C67: TDS Booked by Company | D67: Invoice Number Matched | E67: ledger | F67: 21-08-2025 | G67: ANK2526/SER00050 | H67: invoice | I67: Other | K67: 2505646.1 | L67: PRI-INV1.6-company | M67: 19-Jun-26 10:16 AM | P67: 0 | R67: 2025-08-212ANK/2526/SLD/SVB/00050001 | S67: ANK/2526/SLD/SVB/00050 | T67: 21-08-2025 | U67: 6585216
A68: f1bfb71a-578f-499f-b334-3d225c80979b | B68: 9286c9af-9bb2-3567-b2b7-fdf0c45b4115 | C68: TDS Booked by Party | D68: Multiple Based on Invoice Number | E68: ledger | F68: 14-01-2026 | G68: UTIBR72026011400000544 | H68: payment | I68: Receipt | K68: -3483648 | L68: PRI-PAY5.1-company | M68: 19-Jun-26 10:16 AM | P68: 0 | R68: 2026-01-142ANK/2526/BDR/YB1/00764001 | S68: ANK/2526/BDR/YB1/00764 | T68: 14-01-2026 | U68: 6318825
A69: f1fc1d2c-fb00-477d-8a75-09008d81a667 | B69: 16fef953-aaae-3c19-8966-746b3c3f8cfe | C69: Reconciled | D69: Invoice Number Matched | E69: ledger | F69: 30-04-2025 | G69: ANK2526/GIS00091 | H69: invoice | I69: Sale | K69: 3940384 | L69: PRI-INV1.5_A-company | M69: 19-Jun-26 10:16 AM | P69: 0 | R69: 2025-04-302ANK/2526/ISO/SPP/00030001 | S69: ANK/2526/ISO/SPP/00030 | T69: 30-04-2025 | U69: 7080396
A70: f3934940-c201-4051-9bf2-3ce66b5a27b5 | B70: 9b7b3f14-1268-37bd-8f97-a800357d4974 | C70: TDS Booked by Party | D70: Date and Amount Matched - Recommended | E70: ledger | F70: 30-01-2026 | G70: AXISCN1235469725 | H70: payment | I70: Receipt | K70: -834959 | L70: SEC-PAY3.1-company | M70: 19-Jun-26 10:16 AM | P70: 0 | R70: 2026-01-302ANK/2526/BDR/YB1/00814001 | S70: ANK/2526/BDR/YB1/00814 | T70: 30-01-2026 | U70: 8079944
A71: f8ecbfc7-0224-4122-8ad2-06231f412d43 | B71: e2732d49-1980-36ce-9173-91c7827c949c | C71: TDS Booked by Party | D71: Date and Amount Matched - Recommended | E71: ledger | F71: 21-05-2025 | G71: AXISCN0979676342 | H71: payment | I71: Receipt | K71: -1085246 | L71: SEC-PAY3.1-company | M71: 19-Jun-26 10:16 AM | P71: 0 | R71: 2025-05-212ANK/2526/BDR/YB1/00128001 | S71: ANK/2526/BDR/YB1/00128 | T71: 21-05-2025 | U71: 3736951.44
A72: fad17af0-baf0-4352-a9e7-25d790de30fe | B72: 80ae845c-e9fa-33be-bd86-890140fe421e | C72: TDS Booked by Company | D72: Invoice Number Matched | E72: ledger | F72: 26-11-2025 | G72: ANK2526/GIS00782 | H72: invoice | I72: Sale | K72: 120830 | L72: PRI-INV1.6-company | M72: 19-Jun-26 10:16 AM | P72: 0 | R72: 2025-11-262ANK/2526/ISO/SPP/00256001 | S72: ANK/2526/ISO/SPP/00256 | T72: 26-11-2025 | U72: 3897475
